Workbook
Name AuditFailsCommercial: [1]Audit!$G$12
Name AuditFailsStructural: [1]Audit!$G$11
Name AuditOK: [1]Audit!$G$13

Sheet APP
A2: =Study!CF1 -> القالب الموحّد الشامل لبنود دراسة الجدوى | Master Feasibility Template | B2: =Study!CG1 -> 0 | C2: =Study!CH1 -> 0 | D2: =Study!CI1 -> 0 | E2: =Study!CJ1 -> 0 | F2: =Study!CK1 -> 0
A3: =Study!CF2 -> قالب ثابت يشمل كل المكوّنات والأقسام (حتى الفارغة) | مراجع حية داخل ورقة Study | B3: =Study!CG2 -> 0 | C3: =Study!CH2 -> 0 | D3: =Study!CI2 -> 0 | E3: =Study!CJ2 -> 0 | F3: =Study!CK2 -> 0
A4: =Study!CF3 -> 0 | B4: =Study!CG3 -> 0 | C4: =Study!CH3 -> 0 | D4: =Study!CI3 -> 0 | E4: =Study!CJ3 -> 0 | F4: =Study!CK3 -> 0
A5: =Study!CF4 -> # | B5: =Study!CG4 -> اسم البند | C5: =Study!CH4 -> الناتج | D5: =Study!CI4 -> الفئة | E5: =Study!CJ4 -> مصدر الخلية | F5: =Study!CK4 -> ملاحظة / الوحدة
A6: =Study!CF5 -> ▌ معلومات المشروع | B6: =Study!CG5 -> 0 | C6: =Study!CH5 -> 0 | D6: =Study!CI5 -> 0 | E6: =Study!CJ5 -> 0 | F6: =Study!CK5 -> 0
A7: =Study!CF6 -> 1 | B7: =Study!CG6 -> اسم المشروع | C7: درة الغدير | D7: =Study!CI6 -> معلومات المشروع | E7: =Study!CJ6 -> F2 | F7: =Study!CK6 -> هوية المشروع
A8: =Study!CF7 -> 2 | B8: =Study!CG7 -> موقع المشروع | C8: الرياض | D8: =Study!CI7 -> معلومات المشروع | E8: =Study!CJ7 -> F3 | F8: =Study!CK7 -> 0
A9: =Study!CF8 -> ▌ ملخص الدراسة | B9: =Study!CG8 -> 0 | C9: =Study!CH8 -> 0 | D9: =Study!CI8 -> 0 | E9: =Study!CJ8 -> 0 | F9: =Study!CK8 -> 0
A10: =Study!CF9 -> 3 | B10: =Study!CG9 -> إجمالي الإيرادات | C10: =Study!CH9 -> 3.1318259e+08 | D10: =Study!CI9 -> ملخص الدراسة | E10: =Study!CJ9 -> C17 | F10: =Study!CK9 -> ريال سعودي
A11: =Study!CF10 -> 4 | B11: =Study!CG10 -> إجمالي تكلفة الأرض | C11: =Study!CH10 -> 91847824 | D11: =Study!CI10 -> ملخص الدراسة | E11: =Study!CJ10 -> C18 | F11: =Study!CK10 -> ريال سعودي
A12: =Study!CF11 -> 5 | B12: =Study!CG11 -> إجمالي تكلفة البناء | C12: =Study!CH11 -> 78265608 | D12: =Study!CI11 -> ملخص الدراسة | E12: =Study!CJ11 -> C19 | F12: =Study!CK11 -> ريال سعودي
A13: =Study!CF12 -> 6 | B13: =Study!CG12 -> إجمالي التكاليف الأخرى | C13: =Study!CH12 -> 21170058 | D13: =Study!CI12 -> ملخص الدراسة | E13: =Study!CJ12 -> C20 | F13: =Study!CK12 -> ريال سعودي
A14: =Study!CF13 -> 7 | B14: =Study!CG13 -> إجمالي رسوم الصندوق | C14: =Study!CH13 -> 22314657 | D14: =Study!CI13 -> ملخص الدراسة | E14: =Study!CJ13 -> C21 | F14: =Study!CK13 -> ريال سعودي
A15: =Study!CF14 -> 8 | B15: =Study!CG14 -> فوائد التمويل | C15: =Study!CH14 -> 7141903.3 | D15: =Study!CI14 -> ملخص الدراسة | E15: =Study!CJ14 -> C22 | F15: =Study!CK14 -> ريال سعودي
A16: =Study!CF15 -> 9 | B16: =Study!CG15 -> التمويل البنكي | C16: =Study!CH15 -> 0 | D16: =Study!CI15 -> ملخص الدراسة | E16: =Study!CJ15 -> C23 | F16: =Study!CK15 -> ريال سعودي
A17: =Study!CF16 -> 10 | B17: =Study!CG16 -> إجمالي التكاليف الرأسمالية (CapEx) | C17: =Study!CH16 -> 2.2074005e+08 | D17: =Study!CI16 -> ملخص الدراسة | E17: =Study!CJ16 -> C24 | F17: =Study!CK16 -> ريال سعودي
A18: =Study!CF17 -> 11 | B18: =Study!CG17 -> إجمالي التكاليف التشغيلية (OpEx) | C18: =Study!CH17 -> 6529315.6 | D18: =Study!CI17 -> ملخص الدراسة | E18: =Study!CJ17 -> C25 | F18: =Study!CK17 -> ريال سعودي
A19: =Study!CF18 -> 12 | B19: =Study!CG18 -> صافي الدخل | C19: =Study!CH18 -> 85913221 | D19: =Study!CI18 -> ملخص الدراسة | E19: =Study!CJ18 -> C26 | F19: =Study!CK18 -> ريال سعودي
A20: =Study!CF19 -> 13 | B20: =Study!CG19 -> مدة المشروع المتوقعة (سنوات) | C20: =Study!CH19 -> 5 | D20: =Study!CI19 -> ملخص الدراسة | E20: =Study!CJ19 -> C27 | F20: =Study!CK19 -> سنة
... A653: =Study!CF652 -> 576 | B653: =Study!CG652 -> صافي الدخل (تدفقات) | C653: =Study!CH652 -> 85913221 | D653: =Study!CI652 -> التدفقات النقدية | E653: =Study!CJ652 -> C221 | F653: =Study!CK652 -> ريال سعودي
A654: =Study!CF653 -> 577 | B654: =Study!CG653 -> الاطار الزمني (ربع سنوي) | C654: =Study!CH653 -> Q1 | D654: =Study!CI653 -> Q2 | E654: =Study!CJ653 -> Q3 | F654: =Study!CK653 -> Q4 | G654: =Study!CL653 -> Q5 | H654: =Study!CM653 -> Q6 | ... Z654: =Study!DE653 -> Q24
A655: =Study!CF654 -> 578 | B655: =Study!CG654 -> التاريخ | C655: =Study!CH654 -> 46388 | D655: =Study!CI654 -> 46478 | E655: =Study!CJ654 -> 46569 | F655: =Study!CK654 -> 46661 | G655: =Study!CL654 -> 46753 | H655: =Study!CM654 -> 46844 | ... Z655: =Study!DE654 -> 48488
A656: =Study!CF655 -> 579 | B656: =Study!CG655 -> الحفر والمسح والاختبار (Excavation, surveying, and testing) | C656: =Study!CH655 -> -89728000 | D656: =Study!CI655 -> 0 | E656: =Study!CJ655 -> 0 | F656: =Study!CK655 -> 0 | G656: =Study!CL655 -> 0 | H656: =Study!CM655 -> 0 | ... Z656: =Study!DE655 -> 0
A657: =Study!CF656 -> 580 | B657: =Study!CG656 -> أثاث الوحدات الفندقية (Apartment furniture) | C657: =Study!CH656 -> 0 | D657: =Study!CI656 -> 0 | E657: =Study!CJ656 -> -945120 | F657: =Study!CK656 -> -945120 | G657: =Study!CL656 -> -945120 | H657: =Study!CM656 -> 0 | ... Z657: =Study!DE656 -> 0
A658: =Study!CF657 -> 581 | B658: =Study!CG657 -> رسوم الماء وصرف الصحي (Water and sewer fees) | C658: =Study!CH657 -> -652213.4 | D658: =Study!CI657 -> -652213.4 | E658: =Study!CJ657 -> -652213.4 | F658: =Study!CK657 -> -652213.4 | G658: =Study!CL657 -> -652213.4 | H658: =Study!CM657 -> -652213.4 | ... Z658: =Study!DE657 -> 0
A659: =Study!CF658 -> 582 | B659: =Study!CG658 -> الرخصة (License) | C659: =Study!CH658 -> 0 | D659: =Study!CI658 -> 0 | E659: =Study!CJ658 -> 0 | F659: =Study!CK658 -> 0 | G659: =Study!CL658 -> 0 | H659: =Study!CM658 -> -5478592.6 | ... Z659: =Study!DE658 -> 0
A660: =Study!CF659 -> 583 | B660: =Study!CG659 -> الايراد (Revenue) | C660: =Study!CH659 -> 0 | D660: =Study!CI659 -> 0 | E660: =Study!CJ659 -> 0 | F660: =Study!CK659 -> 0 | G660: =Study!CL659 -> 0 | H660: =Study!CM659 -> 0 | ... Z660: =Study!DE659 -> 0
A661: =Study!CF660 -> 584 | B661: =Study!CG660 -> ضريبة التصرفات العقارية + السعي + ضريبة السعي - (RETT + Commission + Commission tax) | C661: =Study!CH660 -> 0 | D661: =Study!CI660 -> 0 | E661: =Study!CJ660 -> 0 | F661: =Study!CK660 -> 0 | G661: =Study!CL660 -> 0 | H661: =Study!CM660 -> 0 | ... Z661: =Study!DE660 -> 0
A662: =Study!CF661 -> 585 | B662: =Study!CG661 -> اجمالي التكاليف | C662: =Study!CH661 -> -97189235 | D662: =Study!CI661 -> -1316551.4 | E662: =Study!CJ661 -> -1719623.4 | F662: =Study!CK661 -> -2261671.4 | G662: =Study!CL661 -> -2266273.2 | H662: =Study!CM661 -> -7827467.3 | ... Z662: =Study!DE661 -> 0
A663: =Study!CF662 -> 586 | B663: =Study!CG662 -> البيع على الخارطة | C663: =Study!CH662 -> 0 | D663: =Study!CI662 -> 0 | E663: =Study!CJ662 -> 0 | F663: =Study!CK662 -> 0 | G663: =Study!CL662 -> 1304347.8 | H663: =Study!CM662 -> 2305043.5 | ... Z663: =Study!DE662 -> 0
A664: =Study!CF663 -> 586 | B664: =Study!CG663 -> اجمالي الايراد | C664: =Study!CH663 -> 0 | D664: =Study!CI663 -> 0 | E664: =Study!CJ663 -> 0 | F664: =Study!CK663 -> 0 | G664: =Study!CL663 -> 0 | H664: =Study!CM663 -> 0 | ... Z664: =Study!DE663 -> 0

Sheet Cover Page
H1: Legal Disclaimer and Warning: This financial model is confidential property of Rasf Investment, and all rights are fully reserved. It has been shared with you for a specific and authorized purpose only. Any copying, sharing, modification, or use of this file for any other purpose without prior written consent from Rasf Investment is strictly prohibited. If such unauthorized use occurs, legal action will be taken against you in a court of law.
A16: تفاصيل الدراسة (Study Details) | I16: درة الغدير - مشروع مختلط (Mix Use Development - RASF - Alghadeer)
D19: ------------------------------------ | L19: ------------------------------------
A20: التاريخ (Date) | I20: 46147
D23: ------------------------------------ | L23: ------------------------------------
A24: محتويات الدراسة (Study Contents) | I24: Study

Sheet Study
CF1: القالب الموحّد الشامل لبنود دراسة الجدوى | Master Feasibility Template
AE2: توزيع تكاليف المشروع على مكونات البيع المباشر و التأجير السنوي و اليومي | BH2: جدول المؤشرات العامة للمشروع | General Project Indicators Table | BL2: الحدود المرجعية أو المثلى للمؤشرات (Reference Ranges for Indicators) | BN2: سعر المتر بناءً على فترة الاسترداد - (التأجير السنوي) | BQ2: سعر المتر بناءً على فترة الاسترداد - (التأجير اليومي) | BV2: اسم المشروع | BW2: برج جدة | CA2: حالة المشروع | CB2: تاريخ الانتهاء المتوقع | CF2: قالب ثابت يشمل كل المكوّنات والأقسام (حتى الفارغة) | مراجع حية داخل ورقة Study
AE3: المكون | AF3: توزيع تكاليف الأرض | AG3: جزء من تكاليف البناء | AH3: نسبة توزيع تكاليف اللاندسكيب | AI3: توزيع تكاليف اللاندسكيب | AJ3: توزيع تكاليف البوديم و القبو | AK3: توزيع تكاليف الحفر والمسح و الاختبار | AL3: توزيع تكاليف المساحات الحركية والخدمية | AM3: نسب التكاليف السابقة من التكاليف الموجودة بالجدول | AN3: نسب التكاليف السابقة من التكاليف الكلية | AO3: نسب المكون من البيع المباشر أو المخارجة من الإجمالي | AP3: توزيع التكاليف الأخرى | AQ3: توزيع تكاليف أخرى إضافية | AR3: توزيع تكاليف التمويل | AS3: توزيع تكاليف الصندوق | AT3: توزيع التكاليف التشغيلية | AU3: إجمالي تكاليف كل مكون | AV3: توزيع التكلفة على الأمتار البيعية | AW3: نسبة تكاليف كل مكون من إجمالي المشروع | AX3: إجمالي إيراد كل مكون | AY3: صافي العائد لكل م² بيعي | AZ3: صافي دخل كل مكون | BA3: العائد النسبي للمكون | BB3: هامش الربح من إجمالي الإرادات | BC3: نسبة صافي دخل كل مكون من إجمالي صافي دخل المشروع | BD3: نسبة صافي دخل كل مكون | BN3: المكون (Component) | BO3: سعر المتر | BP3: فترة الأسترداد - بالسنوات | BQ3: المكون (Component) | BR3: سعر المتر | BS3: فترة الأسترداد - بالسنوات | BV3: اسم الصندوق (fund Name) | BW3: إتقان | CA3: مرحلة توقيع العقود | CB3: ?
AE4: سكني | AF4: =I45 -> 15362564 | AG4: =J61*AO4 -> 7800408 | AH4: 0 | AI4: =($J$73*AH4)*AO4 -> 0 | AL4: =(((D61-F61)/$I$59)*$J$71)*AO4 -> 0 | AM4: =SUM(AF4:AG4,AI4:AL4)/$AM$14 -> 0.14502019 | AN4: =SUM(AF4:AG4,AI4:AL4)/$AN$14 -> 0.11361589 | AO4: =D129 -> 1 | AP4: =(AN4*SUM($C$86,$C$88:$C$89,$C$96:$C$97))+((H147+X147)/($H$157+$X$157))*$C$99+(SUM($D$93:$D$95)*G61*AO4) -> 749188.5 | AQ4: =(($A$92+$C$98)*AM4)+((C90+C101)*15%) -> 887297.5 | AR4: =AM4*$C$119 -> 1035720.2 | AS4: =AN4*$C$107 -> 2535299.6 | AT4: =SUM(I147,Y147) -> 123565.55 | AU4: =SUM(AF4:AG4,AI4:AL4,AP4:AT4) -> 28494043 | AV4: =IFERROR((AU4-AT4)/E129, "0") -> 9413.5425 | AW4: =(AU4-AT4)/($C$23) -> 0.12852438 | AX4: =SUM(J129,H147,O129,X147) -> 31818130 | AY4: =IFERROR(AZ4/E129, "0.00") -> 1102.9575 | AZ4: =AX4-AU4 -> 3324086.8 | BA4: =IFERROR(BD4/AW4, "0.00") -> 0.91163333 | BB4: =IFERROR(AZ4/AX4, "0.00%") -> 0.10447147 | BC4: =AZ4/$C$25 -> 0.038691214 | BD4: =IFERROR(AZ4/(AU4-AT4), "0.00%") -> 0.11716711 | BE4: سكني | BN4: سكني (Apartments) | BO4: =IFERROR((AU4-AT4) / (C147 * D147 * G147 * (1 - $I$158) * BP4), 0) -> 0 | BQ4: سكني (Apartments) | BR4: =IFERROR((AU4-AT4) / ((R147 * S147 * (1 - $Y$158) * 365 * BS4) * (1 + W147)), 0) -> 0 | BV4: =B19 -> إجمالي تكلفة البناء (Total Construction Cost) | BW4: =J76 -> 78265608 | CF4: # | CG4: اسم البند | CH4: الناتج | CI4: الفئة | CJ4: مصدر الخلية | CK4: ملاحظة / الوحدة
AE5: فلل | AF5: =I46 -> 27351260 | AG5: =J62*AO5 -> 0 | AH5: 0 | AI5: =($J$73*AH5)*AO5 -> 0 | AJ5: =((K62/$L$76)*($J$74+$J$75))*AO5 -> 0 | AK5: =((K62/$L$76)*$C$87)*AO5 -> 0 | AL5: =(((D62-F62)/$I$59)*$J$71)*AO5 -> 0 | AM5: =SUM(AF5:AG5,AI5:AL5)/$AM$14 -> 0.17124249 | AN5: =SUM(AF5:AG5,AI5:AL5)/$AN$14 -> 0.13415971 | AO5: =D130 -> 0 | AP5: =(AN5*SUM($C$86,$C$88:$C$89,$C$96:$C$97))+((H148+X148)/($H$157+$X$157))*$C$99+(SUM($D$93:$D$95)*G62*AO5) -> 456192.67 | AQ5: =(($A$92+$C$98)*AM5)+((C90+C101)*15%) -> 888528.77 | AR5: =AM5*$C$119 -> 1222997.3 | AS5: =AN5*$C$107 -> 2993728 | AT5: =SUM(I148,Y148) -> 0 | AU5: =SUM(AF5:AG5,AI5:AL5,AP5:AT5) -> 32912707 | AV5: =IFERROR((AU5-AT5)/E130, "0") -> 9854.1038 | AW5: =(AU5-AT5)/($C$23) -> 0.14910165 | AX5: =SUM(J130,H148,O130,X148) -> 0 | AY5: =IFERROR(AZ5/E130, "0.00") -> -9854.1038 | AZ5: =AX5-AU5 -> -32912707 | BA5: =IFERROR(BD5/AW5, "0.00") -> -6.7068337 | BB5: =IFERROR(AZ5/AX5, "0.00%") -> 0.00% | BC5: =AZ5/$C$25 -> -0.38309246 | BD5: =IFERROR(AZ5/(AU5-AT5), "0.00%") -> -1 | BE5: فلل | BH5: مؤشرات التكاليف والكفاءة (Costs & Efficiency Indicators) | BN5: فلل (Villas) | BO5: =IFERROR((AU5-AT5) / (C148 * D148 * G148 * (1 - $I$158) * BP5), 0) -> 0 | BQ5: فلل (Villas) | BR5: =IFERROR((AU5-AT5) / ((R148 * S148 * (1 - $Y$158) * 365 * BS5) * (1 + W148)), 0) -> 0 | BV5: =B23 -> إجمالي التكاليف الرأسمالية للمشروع (Total Capital Expenditures) | BW5: =C23 -> 2.2074005e+08 | CF5: ▌ معلومات المشروع
AE6: تاون هاوس | AF6: =((F63/$J$59)*$I$49)*AO6 -> 0 | AG6: =J63*AO6 -> 0 | AH6: 0 | AI6: =($J$73*AH6)*AO6 -> 0 | AJ6: =((K63/$L$76)*($J$74+$J$75))*AO6 -> 0 | AK6: =((K63/$L$76)*$C$87)*AO6 -> 0 | AL6: =(((D63-F63)/$I$59)*$J$71)*AO6 -> 0 | AM6: =SUM(AF6:AG6,AI6:AL6)/$AM$14 -> 0 | AN6: =SUM(AF6:AG6,AI6:AL6)/$AN$14 -> 0 | AO6: =D131 -> 1 | AP6: =(AN6*SUM($C$86,$C$88:$C$90,$C$96:$C$97,$C$101))+((H149+X149)/($H$157+$X$157))*$C$99+(SUM($D$93:$D$95)*G63*AO6) -> 0 | AQ6: =(($A$92+$C$98)*AM6) -> 0 | AR6: =AM6*$C$119 -> 0 | AS6: =AN6*$C$107 -> 0 | AT6: =SUM(I149,Y149) -> 0 | AU6: =SUM(AF6:AG6,AI6:AL6,AP6:AT6) -> 0 | AV6: =IFERROR((AU6-AT6)/E131, "0") -> 0 | AW6: =(AU6-AT6)/($C$23) -> 0 | AX6: =SUM(J131,H149,O131,X149) -> 0 | AY6: =IFERROR(AZ6/E131, "0.00") -> 0.00 | AZ6: =AX6-AU6 -> 0 | BA6: =IFERROR(BD6/AW6, "0.00") -> 0.00 | BB6: =IFERROR(AZ6/AX6, "0.00%") -> 0.00% | BC6: =AZ6/$C$25 -> 0 | BD6: =IFERROR(AZ6/(AU6-AT6), "0.00%") -> 0.00% | BE6: تاون هاوس | BH6: التكلفة لكل م² من إجمالي المساحات التطويرية (Cost per m² of Total Built-Up Area) | BI6: =C23/G59 -> 6941.5896 | BL6: - | BN6: تاون هاوس (Townhouse) | BO6: =IFERROR((AU6-AT6) / (C149 * D149 * G149 * (1 - $I$158) * BP6), 0) -> 0 | BQ6: تاون هاوس (Townhouse) | BR6: =IFERROR((AU6-AT6) / ((R149 * S149 * (1 - $Y$158) * 365 * BS6) * (1 + W149)), 0) -> 0 | BV6: =B17 -> إجمالي الإيرادات (Total Revenue) | BW6: =C17 -> 3.1318259e+08 | CF6: 1 | CG6: اسم المشروع | CH6: =F2 -> 0 | CI6: معلومات المشروع | CJ6: F2 | CK6: هوية المشروع
AE7: أدوار | AF7: =((F64/$J$59)*$I$49)*AO7 -> 0 | AG7: =J64*AO7 -> 0 | AH7: 0 | AI7: =($J$73*AH7)*AO7 -> 0 | AJ7: =((K64/$L$76)*($J$74+$J$75))*AO7 -> 0 | AK7: =((K64/$L$76)*$C$87)*AO7 -> 0 | AL7: =(((D64-F64)/$I$59)*$J$71)*AO7 -> 0 | AM7: =SUM(AF7:AG7,AI7:AL7)/$AM$14 -> 0 | AN7: =SUM(AF7:AG7,AI7:AL7)/$AN$14 -> 0 | AO7: =D132 -> 1 | AP7: =(AN7*SUM($C$86,$C$88:$C$90,$C$96:$C$97,$C$101))+((H150+X150)/($H$157+$X$157))*$C$99+(SUM($D$93:$D$95)*G64*AO7) -> 0 | AQ7: =(($A$92+$C$98)*AM7) -> 0 | AR7: =AM7*$C$119 -> 0 | AS7: =AN7*$C$107 -> 0 | AT7: =SUM(I150,Y150) -> 0 | AU7: =SUM(AF7:AG7,AI7:AL7,AP7:AT7) -> 0 | AV7: =IFERROR((AU7-AT7)/E132, "0") -> 0 | AW7: =(AU7-AT7)/($C$23) -> 0 | AX7: =SUM(J132,H150,O132,X150) -> 0 | AY7: =IFERROR(AZ7/E132, "0.00") -> 0.00 | AZ7: =AX7-AU7 -> 0 | BA7: =IFERROR(BD7/AW7, "0.00") -> 0.00 | BB7: =IFERROR(AZ7/AX7, "0.00%") -> 0.00% | BC7: =AZ7/$C$25 -> 0 | BD7: =IFERROR(AZ7/(AU7-AT7), "0.00%") -> 0.00% | BE7: أدوار | BH7: التكلفة لكل م² من إجمالي المساحات القابلة للبيع (Cost per m² of Saleable Area) | BI7: =C23/J59 -> 22250.24 | BL7: - | BN7: أدوار (Floors) | BO7: =IFERROR((AU7-AT7) / (C150 * D150 * G150 * (1 - $I$158) * BP7), 0) -> 0 | BQ7: أدوار (Floors) | BR7: =IFERROR((AU7-AT7) / ((R150 * S150 * (1 - $Y$158) * 365 * BS7) * (1 + W150)), 0) -> 0 | BV7: =B34 -> العائد على الملكية السنوي (ROE Annually) | BW7: =C32 -> 0.7924872 | CF7: 2 | CG7: موقع المشروع | CH7: =F3 -> 0 | CI7: معلومات المشروع | CJ7: F3
AE8: أستوديوهات | AF8: =((F65/$J$59)*$I$49)*AO8 -> 0 | AG8: =J65*AO8 -> 0 | AH8: 0 | AI8: =($J$73*AH8)*AO8 -> 0 | AJ8: =((K65/$L$76)*($J$74+$J$75))*AO8 -> 0 | AK8: =((K65/$L$76)*$C$87)*AO8 -> 0 | AL8: =(((D65-F65)/$I$59)*$J$71)*AO8 -> 0 | AM8: =SUM(AF8:AG8,AI8:AL8)/$AM$14 -> 0 | AN8: =SUM(AF8:AG8,AI8:AL8)/$AN$14 -> 0 | AO8: =D133 -> 1 | AP8: =(AN8*SUM($C$86,$C$88:$C$90,$C$96:$C$97,$C$101))+((H151+X151)/($H$157+$X$157))*$C$99+(SUM($D$93:$D$95)*G65*AO8) -> 0 | AQ8: =(($A$92+$C$98)*AM8) -> 0 | AR8: =AM8*$C$119 -> 0 | AS8: =AN8*$C$107 -> 0 | AT8: =SUM(I151,Y151) -> 0 | AU8: =SUM(AF8:AG8,AI8:AL8,AP8:AT8) -> 0 | AV8: =IFERROR((AU8-AT8)/E133, "0") -> 0 | AW8: =(AU8-AT8)/($C$23) -> 0 | AX8: =SUM(J133,H151,O133,X151) -> 0 | AY8: =IFERROR(AZ8/E133, "0.00") -> 0.00 | AZ8: =AX8-AU8 -> 0 | BA8: =IFERROR(BD8/AW8, "0.00") -> 0.00 | BB8: =IFERROR(AZ8/AX8, "0.00%") -> 0.00% | BC8: =AZ8/$C$25 -> 0 | BD8: =IFERROR(AZ8/(AU8-AT8), "0.00%") -> 0.00% | BE8: أستوديوهات | BH8: إجمالي التكاليف الصلبة (Total Hard Costs) | BI8: =-SUM(C196:C198,C202:C203) -> 87785008 | BJ8: =BI8/($C$23+$C$24) -> 0.38625975 | BL8: - | BN8: أستوديوهات (Studios) | BO8: =IFERROR((AU8-AT8) / (C151 * D151 * G151 * (1 - $I$158) * BP8), 0) -> 0 | BQ8: أستوديوهات (Studios) | BR8: =IFERROR((AU8-AT8) / ((R151 * S151 * (1 - $Y$158) * 365 * BS8) * (1 + W151)), 0) -> 0 | CA8: - | CF8: ▌ ملخص الدراسة
AE9: مكتبي | AF9: =((F66/$J$59)*$I$49)*AO9 -> 0 | AG9: =J66*AO9 -> 0 | AI9: =($J$73*AH9)*AO9 -> 0 | AJ9: =((K66/$L$76)*($J$74+$J$75))*AO9 -> 0 | AK9: =((K66/$L$76)*$C$87)*AO9 -> 0 | AL9: =(((D66-F66)/$I$59)*$J$71)*AO9 -> 0 | AM9: =SUM(AF9:AG9,AI9:AL9)/$AM$14 -> 0 | AN9: =SUM(AF9:AG9,AI9:AL9)/$AN$14 -> 0 | AO9: =D134 -> 1 | AP9: =(AN9*SUM($C$86,$C$88:$C$90,$C$96:$C$97,$C$101))+((H152+X152)/($H$157+$X$157))*$C$99+(SUM($D$93:$D$95)*G66*AO9) -> 0 | AQ9: =(($A$92+$C$98)*AM9) -> 0 | AR9: =AM9*$C$119 -> 0 | AS9: =AN9*$C$107 -> 0 | AT9: =SUM(I152,Y152) -> 0 | AU9: =SUM(AF9:AG9,AI9:AL9,AP9:AT9) -> 0 | AV9: =IFERROR((AU9-AT9)/E134, "0") -> 0 | AW9: =(AU9-AT9)/($C$23) -> 0 | AX9: =SUM(J134,H152,O134,X152) -> 0 | AY9: =IFERROR(AZ9/E134, "0.00") -> 0.00 | AZ9: =AX9-AU9 -> 0 | BA9: =IFERROR(BD9/AW9, "0.00") -> 0.00 | BB9: =IFERROR(AZ9/AX9, "0.00%") -> 0.00% | BC9: =AZ9/$C$25 -> 0 | BD9: =IFERROR(AZ9/(AU9-AT9), "0.00%") -> 0.00% | BE9: مكتبي | BH9: إجمالي التكاليف اللينة (Total Soft Costs) | BI9: =-SUM(C199:C201,C204:C207,C209:C212,C214:C216) -> 32791331 | BJ9: =BI9/($C$23+$C$24) -> 0.14428399 | BL9: - | BN9: مكتبي (Office) | BO9: =IFERROR((AU9-AT9) / (C152 * D152 * G152 * (1 - $I$158) * BP9), 0) -> 0 | BQ9: مكتبي (Office) | BR9: =IFERROR((AU9-AT9) / ((R152 * S152 * (1 - $Y$158) * 365 * BS9) * (1 + W152)), 0) -> 0 | BV9: اشتراكات رصف | BW9: نسبة الحصة | BX9: مبلغ الاشتراك | BY9: الآلية | BZ9: صافي الربح | CA9: مبلغ الاشتراك + صافي الربح | CB9: ملاحظات | CF9: 3 | CG9: إجمالي الإيرادات | CH9: =C17 -> 3.1318259e+08 | CI9: ملخص الدراسة | CJ9: C17 | CK9: ريال سعودي
AE10: تجاري | AF10: =((F67/$J$59)*$I$49)*AO10 -> 0 | AG10: =J67*AO10 -> 0 | AI10: =($J$73*AH10)*AO10 -> 0 | AJ10: =((K67/$L$76)*($J$74+$J$75))*AO10 -> 0 | AK10: =((K67/$L$76)*$C$87)*AO10 -> 0 | AL10: =(((D67-F67)/$I$59)*$J$71)*AO10 -> 0 | AM10: =SUM(AF10:AG10,AI10:AL10)/$AM$14 -> 0 | AN10: =SUM(AF10:AG10,AI10:AL10)/$AN$14 -> 0 | AO10: =D135 -> 1 | AP10: =(AN10*SUM($C$86,$C$88:$C$90,$C$96:$C$97,$C$101))+((H153+X153)/($H$157+$X$157))*$C$99+(SUM($D$93:$D$95)*G67*AO10) -> 0 | AQ10: =(($A$92+$C$98)*AM10) -> 0 | AR10: =AM10*$C$119 -> 0 | AS10: =AN10*$C$107 -> 0 | AT10: =SUM(I153,Y153) -> 0 | AU10: =SUM(AF10:AG10,AI10:AL10,AP10:AT10) -> 0 | AV10: =IFERROR((AU10-AT10)/E135, "0") -> 0 | AW10: =(AU10-AT10)/($C$23) -> 0 | AX10: =SUM(J135,H153,O135,X153) -> 0 | AY10: =IFERROR(AZ10/E135, "0.00") -> 0.00 | AZ10: =AX10-AU10 -> 0 | BA10: =IFERROR(BD10/AW10, "0.00") -> 0.00 | BB10: =IFERROR(AZ10/AX10, "0.00%") -> 0.00% | BC10: =AZ10/$C$25 -> 0 | BD10: =IFERROR(AZ10/(AU10-AT10), "0.00%") -> 0.00% | BE10: تجاري | BH10: إجمالي التكاليف التي لا تندرج كصلبة أو لينة (Total costs that do not fall under hard or soft costs) | BI10: =-SUM(E192:E193,C194:C195,C208,C213) -> 1.0669303e+08 | BJ10: =BI10/($C$23+$C$24) -> 0.46945626 | BL10: - | BN10: تجاري (Retail) | BO10: =IFERROR((AU10-AT10) / (C153 * D153 * G153 * (1 - $I$158) * BP10), 0) -> 0 | BQ10: تجاري (Retail) | BR10: =IFERROR((AU10-AT10) / ((R153 * S153 * (1 - $Y$158) * 365 * BS10) * (1 + W153)), 0) -> 0 | BV10: الحصة العينية من التطوير | BW10: 1 | BX10: =H22*BW10 -> 0 | BY10: استثمار عيني | BZ10: =BX10*$BW$7 -> 0 | CA10: =BZ10+BX10 -> 0 | CB10: - | CF10: 4 | CG10: إجمالي تكلفة الأرض | CH10: =C18 -> 91847824 | CI10: ملخص الدراسة | CJ10: C18 | CK10: ريال سعودي
AE11: فندقي | AF11: =I44 -> 49134000 | AG11: =J68*AO11 -> 36900000 | AH11: 1 | AI11: =($J$73*AH11)*AO11 -> 6162000 | AJ11: =J74 -> 14176800 | AK11: =C87 -> 2835360 | AL11: =(((D68-F68)/$I$59)*$J$71)*AO11 -> 0 | AM11: =SUM(AF11:AG11,AI11:AL11)/$AM$14 -> 0.68373732 | AN11: =SUM(AF11:AG11,AI11:AL11)/$AN$14 -> 0.53567315 | AO11: =D136 -> 1 | AP11: =(AN11*SUM($C$86,$C$88:$C$89,$C$96:$C$97))+((H154+X154)/($H$157+$X$157))*$C$99+((SUM($D$94:$D$95)*G68*AO11)+(D93*G68/2*AO11)) -> 4250586.9 | AQ11: =(((($C$98)*AM11))+C91)+((C90+C101)*70%) -> 10291049 | AR11: =AM11*$C$119 -> 4883185.8 | AS11: =AN11*$C$107 -> 11953363 | AT11: =SUM(I154,Y154) -> 6405750 | AU11: =SUM(AF11:AG11,AI11:AL11,AP11:AT11) -> 1.4699209e+08 | AV11: =IFERROR((AU11-AT11)/E136, "0") -> 39413.049 | AW11: =(AU11-AT11)/($C$23) -> 0.63688644 | AX11: =SUM(J136,H154,O136,X154) -> 2.348775e+08 | AY11: =IFERROR(AZ11/E136, "0.00") -> 24638.465 | AZ11: =AX11-AU11 -> 87885405 | BA11: =IFERROR(BD11/AW11, "0.00") -> 0.98154817 | BB11: =IFERROR(AZ11/AX11, "0.00%") -> 0.3741755 | BC11: =AZ11/$C$25 -> 1.0229555 | BD11: =IFERROR(AZ11/(AU11-AT11), "0.00%") -> 0.62513472 | BE11: فندقي | BH11: إجمالي التكاليف المباشرة (Total Direct Costs) | BI11: =-SUM(C194:C198,C202:C206,C213) -> 1.8807665e+08 | BJ11: =BI11/($C$23+$C$24) -> 0.82754949 | BL11: غالبًا تمثل 70% – 85% من إجمالي التكاليف | BN11: فندقي (Hotel) | BO11: =IFERROR((AU11-AT11) / (C154 * D154 * G154 * (1 - $I$158) * BP11), 0) -> 0 | BQ11: فندقي (Hotel) | BR11: =IFERROR((AU11-AT11) / ((R154 * S154 * (1 - $Y$158) * 365 * BS11) * (1 + W154)), 0) -> 0 | BV11: الحصة من التطوير | BW11: 0 | BX11: - | BY11: - | BZ11: =H22*BW11 -> 0 | CA11: =BZ11 -> 0 | CB11: - | CF11: 5 | CG11: إجمالي تكلفة البناء | CH11: =C19 -> 78265608 | CI11: ملخص الدراسة | CJ11: C19 | CK11: ريال سعودي
AE12: صحي | AF12: =((F69/$J$59)*$I$49)*AO12 -> 0 | AG12: =J69*AO12 -> 0 | AI12: =($J$73*AH12)*AO12 -> 0 | AJ12: =((K69/$L$76)*($J$74+$J$75))*AO12 -> 0 | AK12: =((K69/$L$76)*$C$87)*AO12 -> 0 | AL12: =(((D69-F69)/$I$59)*$J$71)*AO12 -> 0 | AM12: =SUM(AF12:AG12,AI12:AL12)/$AM$14 -> 0 | AN12: =SUM(AF12:AG12,AI12:AL12)/$AN$14 -> 0 | AO12: =D137 -> 1 | AP12: =(AN12*SUM($C$86,$C$88:$C$90,$C$96:$C$97,$C$101))+((H155+X155)/($H$157+$X$157))*$C$99+(SUM($D$93:$D$95)*G69*AO12) -> 0 | AQ12: =(($A$92+$C$98)*AM12) -> 0 | AR12: =AM12*$C$119 -> 0 | AS12: =AN12*$C$107 -> 0 | AT12: =SUM(I155,Y155) -> 0 | AU12: =SUM(AF12:AG12,AI12:AL12,AP12:AT12) -> 0 | AV12: =IFERROR((AU12-AT12)/E137, "0") -> 0 | AW12: =(AU12-AT12)/($C$23) -> 0 | AX12: =SUM(J137,H155,O137,X155) -> 0 | AY12: =IFERROR(AZ12/E137, "0.00") -> 0.00 | AZ12: =AX12-AU12 -> 0 | BA12: =IFERROR(BD12/AW12, "0.00") -> 0.00 | BB12: =IFERROR(AZ12/AX12, "0.00%") -> 0.00% | BC12: =AZ12/$C$25 -> 0 | BD12: =IFERROR(AZ12/(AU12-AT12), "0.00%") -> 0.00% | BE12: صحي | BH12: إجمالي التكاليف غير المباشرة (Total Indirect Costs) | BI12: =-SUM(E192:E193,C199:C201,C207:C212,C214:C216) -> 39192718 | BJ12: =BI12/($C$23+$C$24) -> 0.17245051 | BL12: من 15% إلى 25% من إجمالي التكاليف غالبًا | BN12: صحي (health) | BO12: =IFERROR((AU12-AT12) / (C155 * D155 * G155 * (1 - $I$158) * BP12), 0) -> 0 | BQ12: صحي (health) | BR12: =IFERROR((AU12-AT12) / ((R155 * S155 * (1 - $Y$158) * 365 * BS12) * (1 + W155)), 0) -> 0 | BV12: الحصة العينية من المقاولات | BW12: 1 | BX12: =(E103*C195)*BW12 -> 0 | BY12: - | BZ12: =BX12*$BW$7 -> 0 | CA12: =BZ12+BX12 -> 0 | CB12: - | CF12: 6 | CG12: إجمالي التكاليف الأخرى | CH12: =C20 -> 21170058 | CI12: ملخص الدراسة | CJ12: C20 | CK12: ريال سعودي
AE13: شاليهات | AF13: =((F70/$J$59)*$I$49)*AO13 -> 0 | AG13: =J70*AO13 -> 0 | AI13: =($J$73*AH13)*AO13 -> 0 | AJ13: =((K70/$L$76)*($J$74+$J$75))*AO13 -> 0 | AK13: =((K70/$L$76)*$C$87)*AO13 -> 0 | AL13: =(((D70-F70)/$I$59)*$J$71)*AO13 -> 0 | AM13: =SUM(AF13:AG13,AI13:AL13)/$AM$14 -> 0 | AN13: =SUM(AF13:AG13,AI13:AL13)/$AN$14 -> 0 | AO13: =D138 -> 1 | AP13: =(AN13*SUM($C$86,$C$88:$C$90,$C$96:$C$97,$C$101))+((H156+X156)/($H$157+$X$157))*$C$99+(SUM($D$93:$D$95)*G70*AO13) -> 0 | AQ13: =(($A$92+$C$98)*AM13) -> 0 | AR13: =AM13*$C$119 -> 0 | AS13: =AN13*$C$107 -> 0 | AT13: =SUM(I156,Y156) -> 0 | AU13: =SUM(AF13:AG13,AI13:AL13,AP13:AT13) -> 0 | AV13: =IFERROR((AU13-AT13)/E138, "0") -> 0 | AW13: =(AU13-AT13)/($C$23) -> 0 | AX13: =SUM(J138,H156,O138,X156) -> 0 | AY13: =IFERROR(AZ13/E138, "0.00") -> 0.00 | AZ13: =AX13-AU13 -> 0 | BA13: =IFERROR(BD13/AW13, "0.00") -> 0.00 | BB13: =IFERROR(AZ13/AX13, "0.00%") -> 0.00% | BC13: =AZ13/$C$25 -> 0 | BD13: =IFERROR(AZ13/(AU13-AT13), "0.00%") -> 0.00% | BE13: شاليهات | BH13: إجمالي التكاليف التشغيلية (Total Operating Costs) | BI13: =C24 -> 6529315.6 | BJ13: =BI13/SUM(C23:C24) -> 0.028729413 | BL13: - | BN13: شاليهات (Chalets) | BO13: =IFERROR((AU13-AT13) / (C156 * D156 * G156 * (1 - $I$158) * BP13), 0) -> 0 | BQ13: شاليهات (Chalets) | BR13: =IFERROR((AU13-AT13) / ((R156 * S156 * (1 - $Y$158) * 365 * BS13) * (1 + W156)), 0) -> 0 | BV13: الحصة من المقاولات | BW13: 0 | BX13: - | BY13: - | BZ13: =(E104*C196)*BW13 -> 0 | CA13: =BZ13 -> 0 | CB13: - | CF13: 7 | CG13: إجمالي رسوم الصندوق | CH13: =C21 -> 22314657 | CI13: ملخص الدراسة | CJ13: C21 | CK13: ريال سعودي
AE14: الإجمالي | AF14: =SUMIF(AF4:AF13, "<>#DIV/0!") -> 91847824 | AG14: =SUMIF(AG4:AG13, "<>#DIV/0!") -> 44700408 | AH14: =SUM(AH4:AH13) -> 1 | AI14: =SUM(AI4:AI13) -> 6162000 | AJ14: =SUMIF(AJ4:AJ13, "<>#DIV/0!") -> 14176800 | AK14: =SUMIF(AK4:AK13, "<>#DIV/0!") -> 2835360 | AL14: =SUM(AL4:AL13) -> 0 | AM14: =SUM(AF14:AG14,AI14:AL14) -> 159722392 | AN14: =SUM(AF4:AG13,AI4:AL13,AF22:AG31,AI22:AL31) -> 2.0387089e+08 | AO14: - | AP14: =SUM(AP4:AQ13) -> 17522844 | AR14: =SUMIF(AR4:AR13, "<>#DIV/0!") -> 7141903.3 | AS14: =SUMIF(AS4:AS13, "<>#DIV/0!") -> 17482390 | AT14: =SUM(AT4:AT13) -> 6529315.6 | AU14: =SUM(AU4:AU13) -> 2.0839884e+08 | AV14: =IFERROR(AU14/E139, "0") -> 21006.267 | AW14: =SUMIF(AW4:AW13, "<>#DIV/0!") -> 0.91451247 | AX14: =SUMIF(AX4:AX13, "<>#DIV/0!") -> 2.6669563e+08 | AY14: =AZ14/E139 -> 5876.2217 | AZ14: =SUMIF(AZ4:AZ13, "<>#DIV/0!") -> 58296785 | BA14: - | BB14: =IFERROR(AZ14/AX14, "0.00%") -> 0.2185892 | BC14: =SUM(BC4:BC13) -> 0.6785543 | BD14: =IFERROR(AZ14/AU14, "0.00%") -> 0.27973661 | BH14: إجمالي قيمة ونسبة تكاليف الأرض من إجمالي تكاليف المشروع (Land Cost as Value and % of Total Project Cost) | BI14: =I49 -> 91847824 | BJ14: =BI14/$C$23 -> 0.41609044 | BL14: من 10% إلى 25% غالبًا | BV14: العمولات 2.5% من المبيعات | BW14: 0.025 | BX14: - | BY14: بيع على الخارطة + بيع مباشر + مخارجة | BZ14: =BW14*(J139+AC139+O139) -> 7233969.4 | CA14: =BZ14 -> 7233969.4 | CB14: - | CF14: 8 | CG14: فوائد التمويل | CH14: =C22 -> 7141903.3 | CI14: ملخص الدراسة | CJ14: C22 | CK14: ريال سعودي
B15: Feasibility Study Summary | ملخص دراسة الجدوى | G15: Financial Structuring | الهيكلة المالية | AF15: =IF(ABS(SUM(Study!AF14,Study!AF32)-SUM(Study!I49))<=0.00000001,"TRUE",SUM(Study!AF14,Study!AF32)-SUM(Study!I49)) -> 30922095 | AG15: =IF(ABS(SUM(Study!AG14,Study!AG32)-SUM(J61:J71))<=0.00000001,"TRUE",SUM(Study!AG14,Study!AG32)-SUM(J61:J71)) -> TRUE | AH15: =IF(ABS(SUM(Study!AH14)-SUM(1))<=0.00000001,"TRUE",SUM(Study!AH14)-SUM(1)) -> TRUE | AI15: =IF(ABS(SUM(Study!AI14,Study!AI32)-SUM(Study!J73))<=0.00000001,"TRUE",SUM(Study!AI14,Study!AI32)-SUM(Study!J73)) -> TRUE | AJ15: =IF(ABS(SUM(Study!AJ14,Study!AJ32)-SUM(J74:J75))<=0.00000001,"TRUE",SUM(Study!AJ14,Study!AJ32)-SUM(J74:J75)) -> TRUE | AK15: =IF(ABS(SUM(Study!AK14,Study!AK32)-SUM(Study!C87))<=0.00000001,"TRUE",SUM(Study!AK14,Study!AK32)-SUM(Study!C87)) -> TRUE | AL15: =IF(ABS(SUM(Study!AL14,Study!AL32)-SUM(Study!J71))<=0.00000001,"TRUE",SUM(Study!AL14,Study!AL32)-SUM(Study!J71)) -> TRUE | AM15: =IF(ABS(SUM(Study!AM4:AM13)-SUM(1))<=0.00000001,"TRUE",SUM(Study!AM4:AM13)-SUM(1)) -> TRUE | AN15: =IF(ABS(SUM(Study!AN4:AN13,Study!AN22:AN31)-SUM(1))<=0.00000001,"TRUE",SUM(Study!AN4:AN13,Study!AN22:AN31)-SUM(1)) -> TRUE | AO15: =IF(ABS(SUM(Study!AO4:AO13,Study!AO22:AO31)-SUM(10))<=0.00000001,"TRUE",SUM(Study!AO4:AO13,Study!AO22:AO31)-SUM(10)) -> TRUE | AP15: =IF(ABS(SUM(Study!AP4:AQ13,Study!AP22:AQ31)-SUM(Study!C86,Study!C88:C101))<=0.1,"TRUE",SUM(Study!AP4:AQ13,Study!AP22:AQ31)-SUM(Study!C86,Study!C88:C101)) -> 1437638.7 | AR15: =IF(ABS(SUM(Study!AR14)-SUM(Study!C119))<=0.00000001,"TRUE",SUM(Study!AR14)-SUM(Study!C119)) -> TRUE | AS15: =IF(ABS(SUM(Study!AS14,Study!AS32)-SUM(Study!C107))<=1,"TRUE",SUM(Study!AS14,Study!AS32)-SUM(Study!C107)) -> TRUE | AT15: =IF(ABS(SUM(Study!AT14)-SUM(Study!C24))<=0.01,"TRUE",SUM(Study!AT14)-SUM(Study!C24)) -> TRUE | AU15: =IF(ABS(SUM(Study!AU14,Study!AU32)-SUM(Study!C23:C24))<=0.25,"TRUE",SUM(Study!AU14,Study!AU32)-SUM(Study!C23:C24)) -> -18870521 | AV15: =AV14=AV14 -> TRUE | AW15: =IF(ABS(SUM(Study!AW14,Study!AW32)-SUM(1))<=0.01,"TRUE",SUM(Study!AW14,Study!AW32)-SUM(1)) -> -0.085487528 | AX15: =IF(ABS(SUM(Study!AX14,Study!AX32)-SUM(Study!C17))<=0.01,"TRUE",SUM(Study!AX14,Study!AX32)-SUM(Study!C17)) -> TRUE | AY15: =AY14=AY14 -> TRUE | AZ15: =IF(ABS(SUM(Study!AZ14,Study!AZ32)-SUM(Study!C25))<=0.2,"TRUE",SUM(Study!AZ14,Study!AZ32)-SUM(Study!C25)) -> -27616435 | BA15: =BA14=BA14 -> TRUE | BB15: =BB14=BB14 -> TRUE | BC15: =IF(ABS(SUM(Study!BC14,Study!BC32)-SUM(1))<=0.01,"TRUE",SUM(Study!BC14,Study!BC32)-SUM(1)) -> -0.3214457 | BD15: =BD14=BD14 -> TRUE | BH15: إجمالي قيمة ونسبة تكاليف البناء من إجمالي تكاليف المشروع (Construction Cost as Value and % of Total Project Cost) | BI15: =J76 -> 78265608 | BJ15: =BI15/$C$23 -> 0.35456007 | BL15: المتوسط غالبًا بين 45% إلى 65% | BV15: نسبة رصف من المستثمرين | BW15: 0 | BX15: =BW15*H21 -> 0 | BY15: - | BZ15: =BX15*$BW$7 -> 0 | CA15: =BZ15+BX15 -> 0 | CB15: - | CF15: 9 | CG15: التمويل البنكي | CI15: ملخص الدراسة | CJ15: C23 | CK15: ريال سعودي
B16: البند (Item) | C16: القيمة (Value) | G16: رأس المال - (capital) | BH16: إجمالي قيمة ونسبة التكاليف الأخرى من إجمالي تكاليف المشروع (Other Costs as % of Total Project Cost) | BI16: =C102 -> 21170058 | BJ16: =BI16/$C$23 -> 0.095904925 | BL16: غالبًا بين 10% – 20% | BV16: الحصة من فارق قيمة الأرض | BW16: 1 | BX16: =K23*BW16 -> 0 | BY16: - | BZ16: =BX16*$BW$7 -> 0 | CA16: =BZ16+BX16 -> 0 | CB16: - | CF16: 10 | CG16: إجمالي التكاليف الرأسمالية (CapEx) | CH16: =C23 -> 2.2074005e+08 | CI16: ملخص الدراسة | CJ16: C24 | CK16: ريال سعودي
B17: إجمالي الإيرادات (Total Revenue) | C17: =SUM(C184:C188) -> 3.1318259e+08 | G17: المصدر (Source) | H17: SAR | I17: % | BH17: إجمالي قيمة ونسبة تكاليف فوائد التمويل من إجمالي تكاليف المشروع (Financing Interest as Value and % of Total Project Cost) | BI17: =C119 -> 7141903.3 | BJ17: =BI17/$C$23 -> 0.032354361 | BL17: من 5% – 12% حسب مدة التمويل والفوائد | BV17: اشتراكات نقدية / مصاريف سابقة | BW17: 0 | BX17: =H19*BW17 -> 0 | BY17: - | BZ17: =BX17*$BW$7 -> 0 | CA17: =BZ17+BX17 -> 0 | CB17: - | CF17: 11 | CG17: إجمالي التكاليف التشغيلية (OpEx) | CH17: =C24 -> 6529315.6 | CI17: ملخص الدراسة | CJ17: C25 | CK17: ريال سعودي
B18: إجمالي تكلفة الأرض (Total Land Cost) | C18: =I49 -> 91847824 | G18: (Equity) - الملكية | BH18: إجمالي قيمة ونسبة تكاليف الصندوق من إجمالي تكاليف المشروع (Fund Management Cost as Value and % of Total Project Cost) | BI18: =C107 -> 22314657 | BJ18: =BI18/$C$23 -> 0.10109021 | BL18: تتراوح من 1% – 7% حسب شروط الصندوق | CF18: 12 | CG18: صافي الدخل | CH18: =C25 -> 85913221 | CI18: ملخص الدراسة | CJ18: C26 | CK18: ريال سعودي
B19: إجمالي تكلفة البناء (Total Construction Cost) | C19: =J76 -> 78265608 | G19: الاشتراكات النقدية (Cash Subscription) | H19: 34500000 | I19: =H19/$H$34 -> 0.15629244 | BH19: مؤشرات الإيرادات والربحية | Revenue & Profitability Indicators | BL19: - | BV19: إجمالي رصف | BX19: =SUM(BX10:BX17) -> 0 | BY19: - | BZ19: =SUM(BZ10:BZ17) -> 7233969.4 | CA19: =SUM(CA10:CA17) -> 7233969.4 | CB19: - | CF19: 13 | CG19: مدة المشروع المتوقعة (سنوات) | CH19: =C27 -> 5 | CI19: ملخص الدراسة | CJ19: C27 | CK19: سنة
B20: إجمالي التكاليف الأخرى (Total Other cost) | C20: =C102 -> 21170058 | G20: الاشتراك من مدير الصندوق (fund manager's Subscription) | I20: =H20/$H$34 -> 0 | AE20: توزيع تكاليف مكونات البيع على الخارطة | BH20: متوسط سعر بيع الأمتار البيعية (Average Selling Price per Sellable m²) | BI20: =SUM(C184,C187:C188)/J59 -> 29166.897 | BL20: - | BV20: مستثمرين رصف | BX20: 0 | BY20: 0.7 | BZ20: =BX20*BW7*BY20 -> 0 | CA20: =BZ20+BX20 -> 0 | CB20: - | CF20: ▌ المؤشرات المالية
B21: إجمالي رسوم الصندوق (Total Fund Fees) | C21: =C107 -> 22314657 | G21: الأشتراك النقدي من المطور (Cash Subscription from Developer) | H21: 11100000 | I21: =H21/$H$34 -> 0.050285392 | J21: =H34*5% -> 11037003 | AE21: المكون | AF21: توزيع تكاليف الأرض | AG21: تكاليف البناء | AH21: نسبة تزيع تكاليف اللاند سكيب | AI21: توزيع تكاليف اللاندسكيب | AJ21: توزيع تكاليف البوديم و القبو | AK21: توزيع تكاليف الحفر والمسح و الاختبار | AL21: توزيع تكاليف المساحات الحركية والخدمية | AM21: نسب التكاليف السابقة من التكاليف الموجودة بالجدول | AN21: نسب التكاليف السابقة من التكاليف الكلية | AO21: نسبة بيع المكون على الخارطة من الإجمالي | AP21: توزيع التكاليف الأخرى | AQ21: توزيع تكاليف أخرى إضافية | AR21: توزيع تكاليف التمويل | AS21: توزيع تكاليف الصندوق | AT21: تكاليف بيع الخارطة | AU21: إجمالي تكاليف كل مكون | AV21: توزيع التكلفة على الأمتار البيعية | AW21: نسبة تكاليف كل مكون من إجمالي المشروع | AX21: إجمالي إيراد كل مكون | AY21: صافي العائد لكل م² بيعي | AZ21: صافي دخل كل مكون | BA21: العائد النسبي للمكون | BB21: هامش الربح من إجمالي الإرادات | BC21: نسبة صافي دخل كل مكون من إجمالي صافي دخل المشروع | BD21: نسبة صافي دخل كل مكون | BH21: متوسط قيمة و نسبة الربح لكل م² (Average Profit Value and % per m²) | BI21: =BI20-BI7 -> 6916.6566 | BJ21: =BI21/BI7 -> 0.31085761 | BL21: - | BV21: الاجمالي | BX21: =SUM(BX19:BX20) -> 0 | BY21: - | BZ21: =SUM(BZ19:BZ20) -> 7233969.4 | CA21: =BZ21+BX21 -> 7233969.4 | CB21: - | CF21: 14 | CG21: معدل العائد الداخلي (IRR) | CH21: =C28 -> 0.13308131 | CI21: المؤشرات المالية | CJ21: C28 | CK21: نسبة مئوية
B22: فوائد التمويل (Interest) | C22: =C119 -> 7141903.3 | G22: الأشتراك العيني من المطور (In-Kind Subscription from Developer) | H22: =J22*((D104+E104)*-E196) -> 0 | I22: =H22/$H$34 -> 0 | J22: 0 | AE22: سكني (بيع على الخارطة) | AF22: =((F61/$J$59)*$I$49)*AO22 -> 0 | AG22: =J61*AO22 -> 0 | AH22: 0.15 | AI22: =($J$73*AH22)*AO22 -> 0 | AJ22: =((K61/$L$76)*($J$74+$J$75))*AO22 -> 0 | AK22: =((K61/$L$76)*$C$87)*AO22 -> 0 | AL22: =(((D61-F61)/$I$59)*$J$71)*AO22 -> 0 | AN22: =SUM(AF22:AG22,AI22:AL22)/$AN$32 -> 0 | AO22: =S129 -> 0 | AP22: =(AN22*SUM($C$86,$C$88:$C$90,$C$96:$C$97,$C$101))+(SUM($D$93:$D$95)*G61*AO22) -> 0 | AR22: لا يــــنــطــبــق | AS22: =AN22*$C$107 -> 0 | AT22: لا يــــنــطــبــق | AV22: =IFERROR((AU22)/T129, "0") -> 0 | AX22: =AC129 -> 0 | AY22: =IFERROR(AZ22/T129, "0.00") -> 0.00 | BA22: =IFERROR(BD22/AW22, "0.00") -> 0.00 | BB22: =IFERROR(AZ22/AX22, "0.00%") -> 0.00% | BD22: =IFERROR(AZ22/(AU22), "0.00%") -> 0.00% | BE22: سكني | BH22: العائد على المتر البيعي (شامل عوائد الإيجار) (Total Return per Saleable m² including Rental Income) | BI22: =C25/F76 -> 8659.9138 | BJ22: =BI22/BI7 -> 0.3892054 | BL22: - | CF22: 15 | CG22: العائد على الاستثمار (ROI) | CH22: =C30 -> 0.3892054 | CI22: المؤشرات المالية | CJ22: C30 | CK22: نسبة مئوية
B23: إجمالي التكاليف الرأسمالية للمشروع (Total Capital Expenditures) | C23: =SUM(C18:C22) -> 2.2074005e+08 | G23: الإشتراك العيني من مالك الأرض (In-Kind Subscription from Landowner) | H23: =(J23*E49)+K23 -> 62809600 | I23: =H23/$H$34 -> 0.28454102 | J23: 0.7 | AE23: فلل (بيع على الخارطة) | AF23: =((F62/$J$59)*$I$49)*AO23 -> 30922095 | AG23: =J62*AO23 -> 13226400 | AH23: 0 | AI23: =($J$73*AH23)*AO23 -> 0 | AJ23: =((K62/$L$76)*($J$74+$J$75))*AO23 -> 0 | AK23: =((K62/$L$76)*$C$87)*AO23 -> 0 | AL23: =(((D62-F62)/$I$59)*$J$71)*AO23 -> 0 | AN23: =SUM(AF23:AL23)/$AN$32 -> 0.21655125 | AO23: =S130 -> 1 | AP23: =(AN23*SUM($C$86,$C$88:$C$90,$C$96:$C$97,$C$101))+(SUM($D$93:$D$95)*G62*AO23) -> 2249493 | AR23: لا يــــنــطــبــق | AS23: =AN23*$C$107 -> 4832266.8 | AT23: لا يــــنــطــبــق | AV23: =IFERROR((AU23-AT23)/T130, "0") -> 0 | AX23: =AC130 -> 46486957 | AY23: =IFERROR(AZ23/T130, "0.00") -> 0 | BA23: =IFERROR(BD23/AW23, "0.00") -> 0.00 | BB23: =IFERROR(AZ23/AX23, "0.00%") -> 0 | BD23: =IFERROR(AZ23/(AU23), "0.00%") -> 0.00% | BE23: فلل | BH23: نسبة صافي الربح من الإيرادات (Net Profit as % of Revenues) | BI23: =C25/C17 -> 0.27432311 | BL23: مثالي إن كان بين 20% إلى 35% (أقل من 15% يُعد ضعيف، وأكثر من 40% نادر وممتاز) | CF23: 16 | CG23: العائد على الملكية (ROE) | CH23: =C32 -> 0.7924872 | CI23: المؤشرات المالية | CJ23: C32 | CK23: نسبة مئوية
B24: إجمالي التكاليف التشغيلية (Total Operating Expenses) | C24: =-SUM(E213) -> 6529315.6 | G24: إجمالي الملكية (Total Equity) | H24: =SUM(H19:H23) -> 108409600 | I24: =H24/$H$34 -> 0.49111885 | AE24: تاون هاوس (بيع على الخارطة) | AF24: =((F63/$J$59)*$I$49)*AO24 -> 0 | AG24: =J63*AO24 -> 0 | AH24: 0 | AI24: =($J$73*AH24)*AO24 -> 0 | AJ24: =((K63/$L$76)*($J$74+$J$75))*AO24 -> 0 | AK24: =((K63/$L$76)*$C$87)*AO24 -> 0 | AL24: =(((D63-F63)/$I$59)*$J$71)*AO24 -> 0 | AN24: =SUM(AF24:AL24)/$AN$32 -> 0 | AO24: =S131 -> 0.00% | AP24: =(AN24*SUM($C$86,$C$88:$C$90,$C$96:$C$97,$C$101))+(SUM($D$93:$D$95)*G63*AO24) -> 0 | AR24: لا يــــنــطــبــق | AS24: =AN24*$C$107 -> 0 | AT24: لا يــــنــطــبــق | AV24: =IFERROR((AU24-AT24)/T131, "0") -> 0 | AX24: =AC131 -> 0 | AY24: =IFERROR(AZ24/T131, "0.00") -> 0.00 | BA24: =IFERROR(BD24/AW24, "0.00") -> 0.00 | BB24: =IFERROR(AZ24/AX24, "0.00%") -> 0.00% | BD24: =IFERROR(AZ24/(AU24), "0.00%") -> 0.00% | BE24: تاون هاوس | BH24: نقطة التعادل - عدد الأمتار البيعية اللازمة لتغطية التكاليف (Sellable Area Required for Cost Recovery) | BI24: =C23/BI20 -> 7568.1706 | BJ24: =BI24/F76 -> 0.76285936 | BL24: - | CF24: 17 | CG24: العائد على الملكية السنوي | CH24: =C34 -> 0.15849744 | CI24: المؤشرات المالية | CJ24: C34 | CK24: نسبة مئوية
B25: صافي الدخل (Net Income) | C25: =C17-(C23+C24) -> 85913221 | G25: التمويل البنكي - (Bank Financing) | AE25: أدوار (بيع على الخارطة) | AF25: =((F64/$J$59)*$I$49)*AO25 -> 0 | AG25: =J64*AO25 -> 0 | AH25: 0 | AI25: =($J$73*AH25)*AO25 -> 0 | AJ25: =((K64/$L$76)*($J$74+$J$75))*AO25 -> 0 | AK25: =((K64/$L$76)*$C$87)*AO25 -> 0 | AL25: =(((D64-F64)/$I$59)*$J$71)*AO25 -> 0 | AN25: =SUM(AF25:AL25)/$AN$32 -> 0 | AO25: =S132 -> 0.00% | AP25: =(AN25*SUM($C$86,$C$88:$C$90,$C$96:$C$97,$C$101))+(SUM($D$93:$D$95)*G64*AO25) -> 0 | AR25: لا يــــنــطــبــق | AS25: =AN25*$C$107 -> 0 | AT25: لا يــــنــطــبــق | AV25: =IFERROR((AU25-AT25)/T132, "0") -> 0 | AX25: =AC132 -> 0 | AY25: =IFERROR(AZ25/T132, "0.00") -> 0.00 | BA25: =IFERROR(BD25/AW25, "0.00") -> 0.00 | BB25: =IFERROR(AZ25/AX25, "0.00%") -> 0.00% | BD25: =IFERROR(AZ25/(AU25), "0.00%") -> 0.00% | BE25: أدوار | BH25: مؤشرات التمويل والمخاطر | Financing & Risk Indicators | BJ25: 0 | BL25: - | CF25: ▌ الهيكلة المالية
B26: أهــــــــــــــــــم مؤشــــــــرات الدراســــــــــة | G26: إجمالي التمويل البنكي (Total Bank Financing) | H26: =E189 -> 54352006 | I26: =H26/$H$34 -> 0.2462263 | AE26: استديوهات (بيع على الخارطة) | AF26: =((F65/$J$59)*$I$49)*AO26 -> 0 | AG26: =J65*AO26 -> 0 | AH26: 0 | AI26: =($J$73*AH26)*AO26 -> 0 | AJ26: =((K65/$L$76)*($J$74+$J$75))*AO26 -> 0 | AK26: =((K65/$L$76)*$C$87)*AO26 -> 0 | AL26: =(((D65-F65)/$I$59)*$J$71)*AO26 -> 0 | AN26: =SUM(AF26:AL26)/$AN$32 -> 0 | AO26: =S133 -> 0.00% | AP26: =(AN26*SUM($C$86,$C$88:$C$90,$C$96:$C$97,$C$101))+(SUM($D$93:$D$95)*G65*AO26) -> 0 | AR26: لا يــــنــطــبــق | AS26: =AN26*$C$107 -> 0 | AT26: لا يــــنــطــبــق | AV26: =IFERROR((AU26-AT26)/T133, "0") -> 0 | AX26: =AC133 -> 0 | AY26: =IFERROR(AZ26/T133, "0.00") -> 0.00 | BA26: =IFERROR(BD26/AW26, "0.00") -> 0.00 | BB26: =IFERROR(AZ26/AX26, "0.00%") -> 0.00% | BD26: =IFERROR(AZ26/(AU26), "0.00%") -> 0.00% | BE26: أستوديوهات | BH26: القيم والنسب الخاصة بالتمويل البنكي (Bank Financing Limits & Conditions) | BI26: =(BJ28+BJ27)-H26 -> 53513192 | BJ26: =H26/(BJ28+BJ27) -> 0.50388825 | BL26: - | CF26: 18 | CG26: الاشتراكات النقدية | CH26: =H19 -> 34500000 | CI26: الهيكلة المالية | CJ26: H19 | CK26: ريال سعودي
B27: مدة المشروع المتوقعة - سنوي (Estimated Project Duration - Years) | C27: =B122 -> 5 | AE27: مكتبي (بيع على الخارطة) | AF27: =((F66/$J$59)*$I$49)*AO27 -> 0 | AG27: =J66*AO27 -> 0 | AH27: 0.35 | AI27: =($J$73*AH27)*AO27 -> 0 | AJ27: =((K66/$L$76)*($J$74+$J$75))*AO27 -> 0 | AK27: =((K66/$L$76)*$C$87)*AO27 -> 0 | AL27: =(((D66-F66)/$I$59)*$J$71)*AO27 -> 0 | AN27: =SUM(AF27:AL27)/$AN$32 -> 1.7167728e-09 | AO27: =S134 -> 0.00% | AP27: =(AN27*SUM($C$86,$C$88:$C$90,$C$96:$C$97,$C$101))+(SUM($D$93:$D$95)*G66*AO27) -> 0.015914983 | AR27: لا يــــنــطــبــق | AS27: =AN27*$C$107 -> 0.038309197 | AT27: لا يــــنــطــبــق | AV27: =IFERROR((AU27-AT27)/T134, "0") -> 0 | AX27: =AC134 -> 0 | AY27: =IFERROR(AZ27/T134, "0.00") -> 0.00 | BA27: =IFERROR(BD27/AW27, "0.00") -> 0.00 | BB27: =IFERROR(AZ27/AX27, "0.00%") -> 0.00% | BD27: =IFERROR(AZ27/(AU27), "0.00%") -> 0.00% | BE27: مكتبي | BI27: 0.6 | BJ27: =(I49*80%)*BI27 -> 44086956 | BL27: - | CF27: 19 | CG27: نسبة الاشتراكات النقدية | CH27: =I19 -> 0.15629244 | CI27: الهيكلة المالية | CJ27: I19 | CK27: نسبة مئوية
B28: معدل العائد الداخلي (IRR) | C28: =C223 -> 0.13308131 | G28: تمويل تشغيلي خارج هيكل رأس المال - (Off-Capital-Structure Operational Financing) | AE28: تجاري (بيع على الخارطة) | AF28: =((F67/$J$59)*$I$49)*AO28 -> 0 | AG28: =J67*AO28 -> 0 | AH28: 0.35 | AI28: =($J$73*AH28)*AO28 -> 0 | AJ28: =((K67/$L$76)*($J$74+$J$75))*AO28 -> 0 | AK28: =((K67/$L$76)*$C$87)*AO28 -> 0 | AL28: =(((D67-F67)/$I$59)*$J$71)*AO28 -> 0 | AN28: =SUM(AF28:AL28)/$AN$32 -> 1.7167728e-09 | AO28: =S135 -> 0.00% | AP28: =(AN28*SUM($C$86,$C$88:$C$90,$C$96:$C$97,$C$101))+(SUM($D$93:$D$95)*G67*AO28) -> 0.015914983 | AR28: لا يــــنــطــبــق | AS28: =AN28*$C$107 -> 0.038309197 | AT28: لا يــــنــطــبــق | AV28: =IFERROR((AU28-AT28)/T135, "0") -> 0 | AX28: =AC135 -> 0 | AY28: =IFERROR(AZ28/T135, "0.00") -> 0.00 | BA28: =IFERROR(BD28/AW28, "0.00") -> 0.00 | BB28: =IFERROR(AZ28/AX28, "0.00%") -> 0.00% | BD28: =IFERROR(AZ28/(AU28), "0.00%") -> 0.00% | BE28: تجاري | BI28: 0.7 | BJ28: =SUM(J76,C86:C90,C93:C95,C96:C96,C101)*BI28 -> 63778242 | BL28: - | CF28: 20 | CG28: الاشتراك من مدير الصندوق | CH28: =H20 -> 0 | CI28: الهيكلة المالية | CJ28: H20 | CK28: ريال سعودي
G29: البيع على الخارطة (Off-Plan Sales) | H29: =K29*J29 -> 46486957 | I29: =H29/$H$34 -> 0.21059593 | J29: =AC139 -> 46486957 | K29: 1 | L29: =-H35/J29 -> 0 | AE29: فندقي (بيع على الخارطة) | AF29: =((F68/$J$59)*$I$49)*AO29 -> 0 | AG29: =J68*AO29 -> 0 | AH29: 0.15 | AI29: =($J$73*AH29)*AO29 -> 0 | AJ29: =((K68/$L$76)*($J$74+$J$75))*AO29 -> 0 | AK29: =((K68/$L$76)*$C$87)*AO29 -> 0 | AL29: =(((D68-F68)/$I$59)*$J$71)*AO29 -> 0 | AN29: =SUM(AF29:AL29)/$AN$32 -> 7.3575979e-10 | AO29: =S136 -> 0 | AP29: =(AN29*SUM($C$86,$C$88:$C$90,$C$96:$C$97,$C$101))+((SUM($D$94:$D$95)*G68*AO29)+(D93*G68/2*AO29)) -> 0.006820707 | AR29: لا يــــنــطــبــق | AS29: =AN29*$C$107 -> 0.016418227 | AT29: لا يــــنــطــبــق | AV29: =IFERROR((AU29-AT29)/T136, "0") -> 0 | AX29: =AC136 -> 0 | AY29: =IFERROR(AZ29/T136, "0.00") -> 0.00 | BA29: =IFERROR(BD29/AW29, "0.00") -> 0.00 | BB29: =IFERROR(AZ29/AX29, "0.00%") -> 0.00% | BD29: =IFERROR(AZ29/(AU29), "0.00%") -> 0.00% | BE29: فندقي | BI29: =BJ29/D119 -> 0.039885606 | BJ29: =BI30/H26 -> 0.13140091 | BL29: - | CF29: 21 | CG29: الاشتراك النقدي من المطور | CH29: =H21 -> 11100000 | CI29: الهيكلة المالية | CJ29: H21 | CK29: ريال سعودي
B30: العائد على الإستثمار (ROI) | C30: =C25/C23 -> 0.3892054 | G30: مصادر أخرى (Other Sources) | H30: =K30*J30 -> 11491488 | I30: =H30/$H$34 -> 0.052058917 | J30: =SUM(J139,M157,AC157) -> 17294496 | K30: 0.66445927 | L30: =-H35/J30 -> 0 | AE30: صحي (بيع على الخارطة) | AF30: =((F69/$J$59)*$I$49)*AO30 -> 0 | AG30: =J69*AO30 -> 0 | AH30: =AH12 -> 0 | AI30: =($J$73*AH30)*AO30 -> 0 | AJ30: =((K69/$L$76)*($J$74+$J$75))*AO30 -> 0 | AK30: =((K69/$L$76)*$C$87)*AO30 -> 0 | AL30: =(((D69-F69)/$I$59)*$J$71)*AO30 -> 0 | AN30: =SUM(AF30:AL30)/$AN$32 -> 0 | AO30: =S137 -> 0.00% | AP30: =(AN30*SUM($C$86,$C$88:$C$90,$C$96:$C$97,$C$101))+(SUM($D$93:$D$95)*G69*AO30) -> 0 | AR30: لا يــــنــطــبــق | AS30: =AN30*$C$107 -> 0 | AT30: لا يــــنــطــبــق | AV30: =IFERROR((AU30-AT30)/T137, "0") -> 0 | AX30: =AC137 -> 0 | AY30: =IFERROR(AZ30/T137, "0.00") -> 0.00 | BA30: =IFERROR(BD30/AW30, "0.00") -> 0.00 | BB30: =IFERROR(AZ30/AX30, "0.00%") -> 0.00% | BD30: =IFERROR(AZ30/(AU30), "0.00%") -> 0.00% | BE30: صحي | BI30: =C22 -> 7141903.3 | BL30: - | CF30: 22 | CG30: الاشتراك العيني من المطور | CH30: =H22 -> 0 | CI30: الهيكلة المالية | CJ30: H22 | CK30: ريال سعودي
G31: إجمالي التمويل التشغيلي (Total Operational Financing) | H31: =SUM(H29:H30) -> 57978444 | I31: =H31/$H$34 -> 0.26265485 | AE31: شاليهات (بيع على الخارطة) | AF31: =((F70/$J$59)*$I$49)*AO31 -> 0 | AG31: =J70*AO31 -> 0 | AH31: =AH13 -> 0 | AI31: =($J$73*AH31)*AO31 -> 0 | AJ31: =((K70/$L$76)*($J$74+$J$75))*AO31 -> 0 | AK31: =((K70/$L$76)*$C$87)*AO31 -> 0 | AL31: =(((D70-F70)/$I$59)*$J$71)*AO31 -> 0 | AN31: =SUM(AF31:AL31)/$AN$32 -> 0 | AO31: =S138 -> 0.00% | AP31: =(AN31*SUM($C$86,$C$88:$C$90,$C$96:$C$97,$C$101))+(SUM($D$93:$D$95)*G70*AO31) -> 0 | AR31: لا يــــنــطــبــق | AS31: =AN31*$C$107 -> 0 | AT31: لا يــــنــطــبــق | AV31: =IFERROR((AU31-AT31)/T138, "0") -> 0 | AX31: =AC138 -> 0 | AY31: =IFERROR(AZ31/T138, "0.00") -> 0.00 | BA31: =IFERROR(BD31/AW31, "0.00") -> 0.00 | BB31: =IFERROR(AZ31/AX31, "0.00%") -> 0.00% | BD31: =IFERROR(AZ31/(AU31), "0.00%") -> 0.00% | BE31: شاليهات | BH31: نسبة المخاطرة التمويلية (Loan to Value Ratio - LTV) | BI31: =H26/(SUM(C184:C188)) -> 0.17354734 | BJ31: =1-BI31 -> 0.82645266 | BL31: بين (50%) و (70%) = طبيعي أقل من (50%) = منخفض (اعتماد كبير على تمويل ذاتي) أكثر من (70%) = مرتفع (مخاطرة عالية على البنك) | CF31: 23 | CG31: نسبة الاشتراك العيني من المطور | CH31: =I22 -> 0 | CI31: الهيكلة المالية | CJ31: I22 | CK31: نسبة مئوية
B32: العائد على الملكية (ROE) | C32: =(C25/H24) -> 0.7924872 | G32: الإجمالي - (Total) | AE32: الإجمالي | AF32: =SUM(AF22:AF31) -> 30922095 | AG32: =SUM(AG22:AG31) -> 13226400 | AH32: =SUM(AH22:AH31) -> 1 | AI32: =SUM(AI22:AI31) -> 0 | AJ32: =SUM(AJ22:AJ31) -> 0 | AK32: =SUM(AK22:AK31) -> 0 | AL32: =SUM(AL22:AL31) -> 0 | AM32: =SUM(AF32:AG32,AI32:AL32) -> 44148495 | AN32: =SUM(AF4:AG13,AI4:AL13,AF22:AG31,AI22:AL31) -> 2.0387089e+08 | AO32: - | AR32: - | AS32: =SUM(AS22:AS31) -> 4832266.9 | AT32: =SUM(AT22:AT31) -> 0 | AV32: =IFERROR(AU32/T139, "0") -> 0 | AX32: =SUM(AX22:AX31) -> 46486957 | AY32: =AZ32/T139 -> 0 | AZ32: =SUMIF(AZ22:AZ31, "<>#DIV/0!") -> 0 | BA32: - | BB32: =IFERROR(AZ32/AX32, "0.00%") -> 0 | BD32: =IFERROR(AZ32/AU32, "0.00%") -> 0.00% | BH32: مؤشر المخاطر التمويلية (Leverage Risk Indicator) | BI32: =H26/H24 -> 0.50135787 | BL32: يفضل أن يكون ≤ 1.5 (كلما ارتفع زادت المخاطرة) | CF32: 24 | CG32: الاشتراك العيني من مالك الأرض | CH32: =H23 -> 62809600 | CI32: الهيكلة المالية | CJ32: H23 | CK32: ريال سعودي
G33: إجمالي مصادر التمويل (Total Financing Sources) | H33: =H24+H26+H31 -> 2.2074005e+08 | I33: =IF(ABS(SUM(1)-SUM(Study!I24,Study!I26,Study!I31))<=0.001,"TRUE",SUM(1)-SUM(Study!I24,Study!I26,Study!I31)) -> TRUE | AF33: =I49-AF14=AF32 -> FALSE | AG33: =SUM(J61:J71)-AG14=AG32 -> TRUE | AH33: =SUM(AH22:AH31)=AH32 -> TRUE | AI33: =ABS((J73 - AI14) - AI32) <= 0.9 -> TRUE | AJ33: =(J74+J75)-AJ14=AJ32 -> TRUE | AK33: =ABS((C87 - AK14) - AK32) <= 0.9 -> TRUE | AL33: =J71-AL14=AL32 -> TRUE | AM33: =SUM(AF22:AG31,AI22:AL31)=AM32 -> TRUE | AN33: =SUM(AI22:AL31,AF22:AG31,AF4:AG13,AI4:AL13)=AN32 -> TRUE | AO33: =SUM(AO4:AO13,AO22:AO31)=1000% -> TRUE | AR33: =AR32=AR32 -> TRUE | AS33: =ABS((C107 - AS14) - AS32) <= 0.9 -> TRUE | AT33: =AT32=AT32 -> TRUE | AV33: =AV32=AV32 -> TRUE | AX33: =AX32=AC139 -> TRUE | AY33: =AY32=AY32 -> TRUE | AZ33: =AZ32=AZ32 -> TRUE | BA33: =BA32=BA32 -> TRUE | BB33: =BB32=BB32 -> TRUE | BD33: =BD32=BD32 -> TRUE | BH33: قيمة ونسبة تمويل مبيعات الخارطة من تكاليف المشروع خلال فترة البيع (Value and % of Off-Plan Sales Financing for Project Costs During Sales Period) | BI33: =AX22 -> 0 | BJ33: =C184/-(SUM(G192:S216)) -> 0.49384503 | BL33: من 30% إلى 60% من التكاليف أثناء البيع يعتبر جيد جداً | CF33: 25 | CG33: نسبة الاشتراك العيني من مالك الأرض | CH33: =I23 -> 0.28454102 | CI33: الهيكلة المالية | CJ33: I23 | CK33: نسبة مئوية
B34: العائد على الملكية السنوي (ROE Annually) | C34: =C32/C27 -> 0.15849744 | G34: إجمالي التكاليف الرأسمالية للمشروع (Total Capital Expenditures) | H34: =C23 -> 2.2074005e+08 | BH34: هامش الأمان (Safety Margin) | BI34: =(C17-C23)/C17 -> 0.29517138 | BL34: المستهدف الجيد ≥ 20% (بمعنى أن القيمة السوقية أعلى بـ 20% من التكلفة) | CF34: 26 | CG34: إجمالي الملكية | CH34: =H24 -> 108409600 | CI34: الهيكلة المالية | CJ34: H24 | CK34: ريال سعودي
G35: الفرق (Difference) | H35: =H33-H34 -> 0 | BH35: مؤشرات الأرض والزمن | Land & Time Indicators | BJ35: 0 | BL35: - | CF35: 27 | CG35: نسبة إجمالي الملكية | CH35: =I24 -> 0.49111885 | CI35: الهيكلة المالية | CJ35: I24 | CK35: نسبة مئوية
BH36: تكلفة متر الأرض شاملة الضريبة والسعي (Land Cost per m² - Including Tax and Commission) | BI36: =I49/C49 -> 11179.141 | BJ36: =D49 -> 10921.13 | BL36: - | CF36: 28 | CG36: إجمالي التمويل البنكي | CH36: =H26 -> 54352006 | CI36: الهيكلة المالية | CJ36: H26 | CK36: ريال سعودي
BH37: سعر متر الأرض عند البيع (Land Price per m² at Sale) | BI37: =((I49/C23)*C17)/C49 -> 15860.793 | BL37: - | CF37: 29 | CG37: نسبة التمويل البنكي | CH37: =I26 -> 0.2462263 | CI37: الهيكلة المالية | CJ37: I26 | CK37: نسبة مئوية
AE38: إجمالي توزيع التكاليف على جميع المكونات | BH38: قيمة ارتفاع سعر متر الأرض عند البيع (Land Price Appreciation Value) | BI38: =BI37-BI36 -> 4681.6523 | BL38: - | CF38: 30 | CG38: البيع على الخارطة (هيكلة) | CH38: =H29 -> 46486957 | CI38: الهيكلة المالية | CJ38: H29 | CK38: ريال سعودي
AE39: المكون | AF39: توزيع تكاليف الأرض | AG39: تكاليف البناء | AH39: نسبة تزيع تكاليف اللاند سكيب | AI39: توزيع تكاليف اللاندسكيب | AJ39: توزيع تكاليف البوديم و القبو | AK39: توزيع تكاليف الحفر والمسح و الاختبار | AL39: توزيع تكاليف المساحات الحركية والخدمية | AM39: نسب التكاليف السابقة من التكاليف الموجودة بالجدول | AN39: نسب التكاليف السابقة من التكاليف الكلية | AO39: نسب المكونات من البيع المباشر أو المخارجة من الإجمالي | AP39: توزيع التكاليف الأخرى | AQ39: توزيع تكاليف أخرى إضافية | AR39: توزيع تكاليف التمويل | AS39: توزيع تكاليف الصندوق | AT39: توزيع التكاليف التشغيلية | AU39: إجمالي تكاليف كل مكون | AV39: توزيع التكلفة على المساحات الصافية القابلة للبيع | AW39: نسبة تكاليف كل مكون من إجمالي المشروع | AX39: إجمالي إيراد كل مكون | AY39: صافي العائد لكل م² بيعي | AZ39: صافي دخل كل مكون | BA39: العائد النسبي للمكون | BB39: هامش الربح من إجمالي الإرادات | BC39: نسبة صافي دخل كل مكون من إجمالي صافي دخل المشروع | BD39: نسبة صافي دخل كل مكون | BH39: نسبة ارتفاع سعر متر الأرض (Land Price Appreciation Rate) | BI39: =BI38/BI36 -> 0.41878461 | BL39: من 10% إلى 40% خلال 3–5 سنوات يعتبر جيد | CF39: 31 | CG39: نسبة البيع على الخارطة | CH39: =I29 -> 0.21059593 | CI39: الهيكلة المالية | CJ39: I29 | CK39: نسبة مئوية
AE40: سكني | AF40: =SUM(AF4,AF22) -> 15362564 | AG40: =SUM(AG4,AG22) -> 7800408 | AH40: =AH4 -> 0 | AI40: =SUM(AI4,AI22) -> 0 | AJ40: =SUM(AJ4,AJ22) -> 0 | AK40: =SUM(AK4,AK22) -> 0 | AL40: =SUM(AL4,AL22) -> 0 | AM40: - | AN40: =SUM(AN4,AN22) -> 0.11361589 | AO40: =SUM(AO4,AO22) -> 1 | AP40: =SUM(AP4,AP22) -> 749188.5 | AQ40: =SUM(AQ4,AQ22) -> 887297.5 | AR40: =SUM(AR4,AR22) -> 1035720.2 | AS40: =SUM(AS4,AS22) -> 2535299.6 | AT40: =SUM(AT4,AT22) -> 123565.55 | AU40: =SUM(AU4,AU22) -> 28494043 | AV40: =IFERROR((AU40-AT40)/F61, "0") -> 9413.5425 | AW40: =SUM(AW4,AW22) -> 0.12852438 | AX40: =SUM(AX22,AX4) -> 31818130 | AY40: =IFERROR(AZ40/F61, "0.00") -> 1102.9575 | AZ40: =SUM(AZ22,AZ4) -> 3324086.8 | BA40: =IFERROR(BD40/AW40, "0.00") -> 0.91163333 | BB40: =IFERROR(AZ40/AX40, "0.00%") -> 0.10447147 | BC40: =AZ40/$C$25 -> 0.038691214 | BD40: =IFERROR(AZ40/(AU40-AT40), "0.00%") -> 0.11716711 | BE40: سكني | BH40: كفاءة المساحة البيعية من المساحات المبنية فوق الأرض (Saleable Efficiency Ratio of Above-Ground Built-Up Area) | BI40: =F76/I59 -> 0.63159036 | BL40: المستهدف المثالي ≥ 70% (الممتاز يتجاوز 75–80%) | CF40: 32 | CG40: مصادر أخرى | CH40: =H30 -> 11491488 | CI40: الهيكلة المالية | CJ40: H30 | CK40: ريال سعودي
AE41: فلل | AF41: =SUM(AF5,AF23) -> 58273355 | AG41: =SUM(AG5,AG23) -> 13226400 | AH41: =AH5 -> 0 | AI41: =SUM(AI5,AI23) -> 0 | AJ41: =SUM(AJ5,AJ23) -> 0 | AK41: =SUM(AK5,AK23) -> 0 | AL41: =SUM(AL5,AL23) -> 0 | AM41: - | AN41: =SUM(AN5,AN23) -> 0.35071096 | AO41: =SUM(AO5,AO23) -> 1 | AP41: =SUM(AP5,AP23) -> 2705685.7 | AQ41: =SUM(AQ5,AQ23) -> 888528.77 | AR41: =SUM(AR5,AR23) -> 1222997.3 | AS41: =SUM(AS5,AS23) -> 7825994.9 | AT41: =SUM(AT5,AT23) -> 0 | AU41: =SUM(AU5,AU23) -> 32912707 | AV41: =IFERROR((AU41-AT41)/F62, "0") -> 9854.1038 | AW41: =SUM(AW5,AW23) -> 0.14910165 | AX41: =SUM(AX23,AX5) -> 46486957 | AY41: =IFERROR(AZ41/F62, "0.00") -> -9854.1038 | AZ41: =SUM(AZ23,AZ5) -> -32912707 | BA41: =IFERROR(BD41/AW41, "0.00") -> -6.7068337 | BB41: =IFERROR(AZ41/AX41, "0.00%") -> -0.70799874 | BC41: =AZ41/$C$25 -> -0.38309246 | BD41: =IFERROR(AZ41/(AU41-AT41), "0.00%") -> -1 | BE41: فلل | BH41: مدة البيع - بالسنوات (غير شامل بيع الخارطة) (Sales Duration – Years) | BI41: =COUNTIFS(F187:AC187,">500")/4 -> 0 | BJ41: =BI41/B122 -> 0 | BL41: الطبيعي من 1 إلى 1.5 سنوات | CF41: 33 | CG41: نسبة المصادر الأخرى | CH41: =I30 -> 0.052058917 | CI41: الهيكلة المالية | CJ41: I30 | CK41: نسبة مئوية
B42: تفاصيل الأرض | Land Details | AE42: تاون هاوس | AF42: =SUM(AF6,AF24) -> 0 | AG42: =SUM(AG6,AG24) -> 0 | AH42: =AH6 -> 0 | AI42: =SUM(AI6,AI24) -> 0 | AJ42: =SUM(AJ6,AJ24) -> 0 | AK42: =SUM(AK6,AK24) -> 0 | AL42: =SUM(AL6,AL24) -> 0 | AM42: - | AN42: =SUM(AN6,AN24) -> 0 | AO42: =SUM(AO6,AO24) -> 1 | AP42: =SUM(AP6,AP24) -> 0 | AQ42: =SUM(AQ6,AQ24) -> 0 | AR42: =SUM(AR6,AR24) -> 0 | AS42: =SUM(AS6,AS24) -> 0 | AT42: =SUM(AT6,AT24) -> 0 | AU42: =SUM(AU6,AU24) -> 0 | AV42: =IFERROR((AU42-AT42)/F63, "0") -> 0 | AW42: =SUM(AW6,AW24) -> 0 | AX42: =SUM(AX24,AX6) -> 0 | AY42: =IFERROR(AZ42/F63, "0.00") -> 0.00 | AZ42: =SUM(AZ24,AZ6) -> 0 | BA42: =IFERROR(BD42/AW42, "0.00") -> 0.00 | BB42: =IFERROR(AZ42/AX42, "0.00%") -> 0.00% | BC42: =AZ42/$C$25 -> 0 | BD42: =IFERROR(AZ42/(AU42-AT42), "0.00%") -> 0.00% | BE42: تاون هاوس | BH42: توزيع الأرباح | Profit Distribution | BL42: - | CF42: 34 | CG42: إجمالي التمويل التشغيلي | CH42: =H31 -> 57978444 | CI42: الهيكلة المالية | CJ42: H31 | CK42: ريال سعودي
B43: رقم الأرض (Land Number) | C43: المساحة الأرض (Land Area) | D43: التكلفة للمتر (Cost per SQM) | E43: تكلفة الأرض قبل الضرائب (Land Cost Before Taxes) | F43: ضريبة التصرفات العقارية (RETT) | G43: السعي (Commission) | H43: ضريبة السعي (Commission tax) | I43: إجمالي تكلفة الأرض بعد الضرائب (Total Land Cost After Taxes) | K43: معامل البناء (FAR) | L43: إجمالي مسطحات البناء فوق الأرض (Above Grade Gross Building Area) | AE43: أدوار | AF43: =SUM(AF7,AF25) -> 0 | AG43: =SUM(AG7,AG25) -> 0 | AH43: =AH7 -> 0 | AI43: =SUM(AI7,AI25) -> 0 | AJ43: =SUM(AJ7,AJ25) -> 0 | AK43: =SUM(AK7,AK25) -> 0 | AL43: =SUM(AL7,AL25) -> 0 | AM43: - | AN43: =SUM(AN7,AN25) -> 0 | AO43: =SUM(AO7,AO25) -> 1 | AP43: =SUM(AP7,AP25) -> 0 | AQ43: =SUM(AQ7,AQ25) -> 0 | AR43: =SUM(AR7,AR25) -> 0 | AS43: =SUM(AS7,AS25) -> 0 | AT43: =SUM(AT7,AT25) -> 0 | AU43: =SUM(AU7,AU25) -> 0 | AV43: =IFERROR((AU43-AT43)/F64, "0") -> 0 | AW43: =SUM(AW7,AW25) -> 0 | AX43: =SUM(AX25,AX7) -> 0 | AY43: =IFERROR(AZ43/F64, "0.00") -> 0.00 | AZ43: =SUM(AZ25,AZ7) -> 0 | BA43: =IFERROR(BD43/AW43, "0.00") -> 0.00 | BB43: =IFERROR(AZ43/AX43, "0.00%") -> 0.00% | BC43: =AZ43/$C$25 -> 0 | BD43: =IFERROR(AZ43/(AU43-AT43), "0.00%") -> 0.00% | BE43: أدوار | BH43: المستفيد (Beneficiaries) | BI43: نسبة المساهمة من إجمالي الملكية (Equity Ownership Percentage) | BJ43: صافي الربح للمستفيدين (Net Profit for Beneficiaries) | BL43: رأس المال + الأرباح | CF43: 35 | CG43: نسبة إجمالي التمويل التشغيلي | CH43: =I31 -> 0.26265485 | CI43: الهيكلة المالية | CJ43: I31 | CK43: نسبة مئوية
B44: 1 | C44: 3000 | D44: 16000 | E44: =D44*C44 -> 48000000 | F44: =(E44*$F$50)*$F$51 -> 720000 | G44: =(E44*$G$50)*$G$51 -> 360000 | H44: =(G44*$H$50)*$H$51 -> 54000 | I44: =SUM(E44:H44) -> 49134000 | K44: 2.05 | L44: =K44*C44 -> 6150 | M44: فندقي | AE44: استديوهات | AF44: =SUM(AF8,AF26) -> 0 | AG44: =SUM(AG8,AG26) -> 0 | AH44: =AH8 -> 0 | AI44: =SUM(AI8,AI26) -> 0 | AJ44: =SUM(AJ8,AJ26) -> 0 | AK44: =SUM(AK8,AK26) -> 0 | AL44: =SUM(AL8,AL26) -> 0 | AM44: - | AN44: =SUM(AN8,AN26) -> 0 | AO44: =SUM(AO8,AO26) -> 1 | AP44: =SUM(AP8,AP26) -> 0 | AQ44: =SUM(AQ8,AQ26) -> 0 | AR44: =SUM(AR8,AR26) -> 0 | AS44: =SUM(AS8,AS26) -> 0 | AT44: =SUM(AT8,AT26) -> 0 | AU44: =SUM(AU8,AU26) -> 0 | AV44: =IFERROR((AU44-AT44)/F65, "0") -> 0 | AW44: =SUM(AW8,AW26) -> 0 | AX44: =SUM(AX26,AX8) -> 0 | AY44: =IFERROR(AZ44/F65, "0.00") -> 0.00 | AZ44: =SUM(AZ26,AZ8) -> 0 | BA44: =IFERROR(BD44/AW44, "0.00") -> 0.00 | BB44: =IFERROR(AZ44/AX44, "0.00%") -> 0.00% | BC44: =AZ44/$C$25 -> 0 | BD44: =IFERROR(AZ44/(AU44-AT44), "0.00%") -> 0.00% | BE44: أستوديوهات | BH44: الاشتراكات النقدية (Cash Subscription) | BI44: =H19/$H$24 -> 0.3182375 | BJ44: =BI44*$C$25 -> 27340809 | BL44: =BJ44+H19 -> 61840809 | CF44: 36 | CG44: إجمالي مصادر التمويل | CH44: =H33 -> 2.2074005e+08 | CI44: الهيكلة المالية | CJ44: H33 | CK44: ريال سعودي
B45: 2 | C45: 1876 | D45: 8000 | E45: =D45*C45 -> 15008000 | F45: =(E45*$F$50)*$F$51 -> 225120 | G45: =(E45*$G$50)*$G$51 -> 112560 | H45: =(G45*$H$50)*$H$51 -> 16884 | I45: =SUM(E45:H45) -> 15362564 | K45: 1.89 | L45: =K45*C45 -> 3545.64 | M45: شقق | AE45: مكتبي | AF45: =SUM(AF9,AF27) -> 0 | AG45: =SUM(AG9,AG27) -> 0 | AH45: =AH9 -> 0 | AI45: =SUM(AI9,AI27) -> 0 | AJ45: =SUM(AJ9,AJ27) -> 0 | AK45: =SUM(AK9,AK27) -> 0 | AL45: =SUM(AL9,AL27) -> 0 | AM45: - | AN45: =SUM(AN9,AN27) -> 1.7167728e-09 | AO45: =SUM(AO9,AO27) -> 1 | AP45: =SUM(AP9,AP27) -> 0.015914983 | AQ45: =SUM(AQ9,AQ27) -> 0 | AR45: =SUM(AR9,AR27) -> 0 | AS45: =SUM(AS9,AS27) -> 0.038309197 | AT45: =SUM(AT9,AT27) -> 0 | AU45: =SUM(AU9,AU27) -> 0 | AV45: =IFERROR((AU45-AT45)/F66, "0") -> 0 | AW45: =SUM(AW9,AW27) -> 0 | AX45: =SUM(AX27,AX9) -> 0 | AY45: =IFERROR(AZ45/F66, "0.00") -> 0.00 | AZ45: =SUM(AZ27,AZ9) -> 0 | BA45: =IFERROR(BD45/AW45, "0.00") -> 0.00 | BB45: =IFERROR(AZ45/AX45, "0.00%") -> 0.00% | BC45: =AZ45/$C$25 -> 0 | BD45: =IFERROR(AZ45/(AU45-AT45), "0.00%") -> 0.00% | BE45: مكتبي | BH45: الاشتراك من مدير الصندوق (fund manager's Subscription) | BI45: =H20/$H$24 -> 0 | BJ45: =BI45*$C$25 -> 0 | BL45: =BJ45+H20 -> 0 | CF45: ▌ تفاصيل الأرض
B46: 3 | C46: 3340 | D46: 8000 | E46: =D46*C46 -> 26720000 | F46: =(E46*$F$50)*$F$51 -> 400800 | G46: =(E46*$G$50)*$G$51 -> 200400 | H46: =(G46*$H$50)*$H$51 -> 30060 | I46: =SUM(E46:H46) -> 27351260 | K46: 1.8 | L46: =K46*C46 -> 6012 | M46: فلل | AE46: تجاري | AF46: =SUM(AF10,AF28) -> 0 | AG46: =SUM(AG10,AG28) -> 0 | AH46: =AH10 -> 0 | AI46: =SUM(AI10,AI28) -> 0 | AJ46: =SUM(AJ10,AJ28) -> 0 | AK46: =SUM(AK10,AK28) -> 0 | AL46: =SUM(AL10,AL28) -> 0 | AM46: - | AN46: =SUM(AN10,AN28) -> 1.7167728e-09 | AO46: =SUM(AO10,AO28) -> 1 | AP46: =SUM(AP10,AP28) -> 0.015914983 | AQ46: =SUM(AQ10,AQ28) -> 0 | AR46: =SUM(AR10,AR28) -> 0 | AS46: =SUM(AS10,AS28) -> 0.038309197 | AT46: =SUM(AT10,AT28) -> 0 | AU46: =SUM(AU10,AU28) -> 0 | AV46: =IFERROR((AU46-AT46)/F67, "0") -> 0 | AW46: =SUM(AW10,AW28) -> 0 | AX46: =SUM(AX28,AX10) -> 0 | AY46: =IFERROR(AZ46/F67, "0.00") -> 0.00 | AZ46: =SUM(AZ28,AZ10) -> 0 | BA46: =IFERROR(BD46/AW46, "0.00") -> 0.00 | BB46: =IFERROR(AZ46/AX46, "0.00%") -> 0.00% | BC46: =AZ46/$C$25 -> 0 | BD46: =IFERROR(AZ46/(AU46-AT46), "0.00%") -> 0.00% | BE46: تجاري | BH46: الأشتراك النقدي من المطور (Cash Subscription from Developer) | BI46: =H21/$H$24 -> 0.10238946 | BJ46: =BI46*$C$25 -> 8796608 | BL46: =BJ46+H21 -> 19896608 | CF46: 37 | CG46: مساحة الأرض الإجمالية | CH46: =C49 -> 8216 | CI46: تفاصيل الأرض | CJ46: C49 | CK46: م²
B47: 4 | E47: =D47*C47 -> 0 | F47: =(E47*$F$50)*$F$51 -> 0 | G47: =(E47*$G$50)*$G$51 -> 0 | H47: =(G47*$H$50)*$H$51 -> 0 | I47: =SUM(E47:H47) -> 0 | L47: =K47*C47 -> 0 | AE47: فندقي | AF47: =SUM(AF11,AF29) -> 49134000 | AG47: =SUM(AG11,AG29) -> 36900000 | AH47: =AH11 -> 1 | AI47: =SUM(AI11,AI29) -> 6162000 | AJ47: =SUM(AJ11,AJ29) -> 14176800 | AK47: =SUM(AK11,AK29) -> 2835360 | AL47: =SUM(AL11,AL29) -> 0 | AM47: - | AN47: =SUM(AN11,AN29) -> 0.53567315 | AO47: =SUM(AO11,AO29) -> 1 | AP47: =SUM(AP11,AP29) -> 4250586.9 | AQ47: =SUM(AQ11,AQ29) -> 10291049 | AR47: =SUM(AR11,AR29) -> 4883185.8 | AS47: =SUM(AS11,AS29) -> 11953363 | AT47: =SUM(AT11,AT29) -> 6405750 | AU47: =SUM(AU11,AU29) -> 1.4699209e+08 | AV47: =IFERROR((AU47-AT47)/F68, "0") -> 39413.049 | AW47: =SUM(AW11,AW29) -> 0.63688644 | AX47: =SUM(AX29,AX11) -> 2.348775e+08 | AY47: =IFERROR(AZ47/F68, "0.00") -> 24638.465 | AZ47: =SUM(AZ29,AZ11) -> 87885405 | BA47: =IFERROR(BD47/AW47, "0.00") -> 0.98154817 | BB47: =IFERROR(AZ47/AX47, "0.00%") -> 0.3741755 | BC47: =AZ47/$C$25 -> 1.0229555 | BD47: =IFERROR(AZ47/(AU47-AT47), "0.00%") -> 0.62513472 | BE47: فندقي | BH47: الأشتراك العيني من المطور (In-Kind Subscription from Developer) | BI47: =H22/$H$24 -> 0 | BJ47: =BI47*$C$25 -> 0 | BL47: =BJ47+H22 -> 0 | CF47: 38 | CG47: التكلفة للمتر | CH47: =D49 -> 10921.13 | CI47: تفاصيل الأرض | CJ47: D49 | CK47: ريال/م²
B48: 5 | E48: =D48*C48 -> 0 | F48: =(E48*$F$50)*$F$51 -> 0 | G48: =(E48*$G$50)*$G$51 -> 0 | H48: =(G48*$H$50)*$H$51 -> 0 | I48: =SUM(E48:H48) -> 0 | L48: =K48*C48 -> 0 | AE48: صحي | AF48: =SUM(AF12,AF30) -> 0 | AG48: =SUM(AG12,AG30) -> 0 | AH48: =AH12 -> 0 | AI48: =SUM(AI12,AI30) -> 0 | AJ48: =SUM(AJ12,AJ30) -> 0 | AK48: =SUM(AK12,AK30) -> 0 | AL48: =SUM(AL12,AL30) -> 0 | AM48: - | AN48: =SUM(AN12,AN30) -> 0 | AO48: =SUM(AO12,AO30) -> 1 | AP48: =SUM(AP12,AP30) -> 0 | AQ48: =SUM(AQ12,AQ30) -> 0 | AR48: =SUM(AR12,AR30) -> 0 | AS48: =SUM(AS12,AS30) -> 0 | AT48: =SUM(AT12,AT30) -> 0 | AU48: =SUM(AU12,AU30) -> 0 | AV48: =IFERROR((AU48-AT48)/F69, "0") -> 0 | AW48: =SUM(AW12,AW30) -> 0 | AX48: =SUM(AX30,AX12) -> 0 | AY48: =IFERROR(AZ48/F69, "0.00") -> 0.00 | AZ48: =SUM(AZ30,AZ12) -> 0 | BA48: =IFERROR(BD48/AW48, "0.00") -> 0.00 | BB48: =IFERROR(AZ48/AX48, "0.00%") -> 0.00% | BC48: =AZ48/$C$25 -> 0 | BD48: =IFERROR(AZ48/(AU48-AT48), "0.00%") -> 0.00% | BE48: صحي | BH48: الإشتراك العيني من مالك الأرض (In-Kind Subscription from Landowner) | BI48: =H23/$H$24 -> 0.57937304 | BJ48: =BI48*$C$25 -> 49775804 | BL48: =BJ48+H23 -> 1.125854e+08 | CF48: 39 | CG48: تكلفة الأرض قبل الضرائب | CH48: =E49 -> 89728000 | CI48: تفاصيل الأرض | CJ48: E49 | CK48: ريال سعودي
B49: الإجمالي (Total) | C49: =SUM(C44:C48) -> 8216 | D49: =E49/C49 -> 10921.13 | E49: =SUM(E44:E48) -> 89728000 | F49: =SUM(F44:F48) -> 1345920 | G49: =SUM(G44:G48) -> 672960 | H49: =SUM(H44:H48) -> 100944 | I49: =SUM(I44:I48) -> 91847824 | K49: =L49/C49 -> 1.9118354 | L49: =SUM(L44:L48) -> 15707.64 | AE49: شاليهات | AF49: =SUM(AF13,AF31) -> 0 | AG49: =SUM(AG13,AG31) -> 0 | AH49: =AH13 -> 0 | AI49: =SUM(AI13,AI31) -> 0 | AJ49: =SUM(AJ13,AJ31) -> 0 | AK49: =SUM(AK13,AK31) -> 0 | AL49: =SUM(AL13,AL31) -> 0 | AM49: - | AN49: =SUM(AN13,AN31) -> 0 | AO49: =SUM(AO13,AO31) -> 1 | AP49: =SUM(AP13,AP31) -> 0 | AQ49: =SUM(AQ13,AQ31) -> 0 | AR49: =SUM(AR13,AR31) -> 0 | AS49: =SUM(AS13,AS31) -> 0 | AT49: =SUM(AT13,AT31) -> 0 | AU49: =SUM(AU13,AU31) -> 0 | AV49: =IFERROR((AU49-AT49)/F70, "0") -> 0 | AW49: =SUM(AW13,AW31) -> 0 | AX49: =SUM(AX31,AX13) -> 0 | AY49: =IFERROR(AZ49/F70, "0.00") -> 0.00 | AZ49: =SUM(AZ31,AZ13) -> 0 | BA49: =IFERROR(BD49/AW49, "0.00") -> 0.00 | BB49: =IFERROR(AZ49/AX49, "0.00%") -> 0.00% | BC49: =AZ49/$C$25 -> 0 | BD49: =IFERROR(AZ49/(AU49-AT49), "0.00%") -> 0.00% | BE49: شاليهات | BH49: - | BI49: =SUM(BI44:BI48)=100% -> TRUE | BJ49: =SUM(BJ44:BJ48)=C25 -> TRUE | BL49: =SUM(BL44:BL48) -> 1.9432282e+08 | CF49: 40 | CG49: ضريبة التصرفات العقارية (RETT) | CH49: =F49 -> 1345920 | CI49: تفاصيل الأرض | CJ49: F49 | CK49: ريال سعودي
F50: 0.05 | G50: 0.025 | H50: 0.15 | AE50: الإجمالي | AF50: =SUM(AF40:AF49) -> 1.2276992e+08 | AG50: =SUM(AG40:AG49) -> 57926808 | AH50: =SUM(AH40:AH49) -> 1 | AI50: =SUM(AI40:AI49) -> 6162000 | AJ50: =SUM(AJ40:AJ49) -> 14176800 | AK50: =SUM(AK40:AK49) -> 2835360 | AL50: =SUM(AL40:AL49) -> 0 | AM50: - | AN50: =SUM(AN40:AN49) -> 1 | AO50: - | AP50: =SUM(AP40:AQ49) -> 19772337 | AR50: =SUM(AR40:AR49) -> 7141903.3 | AS50: =SUM(AS40:AS49) -> 22314657 | AT50: =SUM(AT40:AT49) -> 6529315.6 | AU50: =SUM(AU40:AU49) -> 2.0839884e+08 | AV50: =AU50/F76 -> 21006.267 | AW50: =SUM(AW40:AW49) -> 0.91451247 | AX50: =SUM(AX40:AX49) -> 3.1318259e+08 | AY50: =AZ50/F76 -> 5876.2217 | AZ50: =SUM(AZ40:AZ49) -> 58296785 | BA50: - | BB50: =IFERROR(AZ50/AX50, "0.00%") -> 0.18614312 | BC50: - | BD50: =IFERROR(AZ50/AU50, "0.00%") -> 0.27973661 | CF50: 41 | CG50: السعي (Commission) | CH50: =G49 -> 672960 | CI50: تفاصيل الأرض | CJ50: G49 | CK50: ريال سعودي
F51: 0.3 | G51: =F51 -> 0.3 | H51: 1 | AF51: =AF50=I49 -> FALSE | AG51: =AG50=SUM(J61:J71) -> TRUE | AH51: =AH50=100% -> TRUE | AI51: =AI50=J73 -> TRUE | AJ51: =AJ50=SUM(J74:J75) -> TRUE | AK51: =AK50=C87 -> TRUE | AL51: =AL50=J71 -> TRUE | AM51: =AM50=AM50 -> TRUE | AN51: =ABS(AN50 - 1) <= 0.0001 -> TRUE | AO51: =AO50=AO50 -> TRUE | AP51: =ABS(AP50 - (C102 - C87)) <= 0.9 -> FALSE | AR51: =AR50=C119 -> TRUE | AS51: =ABS(AS50 - C107) <= 0.9 -> TRUE | AT51: =AT50=C24 -> TRUE | AU51: =ABS(AU50 - (C23 + C24)) <= 0.9 -> FALSE | AV51: =AV50=AV50 -> TRUE | AW51: =ABS(AW50 - 1) <= 0.0001 -> FALSE | AX51: =AX50=C17 -> TRUE | AY51: =AY50=AY50 -> TRUE | AZ51: =ABS(AZ50 - C25) <= 0.9 -> FALSE | BA51: =BA50=BA50 -> TRUE | BB51: =BB50=BB50 -> TRUE | BC51: =BC50=BC50 -> TRUE | BD51: =BD50=BD50 -> TRUE | CF51: 42 | CG51: ضريبة السعي | CH51: =H49 -> 100944 | CI51: تفاصيل الأرض | CJ51: H49 | CK51: ريال سعودي
CF52: 43 | CG52: إجمالي تكلفة الأرض بعد الضرائب | CH52: =I49 -> 91847824 | CI52: تفاصيل الأرض | CJ52: I49 | CK52: ريال سعودي
CF53: 44 | CG53: معامل البناء (FAR) | CH53: =K49 -> 1.9118354 | CI53: تفاصيل الأرض | CJ53: K49 | CK53: معامل
CF54: 45 | CG54: إجمالي مسطحات البناء فوق الأرض | CH54: =L49 -> 15707.64 | CI54: تفاصيل الأرض | CJ54: L49 | CK54: م²
CF55: ▌ تفاصيل البناء
B56: Construction Details and Costs | تفاصيل البناء و تكاليفة | CF56: 46 | CG56: معامل البناء (FAR) | CH56: =D59 -> 0 | CI56: تفاصيل البناء | CJ56: D59 | CK56: معامل
CF57: 47 | CG57: إجمالي المساحة التطويرية | CH57: =E59 -> 0 | CI57: تفاصيل البناء | CJ57: E59 | CK57: م²
B58: طول الأرض على الشارع (Land Frontage) | C58: عمق الأرض (Land Depth) | D58: عدد أدوار المشروع (Total Project Floors) | E58: عدد عماير المشروع (Total Project Building) | F58: معامل البناء (FAR) | G58: إجمالي المساحة التطويرية (Total Development Area) | H58: إجمالي المساحة المبنية (Gross Built-Up Area) | I58: إجمالي المساحة البنائية فوق مستوى الأرض (Above Grade Gross Building Area) | J58: إجمالي المساحات القابلة للبيع (Net Sellable Area) | K58: المواقف (Parking) | L58: معيار المواقف (Parking Standards) | CF58: 48 | CG58: إجمالي المساحة المبنية (GBA) | CH58: =F59 -> 1.9118354 | CI58: تفاصيل البناء | CJ58: F59 | CK58: م²
B59: 0 | C59: 0 | D59: 0 | E59: 0 | F59: =K49 -> 1.9118354 | G59: =SUM(D61:D75) -> 31799.64 | H59: =SUM(D61:D71,D74:D75) -> 23583.64 | I59: =SUM(D61:D71) -> 15707.64 | J59: =F76 -> 9920.794 | CF59: 49 | CG59: إجمالي المساحة فوق مستوى الأرض | CH59: =H59 -> 23583.64 | CI59: تفاصيل البناء | CJ59: H59 | CK59: م²
B60: المكون (Component) | C60: نسبة المكون من المساحة البنائية (GBA-%) | D60: إجمالي المساحة البنائية للمكون (GBA) | E60: نسبة المساحات الصافية القابلة للبيع (NSA-%) | F60: المساحات الصافية القابلة للبيع (NSA) | G60: عدد الوحدات (Number of Units) | H60: مساحة الوحدة (Unit Area) | I60: تكلفة متر البناء (Construction cost Per m²) | J60: اجمالي التكاليف (Total Costs) | K60: =B59/L60 -> 0 | L60: 3.5 | CF60: 50 | CG60: إجمالي المساحات القابلة للبيع (NSA) | CH60: =J59 -> 9920.794 | CI60: تفاصيل البناء | CJ60: J59 | CK60: م²
B61: سكني (Apartments) | C61: 0.2257271 | D61: =$L$49*C61 -> 3545.64 | E61: 0.85 | F61: =E61*D61 -> 3013.794 | G61: 12 | H61: =IFERROR(F61/G61, "0.00") -> 251.1495 | I61: 2200 | J61: =I61*D61 -> 7800408 | K61: =L61*G61 -> 12 | L61: 1 | CF61: 51 | CG61: معيار المواقف | CH61: =L60 -> 3.5 | CI61: تفاصيل البناء | CJ61: L60 | CK61: موقف/وحدة
B62: فلل* (Villas) | C62: 0.38274368 | D62: =$L$49*C62 -> 6012 | E62: 1 | F62: =C77*$C$46 -> 3340 | G62: 11 | H62: =IFERROR(F62/G62, "0.00") -> 303.63636 | I62: 2200 | J62: =I62*D62 -> 13226400 | K62: =L62*G62 -> 0 | L62: 0 | CF62: ▌ مكوّن البناء - سكني
B63: تاون هاوس* (Townhouse) | C63: 0 | D63: =$L$49*C63 -> 0 | E63: 0 | F63: =C78*$C$49 -> 0 | H63: =IFERROR(F63/G63, "0.00") -> 0.00 | J63: =I63*D63 -> 0 | K63: =L63*G63 -> 0 | L63: 0 | CF63: 52 | CG63: سكني - نسبة من المساحة البنائية | CH63: =C61 -> 0.2257271 | CI63: مكوّن البناء - سكني | CJ63: C61 | CK63: نسبة مئوية
B64: أدوار (Floors) | C64: 0 | D64: =$L$49*C64 -> 0 | E64: 0 | F64: =E64*D64 -> 0 | H64: =IFERROR(F64/G64, "0.00") -> 0.00 | J64: =I64*D64 -> 0 | K64: =L64*G64 -> 0 | L64: 0 | CF64: 53 | CG64: سكني - إجمالي المساحة البنائية (GBA) | CH64: =D61 -> 3545.64 | CI64: مكوّن البناء - سكني | CJ64: D61 | CK64: م²
B65: أستوديوهات (Studios) | C65: 0 | D65: =$L$49*C65 -> 0 | E65: 0 | F65: =E65*D65 -> 0 | H65: =IFERROR(F65/G65, "0.00") -> 0.00 | J65: =I65*D65 -> 0 | K65: =L65*G65 -> 0 | L65: 1 | CF65: 54 | CG65: سكني - نسبة المساحات القابلة للبيع | CH65: =E61 -> 0.85 | CI65: مكوّن البناء - سكني | CJ65: E61 | CK65: نسبة مئوية
B66: مكتبي (Office) | C66: 0 | D66: =$L$49*C66 -> 0 | E66: 0 | F66: =E66*D66 -> 0 | H66: =IFERROR(F66/G66, "0.00") -> 0.00 | J66: =I66*D66 -> 0 | K66: =F66/L66 -> 0 | L66: 25 | CF66: 55 | CG66: سكني - المساحات الصافية القابلة للبيع (NSA) | CH66: =F61 -> 3013.794 | CI66: مكوّن البناء - سكني | CJ66: F61 | CK66: م²
B67: تجاري (Retail) | C67: 0 | D67: =$L$49*C67 -> 0 | E67: 0 | F67: =E67*D67 -> 0 | H67: =IFERROR(F67/G67, "0.00") -> 0.00 | J67: =I67*D67 -> 0 | K67: =F67/L67 -> 0 | L67: 45 | CF67: 56 | CG67: سكني - مساحة الوحدة | CH67: =G61 -> 12 | CI67: مكوّن البناء - سكني | CJ67: G61 | CK67: م²
B68: فندقي (Hotel) | C68: 0.39152922 | D68: =$L$49*C68 -> 6150 | E68: 0.58 | F68: =E68*D68 -> 3567 | G68: 100 | H68: =IFERROR(F68/G68, "0.00") -> 35.67 | I68: 6000 | J68: =I68*D68 -> 36900000 | K68: =G68/L68 -> 50 | L68: 2 | CF68: 57 | CG68: سكني - عدد الوحدات | CH68: =H61 -> 251.1495 | CI68: مكوّن البناء - سكني | CJ68: H61 | CK68: وحدة
B69: صحي (health) | C69: 0 | D69: =$L$49*C69 -> 0 | F69: =E69*D69 -> 0 | H69: =IFERROR(F69/G69, "0.00") -> 0.00 | J69: =I69*D69 -> 0 | K69: =F69/L69 -> 0 | L69: 35 | CF69: 58 | CG69: سكني - تكلفة متر البناء | CH69: =I61 -> 2200 | CI69: مكوّن البناء - سكني | CJ69: I61 | CK69: ريال/م²
B70: شاليهات (Chalets) | D70: =$L$49*C70 -> 0 | F70: =E70*D70 -> 0 | H70: =IFERROR(F70/G70, "0.00") -> 0.00 | J70: =I70*D70 -> 0 | K70: 0 | L70: لا يــــنــطــبــق | CF70: 59 | CG70: سكني - إجمالي التكاليف | CH70: =J61 -> 7800408 | CI70: مكوّن البناء - سكني | CJ70: J61 | CK70: ريال سعودي
B71: المساحات الحركية والخدمية (Circulation & Service Areas) | C71: =100%-SUM(C61:C70) -> 0 | D71: =$L$49*C71 -> 0 | E71: لا يــــنــطــبــق | F71: لا يــــنــطــبــق | G71: لا يــــنــطــبــق | H71: لا يــــنــطــبــق | J71: =I71*D71 -> 0 | K71: لا يــــنــطــبــق | L71: لا يــــنــطــبــق | CF71: 60 | CG71: سكني - عدد المواقف | CH71: =K61 -> 12 | CI71: مكوّن البناء - سكني | CJ71: K61 | CK71: موقف
B72: - | C72: - | D72: - | E72: - | F72: - | G72: - | H72: - | I72: - | J72: - | K72: - | L72: - | CF72: 61 | CG72: سكني - معيار المواقف | CH72: =L61 -> 1 | CI72: مكوّن البناء - سكني | CJ72: L61 | CK72: معيار
B73: لاند سكيب* (Landscape) | C73: 1 | D73: =$C$49*C73 -> 8216 | E73: لا يــــنــطــبــق | F73: لا يــــنــطــبــق | G73: لا يــــنــطــبــق | H73: لا يــــنــطــبــق | I73: 750 | J73: =I73*D73 -> 6162000 | K73: لا يــــنــطــبــق | L73: لا يــــنــطــبــق | CF73: ▌ مكوّن البناء - فلل
B74: البدروم* (Basement) | C74: 0.95861733 | D74: {=SUM(C44:C46*C74)} -> 7876 | E74: لا يــــنــطــبــق | F74: لا يــــنــطــبــق | G74: لا يــــنــطــبــق | H74: لا يــــنــطــبــق | I74: 1800 | J74: =I74*D74 -> 14176800 | K74: =D74/L74 -> 175.02222 | L74: 45 | CF74: 62 | CG74: فلل - نسبة من المساحة البنائية | CH74: =C62 -> 0.38274368 | CI74: مكوّن البناء - فلل | CJ74: C62 | CK74: نسبة مئوية
B75: بوديوم* (Podium) | C75: 0 | D75: =$C$49*C75 -> 0 | E75: لا يــــنــطــبــق | F75: لا يــــنــطــبــق | G75: لا يــــنــطــبــق | H75: لا يــــنــطــبــق | I75: 0 | J75: =I75*D75 -> 0 | K75: =D75/L75 -> 0 | L75: 45 | CF75: 63 | CG75: فلل - إجمالي المساحة البنائية (GBA) | CH75: =D62 -> 6012 | CI75: مكوّن البناء - فلل | CJ75: D62 | CK75: م²
B76: الإجمالي (Total) | C76: =SUM(C61:C71) -> 1 | D76: =SUM(D61:D75) -> 31799.64 | E76: =SUMPRODUCT(E61:E70, C61:C70) / SUM(C61:C70) -> 0.80169866 | F76: =SUMIF(F61:F70, "<>#DIV/0!") -> 9920.794 | G76: =SUMIF(G61:G75, "<>#DIV/0!") -> 123 | H76: =IFERROR(F76/G76, "0.00") -> 80.656862 | I76: =J76/D76 -> 2461.2105 | J76: =SUM(J61:J75) -> 78265608 | K76: إجمالي المواقف المطلوبة (Total Required Parking Spaces) | L76: =SUMIF(K61:K69, "<>#DIV/0!") -> 62 | CF76: 64 | CG76: فلل - نسبة المساحات القابلة للبيع | CH76: =E62 -> 1 | CI76: مكوّن البناء - فلل | CJ76: E62 | CK76: نسبة مئوية
B77: من مساحة الأرض* (Based on Land Area) | C77: 1 | K77: إجمالي المواقف المتوفرة (Total Available Parking Spaces) | L77: =SUM(K60,K74:K75) -> 175.02222 | CF77: 65 | CG77: فلل - المساحات الصافية القابلة للبيع (NSA) | CH77: =F62 -> 3340 | CI77: مكوّن البناء - فلل | CJ77: F62 | CK77: م²
C78: 0 | K78: فارق المواقف (Parking Deficit) | L78: =L77-L76 -> 113.02222 | CF78: 66 | CG78: فلل - مساحة الوحدة | CH78: =G62 -> 11 | CI78: مكوّن البناء - فلل | CJ78: G62 | CK78: م²
CF79: 67 | CG79: فلل - عدد الوحدات | CH79: =H62 -> 303.63636 | CI79: مكوّن البناء - فلل | CJ79: H62 | CK79: وحدة
CF80: 68 | CG80: فلل - تكلفة متر البناء | CH80: =I62 -> 2200 | CI80: مكوّن البناء - فلل | CJ80: I62 | CK80: ريال/م²
CF81: 69 | CG81: فلل - إجمالي التكاليف | CH81: =J62 -> 13226400 | CI81: مكوّن البناء - فلل | CJ81: J62 | CK81: ريال سعودي
CF82: 70 | CG82: فلل - عدد المواقف | CH82: =K62 -> 0 | CI82: مكوّن البناء - فلل | CJ82: K62 | CK82: موقف
CF83: 71 | CG83: فلل - معيار المواقف | CH83: =L62 -> 0 | CI83: مكوّن البناء - فلل | CJ83: L62 | CK83: معيار
B84: Other Cost | التكاليف الأخرى | E84: نسبة البند من الإجمالي (Percentage) | CF84: ▌ مكوّن البناء - تاون هاوس
B85: البند (Item) | C85: القيمة (Value) | D85: المعيار (Standard) | E85: % | CF85: 72 | CG85: تاون هاوس - نسبة من المساحة البنائية | CH85: =C63 -> 0 | CI85: مكوّن البناء - تاون هاوس | CJ85: C63 | CK85: نسبة مئوية
B86: التسوير (Fencing) | C86: =D86*C49 -> 534040 | D86: 65 | E86: =C86/$C$102 -> 0.025226195 | CF86: 73 | CG86: تاون هاوس - إجمالي المساحة البنائية (GBA) | CH86: =D63 -> 0 | CI86: مكوّن البناء - تاون هاوس | CJ86: D63 | CK86: م²
B87: الحفر والمسح والاختبار (Excavation, surveying, and testing) | C87: =(D74)*4.5*D87 -> 2835360 | D87: 80 | E87: =C87/$C$102 -> 0.13393256 | CF87: 74 | CG87: تاون هاوس - نسبة المساحات القابلة للبيع | CH87: =E63 -> 0 | CI87: مكوّن البناء - تاون هاوس | CJ87: E63 | CK87: نسبة مئوية
B88: التأمين (Insurance) | C88: =D88*C110 -> 1330515.3 | D88: 0.017 | E88: =C88/$C$102 -> 0.062848923 | CF88: 75 | CG88: تاون هاوس - المساحات الصافية القابلة للبيع (NSA) | CH88: =F63 -> 0 | CI88: مكوّن البناء - تاون هاوس | CJ88: F63 | CK88: م²
B89: الرخصة (License) | C89: =D89*I59 -> 62830.56 | D89: 4 | E89: =C89/$C$102 -> 0.0029678974 | CF89: 76 | CG89: تاون هاوس - مساحة الوحدة | CH89: =G63 -> 0 | CI89: مكوّن البناء - تاون هاوس | CJ89: G63 | CK89: م²
B90: التصميم (Design) | C90: =D90*C110 -> 3913280.4 | D90: 0.05 | E90: =C90/$C$102 -> 0.18484977 | CF90: 77 | CG90: تاون هاوس - عدد الوحدات | CH90: =H63 -> 0.00 | CI90: مكوّن البناء - تاون هاوس | CJ90: H63 | CK90: وحدة
B91: أثاث الوحدات الفندقية (Hotel Furniture Units) | C91: =D91*D68 -> 6150000 | D91: 1000 | E91: =C91/$C$102 -> 0.29050464 | CF91: 78 | CG91: تاون هاوس - تكلفة متر البناء | CH91: =I63 -> 0 | CI91: مكوّن البناء - تاون هاوس | CJ91: I63 | CK91: ريال/م²
B92: أثاث الوحدات (Furniture Units) | C92: =D92*SUM(H61,H65,H66) -> 0 | D92: 0 | E92: =C92/$C$102 -> 0 | CF92: 79 | CG92: تاون هاوس - إجمالي التكاليف | CH92: =J63 -> 0 | CI92: مكوّن البناء - تاون هاوس | CJ92: J63 | CK92: ريال سعودي
B93: رسوم الكهرباء (Electricity fees) | C93: =D93*SUM(G61:G67,G69:G70)+(D93*(G68/2)) -> 912500 | D93: 12500 | E93: =C93/$C$102 -> 0.04310333 | CF93: 80 | CG93: تاون هاوس - عدد المواقف | CH93: =K63 -> 0 | CI93: مكوّن البناء - تاون هاوس | CJ93: K63 | CK93: موقف
B94: رسوم الماء وصرف الصحي (Water and sewer fees) | C94: =D94*$G$76 -> 984000 | D94: 8000 | E94: =C94/$C$102 -> 0.046480742 | CF94: 81 | CG94: تاون هاوس - معيار المواقف | CH94: =L63 -> 0 | CI94: مكوّن البناء - تاون هاوس | CJ94: L63 | CK94: معيار
B95: الفرز (Sorting) | C95: =D95*(C129+C130) -> 18000 | D95: 1500 | E95: =C95/$C$102 -> 0.00085025747 | CF95: ▌ مكوّن البناء - أدوار
B96: الصيانة و التشغيل (Maintenance and Operation) | C96: =D96*(G61+G62) -> 299000 | D96: 13000 | E96: =C96/$C$102 -> 0.014123721 | CF96: 82 | CG96: أدوار - نسبة من المساحة البنائية | CH96: =C64 -> 0 | CI96: مكوّن البناء - أدوار | CJ96: C64 | CK96: نسبة مئوية
B97: الاحتياطي (Contingency) | C97: =D97*C110 -> 1173984.1 | D97: 0.015 | E97: =C97/$C$102 -> 0.055454932 | CF97: 83 | CG97: أدوار - إجمالي المساحة البنائية (GBA) | CH97: =D64 -> 0 | CI97: مكوّن البناء - أدوار | CJ97: D64 | CK97: م²
B98: تسويق المبيعات (Sales Marketing) | C98: =D98*(J139+M157) -> 46954.911 | D98: 0.02 | E98: =C98/$C$102 -> 0.0022179869 | CF98: 84 | CG98: أدوار - نسبة المساحات القابلة للبيع | CH98: =E64 -> 0 | CI98: مكوّن البناء - أدوار | CJ98: E64 | CK98: نسبة مئوية
B99: تسويق التأجير (Leasing Marketing) | C99: =D99*(SUM(C185:C186)) -> 952952.44 | D99: 0.04 | E99: =C99/$C$102 -> 0.045014163 | CF99: 85 | CG99: أدوار - المساحات الصافية القابلة للبيع (NSA) | CH99: =F64 -> 0 | CI99: مكوّن البناء - أدوار | CJ99: F64 | CK99: م²
B100: تسويق البيع على الخارطة (Off-Plan Sales Marketing) | C100: =D100*Y139 -> 0 | D100: 0 | E100: =C100/$C$102 -> 0 | CF100: 86 | CG100: أدوار - مساحة الوحدة | CH100: =G64 -> 0 | CI100: مكوّن البناء - أدوار | CJ100: G64 | CK100: م²
...

Sheet Summary
B1: رصف للاستثمار | RASF Investment
B6: Values shown are SAR except where stated | القيم المعروضة هي بالريال سعودي باستثناء ما هو مذكور | E6: NSA.m² | Net Sellable Area|TDA.m² | Total Development Area|LA.m² | Total Land Area NSA.m² | المساحات الصافية القابلة للبيع |TDA.m² | إجمالي المساحة التطويرية | LA.m² | مساحة الأرض الإجمالية
C10: Summary | ملخص
I12: (Area) - المساحة | J12: (SR/m²) - ر.س/م² | K12: الإجمالي - (Total)
C13: تكلفة شراء الأرض - باستثناء الضرائب والعمولات (Land purchase cost - except taxes & commissions) | I13: =Study!C49 -> 8216 | J13: =Study!D49 -> 10921.13 | K13: =I13*J13 -> 89728000
C14: التكلفة الإجمالية للمشروع (Total project cost) | I14: =Study!G59 -> 31799.64 | J14: =K14/I14 -> 6941.5896 | K14: =Study!C23 -> 2.2074005e+08
C15: إجمالي الإيرادات (Total Revenue) | I15: =Study!J59 -> 9920.794 | J15: =K15/I15 -> 31568.299 | K15: =Study!C17 -> 3.1318259e+08
C17: نمو قيمة الأرض للمتر - Land Value Uplift per SQM | I17: وقت الشراء | J17: وقت البيع | K17: الفارق
I19: =K95/I13 -> 5980.2824 | J19: =((K95/K14)*K15)/I13 -> 8484.7326 | K19: =J19-I19 -> 2504.4502
C21: المؤشرات المالية | Financial Indicators | H21: معدل العائد الداخلي IRR | I21: العائد على الإستثمار ROI | J21: العائد على الملكية ROE | K21: العائد على الملكية سنوياَ ROE Annualy
H24: =Study!C28 -> 0.13308131 | I24: =Study!C30 -> 0.3892054 | J24: =Study!C32 -> 0.7924872 | K24: =Study!C34 -> 0.15849744
C27: التفاصيل الفنية و المالية لجميع للمكونات | Technical and Financial Details For All Components | D27: عدد الوحدات (Number of Units) | E27: مساحة الوحدة (One Unit Area) | H27: إجمالي تكاليف كل مكون (Total cost per component) | I27: صافي العائد لكل م² بيعي (Net return per NSA.m²) | J27: صافي دخل كل مكون (Net Income per Component) | K27: نسبة عائد كل مكون (Return % per Component)
C29: سكني (Apartments) | D29: =Study!G61 -> 12 | E29: =Study!H61 -> 251.1495 | H29: =Study!AU40 -> 28494043 | I29: =Study!AY4 -> 1102.9575 | J29: =Study!AZ4 -> 3324086.8 | K29: =Study!BD4 -> 0.11716711
C30: فلل (Villas) | D30: =Study!G62 -> 11 | E30: =Study!H62 -> 303.63636 | H30: =Study!AU41 -> 32912707 | I30: =Study!AY5 -> -9854.1038 | J30: =Study!AZ5 -> -32912707 | K30: =Study!BD5 -> -1
C31: تاون هاوس (Townhouse) | D31: =Study!G63 -> 0 | E31: =Study!H63 -> 0.00 | H31: =Study!AU42 -> 0 | I31: =Study!AY6 -> 0.00 | J31: =Study!AZ6 -> 0 | K31: =Study!BD6 -> 0.00%
C32: أدوار (Floors) | D32: =Study!G64 -> 0 | E32: =Study!H64 -> 0.00 | H32: =Study!AU43 -> 0 | I32: =Study!AY7 -> 0.00 | J32: =Study!AZ7 -> 0 | K32: =Study!BD7 -> 0.00%
C33: أستوديوهات (Studios) | D33: =Study!G65 -> 0 | E33: =Study!H65 -> 0.00 | H33: =Study!AU44 -> 0 | I33: =Study!AY8 -> 0.00 | J33: =Study!AZ8 -> 0 | K33: =Study!BD8 -> 0.00%
C34: مكتبي (Office) | D34: =Study!G66 -> 0 | E34: =Study!H66 -> 0.00 | H34: =Study!AU45 -> 0 | I34: =Study!AY9 -> 0.00 | J34: =Study!AZ9 -> 0 | K34: =Study!BD9 -> 0.00%
C35: تجاري (Retail) | D35: =Study!G67 -> 0 | E35: =Study!H67 -> 0.00 | H35: =Study!AU46 -> 0 | I35: =Study!AY10 -> 0.00 | J35: =Study!AZ10 -> 0 | K35: =Study!BD10 -> 0.00%
C36: فندقي (Hotel) | D36: =Study!G68 -> 100 | E36: =Study!H68 -> 35.67 | H36: =Study!AU47 -> 1.4699209e+08 | I36: =Study!AY11 -> 24638.465 | J36: =Study!AZ11 -> 87885405 | K36: =Study!BD11 -> 0.62513472
C37: صحي (health) | D37: =Study!G69 -> 0 | E37: =Study!H69 -> 0.00 | H37: =Study!AU48 -> 0 | I37: =Study!AY12 -> 0.00 | J37: =Study!AZ12 -> 0 | K37: =Study!BD12 -> 0.00%
C38: شاليهات (Chalets) | D38: =Study!G70 -> 0 | E38: =Study!H70 -> 0.00 | H38: =Study!AU49 -> 0 | I38: =Study!AY13 -> 0.00 | J38: =Study!AZ13 -> 0 | K38: =Study!BD13 -> 0.00%
E40: 1 | F40: 2 | G40: 3 | H40: 4 | I40: 5 | J40: 6 | K40: =Study!B122 -> 5
C42: رخصة البناء و التصميم (Design & License) | D42: =Study!C344 -> 46388 | E42: =IF(ABS(SUM(OFFSET(Study!$F$200,0,(COLUMN()-COLUMN($E$42))*4,2,4)))<0.01,"",SUM(OFFSET(Study!$F$200,0,(COLUMN()-COLUMN($E$42))*4,2,4))) -> -2608853.6 | F42: =IF(ABS(SUM(OFFSET(Study!$F$200,0,(COLUMN()-COLUMN($E$42))*4,2,4)))<0.01,"",SUM(OFFSET(Study!$F$200,0,(COLUMN()-COLUMN($E$42))*4,2,4))) -> -1367257.4 | G42: =IF(ABS(SUM(OFFSET(Study!$F$200,0,(COLUMN()-COLUMN($E$42))*4,2,4)))<0.01,"",SUM(OFFSET(Study!$F$200,0,(COLUMN()-COLUMN($E$42))*4,2,4))) | H42: =IF(ABS(SUM(OFFSET(Study!$F$200,0,(COLUMN()-COLUMN($E$42))*4,2,4)))<0.01,"",SUM(OFFSET(Study!$F$200,0,(COLUMN()-COLUMN($E$42))*4,2,4))) | I42: =IF(ABS(SUM(OFFSET(Study!$F$200,0,(COLUMN()-COLUMN($E$42))*4,2,4)))<0.01,"",SUM(OFFSET(Study!$F$200,0,(COLUMN()-COLUMN($E$42))*4,2,4))) | J42: =IF(ABS(SUM(OFFSET(Study!$F$200,0,(COLUMN()-COLUMN($E$42))*4,2,4)))<0.01,"",SUM(OFFSET(Study!$F$200,0,(COLUMN()-COLUMN($E$42))*4,2,4))) | K42: =Study!H344 -> 46934
C43: -------------------------------------------
C44: فوائد التمويل (Interest) | D44: =Study!C345 -> 47027 | E44: =IF(ABS(SUM(OFFSET(Study!$F$192,0,(COLUMN()-COLUMN($E$44))*4,2,4)))<0.0001,"",SUM(OFFSET(Study!$F$192,0,(COLUMN()-COLUMN($E$44))*4,2,4))) -> -271760.03 | F44: =IF(ABS(SUM(OFFSET(Study!$F$192,0,(COLUMN()-COLUMN($E$44))*4,2,4)))<0.0001,"",SUM(OFFSET(Study!$F$192,0,(COLUMN()-COLUMN($E$44))*4,2,4))) -> -46574.109 | G44: =IF(ABS(SUM(OFFSET(Study!$F$192,0,(COLUMN()-COLUMN($E$44))*4,2,4)))<0.0001,"",SUM(OFFSET(Study!$F$192,0,(COLUMN()-COLUMN($E$44))*4,2,4))) -> -551296.44 | H44: =IF(ABS(SUM(OFFSET(Study!$F$192,0,(COLUMN()-COLUMN($E$44))*4,2,4)))<0.0001,"",SUM(OFFSET(Study!$F$192,0,(COLUMN()-COLUMN($E$44))*4,2,4))) -> -2381771.4 | I44: =IF(ABS(SUM(OFFSET(Study!$F$192,0,(COLUMN()-COLUMN($E$44))*4,2,4)))<0.0001,"",SUM(OFFSET(Study!$F$192,0,(COLUMN()-COLUMN($E$44))*4,2,4))) -> -3890501.3 | J44: =IF(ABS(SUM(OFFSET(Study!$F$192,0,(COLUMN()-COLUMN($E$44))*4,2,4)))<0.0001,"",SUM(OFFSET(Study!$F$192,0,(COLUMN()-COLUMN($E$44))*4,2,4))) | K44: =Study!H345 -> 48213
C45: -------------------------------------------
C46: تكاليف البناء (Construction Costs) | D46: =Study!C346 -> 46844 | E46: =IF(ABS(SUM(OFFSET(Study!$F$196,0,(COLUMN()-COLUMN($E$46))*4,1,4)))<0.0001,"",SUM(OFFSET(Study!$F$196,0,(COLUMN()-COLUMN($E$46))*4,1,4))) | F46: =IF(ABS(SUM(OFFSET(Study!$F$196,0,(COLUMN()-COLUMN($E$46))*4,1,4)))<0.0001,"",SUM(OFFSET(Study!$F$196,0,(COLUMN()-COLUMN($E$46))*4,1,4))) -> -16435778 | G46: =IF(ABS(SUM(OFFSET(Study!$F$196,0,(COLUMN()-COLUMN($E$46))*4,1,4)))<0.0001,"",SUM(OFFSET(Study!$F$196,0,(COLUMN()-COLUMN($E$46))*4,1,4))) -> -39915460 | H46: =IF(ABS(SUM(OFFSET(Study!$F$196,0,(COLUMN()-COLUMN($E$46))*4,1,4)))<0.0001,"",SUM(OFFSET(Study!$F$196,0,(COLUMN()-COLUMN($E$46))*4,1,4))) -> -21914370 | I46: =IF(ABS(SUM(OFFSET(Study!$F$196,0,(COLUMN()-COLUMN($E$46))*4,1,4)))<0.0001,"",SUM(OFFSET(Study!$F$196,0,(COLUMN()-COLUMN($E$46))*4,1,4))) | J46: =IF(ABS(SUM(OFFSET(Study!$F$196,0,(COLUMN()-COLUMN($E$46))*4,1,4)))<0.0001,"",SUM(OFFSET(Study!$F$196,0,(COLUMN()-COLUMN($E$46))*4,1,4))) | K46: =Study!H346 -> 47848
C47: -------------------------------------------
C48: الخدمات (Infrastructure services) | D48: =Study!C347 -> 47757 | E48: =IF(ABS(SUM(OFFSET(Study!$F$204,0,(COLUMN()-COLUMN($E$48))*4,3,4)))<0.0001,"",SUM(OFFSET(Study!$F$204,0,(COLUMN()-COLUMN($E$48))*4,3,4))) | F48: =IF(ABS(SUM(OFFSET(Study!$F$204,0,(COLUMN()-COLUMN($E$48))*4,3,4)))<0.0001,"",SUM(OFFSET(Study!$F$204,0,(COLUMN()-COLUMN($E$48))*4,3,4))) | G48: =IF(ABS(SUM(OFFSET(Study!$F$204,0,(COLUMN()-COLUMN($E$48))*4,3,4)))<0.0001,"",SUM(OFFSET(Study!$F$204,0,(COLUMN()-COLUMN($E$48))*4,3,4))) | H48: =IF(ABS(SUM(OFFSET(Study!$F$204,0,(COLUMN()-COLUMN($E$48))*4,3,4)))<0.0001,"",SUM(OFFSET(Study!$F$204,0,(COLUMN()-COLUMN($E$48))*4,3,4))) -> -1914500 | I48: =IF(ABS(SUM(OFFSET(Study!$F$204,0,(COLUMN()-COLUMN($E$48))*4,3,4)))<0.0001,"",SUM(OFFSET(Study!$F$204,0,(COLUMN()-COLUMN($E$48))*4,3,4))) | J48: =IF(ABS(SUM(OFFSET(Study!$F$204,0,(COLUMN()-COLUMN($E$48))*4,3,4)))<0.0001,"",SUM(OFFSET(Study!$F$204,0,(COLUMN()-COLUMN($E$48))*4,3,4))) | K48: =Study!H347 -> 47848
C49: -------------------------------------------
C50: الأثاث (furniture) | D50: =Study!C348 -> 47849 | E50: =IF(ABS(SUM(OFFSET(Study!$F$202,0,(COLUMN()-COLUMN($E$50))*4,2,4)))<0.0001,"",SUM(OFFSET(Study!$F$202,0,(COLUMN()-COLUMN($E$50))*4,2,4))) | F50: =IF(ABS(SUM(OFFSET(Study!$F$202,0,(COLUMN()-COLUMN($E$50))*4,2,4)))<0.0001,"",SUM(OFFSET(Study!$F$202,0,(COLUMN()-COLUMN($E$50))*4,2,4))) | G50: =IF(ABS(SUM(OFFSET(Study!$F$202,0,(COLUMN()-COLUMN($E$50))*4,2,4)))<0.0001,"",SUM(OFFSET(Study!$F$202,0,(COLUMN()-COLUMN($E$50))*4,2,4))) | H50: =IF(ABS(SUM(OFFSET(Study!$F$202,0,(COLUMN()-COLUMN($E$50))*4,2,4)))<0.0001,"",SUM(OFFSET(Study!$F$202,0,(COLUMN()-COLUMN($E$50))*4,2,4))) | I50: =IF(ABS(SUM(OFFSET(Study!$F$202,0,(COLUMN()-COLUMN($E$50))*4,2,4)))<0.0001,"",SUM(OFFSET(Study!$F$202,0,(COLUMN()-COLUMN($E$50))*4,2,4))) -> -6150000 | J50: =IF(ABS(SUM(OFFSET(Study!$F$202,0,(COLUMN()-COLUMN($E$50))*4,2,4)))<0.0001,"",SUM(OFFSET(Study!$F$202,0,(COLUMN()-COLUMN($E$50))*4,2,4))) | K50: =Study!H348 -> 48029
C51: -------------------------------------------
C52: البيع على الخارطة (Off-Plan Sale) | D52: =Study!C349 -> 46753 | E52: =IF(ABS(SUM(OFFSET(Study!$F$184,0,(COLUMN()-COLUMN($E$52))*4,1,4)))<0.0001,"",SUM(OFFSET(Study!$F$184,0,(COLUMN()-COLUMN($E$52))*4,1,4))) | F52: =IF(ABS(SUM(OFFSET(Study!$F$184,0,(COLUMN()-COLUMN($E$52))*4,1,4)))<0.0001,"",SUM(OFFSET(Study!$F$184,0,(COLUMN()-COLUMN($E$52))*4,1,4))) -> 14273087 | G52: =IF(ABS(SUM(OFFSET(Study!$F$184,0,(COLUMN()-COLUMN($E$52))*4,1,4)))<0.0001,"",SUM(OFFSET(Study!$F$184,0,(COLUMN()-COLUMN($E$52))*4,1,4))) -> 30956330 | H52: =IF(ABS(SUM(OFFSET(Study!$F$184,0,(COLUMN()-COLUMN($E$52))*4,1,4)))<0.0001,"",SUM(OFFSET(Study!$F$184,0,(COLUMN()-COLUMN($E$52))*4,1,4))) -> 1257540.4 | I52: =IF(ABS(SUM(OFFSET(Study!$F$184,0,(COLUMN()-COLUMN($E$52))*4,1,4)))<0.0001,"",SUM(OFFSET(Study!$F$184,0,(COLUMN()-COLUMN($E$52))*4,1,4))) | J52: =IF(ABS(SUM(OFFSET(Study!$F$184,0,(COLUMN()-COLUMN($E$52))*4,1,4)))<0.0001,"",SUM(OFFSET(Study!$F$184,0,(COLUMN()-COLUMN($E$52))*4,1,4))) | K52: =Study!H349 -> 47848
C53: -------------------------------------------
C54: إيرادات التأجير (Rental Revenue) | D54: =Study!C350 -> 47849 | E54: =IF(ABS(SUM(OFFSET(Study!$F$185,0,(COLUMN()-COLUMN($E$54))*4,2,4)))<0.0001,"",SUM(OFFSET(Study!$F$185,0,(COLUMN()-COLUMN($E$54))*4,2,4))) | F54: =IF(ABS(SUM(OFFSET(Study!$F$185,0,(COLUMN()-COLUMN($E$54))*4,2,4)))<0.0001,"",SUM(OFFSET(Study!$F$185,0,(COLUMN()-COLUMN($E$54))*4,2,4))) | G54: =IF(ABS(SUM(OFFSET(Study!$F$185,0,(COLUMN()-COLUMN($E$54))*4,2,4)))<0.0001,"",SUM(OFFSET(Study!$F$185,0,(COLUMN()-COLUMN($E$54))*4,2,4))) | H54: =IF(ABS(SUM(OFFSET(Study!$F$185,0,(COLUMN()-COLUMN($E$54))*4,2,4)))<0.0001,"",SUM(OFFSET(Study!$F$185,0,(COLUMN()-COLUMN($E$54))*4,2,4))) | I54: =IF(ABS(SUM(OFFSET(Study!$F$185,0,(COLUMN()-COLUMN($E$54))*4,2,4)))<0.0001,"",SUM(OFFSET(Study!$F$185,0,(COLUMN()-COLUMN($E$54))*4,2,4))) -> 23823811 | J54: =IF(ABS(SUM(OFFSET(Study!$F$185,0,(COLUMN()-COLUMN($E$54))*4,2,4)))<0.0001,"",SUM(OFFSET(Study!$F$185,0,(COLUMN()-COLUMN($E$54))*4,2,4))) | K54: =Study!H350 -> 48213
C55: -------------------------------------------
C56: البيع المباشر (Direct Sale) | D56: =Study!C351 | E56: =IF(ABS(SUM(OFFSET(Study!$F$187,0,(COLUMN()-COLUMN($E$56))*4,1,4)))<0.0001,"",SUM(OFFSET(Study!$F$187,0,(COLUMN()-COLUMN($E$56))*4,1,4))) | F56: =IF(ABS(SUM(OFFSET(Study!$F$187,0,(COLUMN()-COLUMN($E$56))*4,1,4)))<0.0001,"",SUM(OFFSET(Study!$F$187,0,(COLUMN()-COLUMN($E$56))*4,1,4))) | G56: =IF(ABS(SUM(OFFSET(Study!$F$187,0,(COLUMN()-COLUMN($E$56))*4,1,4)))<0.0001,"",SUM(OFFSET(Study!$F$187,0,(COLUMN()-COLUMN($E$56))*4,1,4))) | H56: =IF(ABS(SUM(OFFSET(Study!$F$187,0,(COLUMN()-COLUMN($E$56))*4,1,4)))<0.0001,"",SUM(OFFSET(Study!$F$187,0,(COLUMN()-COLUMN($E$56))*4,1,4))) | I56: =IF(ABS(SUM(OFFSET(Study!$F$187,0,(COLUMN()-COLUMN($E$56))*4,1,4)))<0.0001,"",SUM(OFFSET(Study!$F$187,0,(COLUMN()-COLUMN($E$56))*4,1,4))) | J56: =IF(ABS(SUM(OFFSET(Study!$F$187,0,(COLUMN()-COLUMN($E$56))*4,1,4)))<0.0001,"",SUM(OFFSET(Study!$F$187,0,(COLUMN()-COLUMN($E$56))*4,1,4))) | K56: =Study!H351
C57: -------------------------------------------
C58: المخارجة (Buyout) | D58: =Study!C352 -> 48122 | E58: =IF(ABS(SUM(OFFSET(Study!$F$188,0,(COLUMN()-COLUMN($E$58))*4,1,4)))<0.0001,"",SUM(OFFSET(Study!$F$188,0,(COLUMN()-COLUMN($E$58))*4,1,4))) | F58: =IF(ABS(SUM(OFFSET(Study!$F$188,0,(COLUMN()-COLUMN($E$58))*4,1,4)))<0.0001,"",SUM(OFFSET(Study!$F$188,0,(COLUMN()-COLUMN($E$58))*4,1,4))) | G58: =IF(ABS(SUM(OFFSET(Study!$F$188,0,(COLUMN()-COLUMN($E$58))*4,1,4)))<0.0001,"",SUM(OFFSET(Study!$F$188,0,(COLUMN()-COLUMN($E$58))*4,1,4))) | H58: =IF(ABS(SUM(OFFSET(Study!$F$188,0,(COLUMN()-COLUMN($E$58))*4,1,4)))<0.0001,"",SUM(OFFSET(Study!$F$188,0,(COLUMN()-COLUMN($E$58))*4,1,4))) | I58: =IF(ABS(SUM(OFFSET(Study!$F$188,0,(COLUMN()-COLUMN($E$58))*4,1,4)))<0.0001,"",SUM(OFFSET(Study!$F$188,0,(COLUMN()-COLUMN($E$58))*4,1,4))) -> 2.4287182e+08 | J58: =IF(ABS(SUM(OFFSET(Study!$F$188,0,(COLUMN()-COLUMN($E$58))*4,1,4)))<0.0001,"",SUM(OFFSET(Study!$F$188,0,(COLUMN()-COLUMN($E$58))*4,1,4))) | K58: =Study!H352 -> 48213
C59: -------------------------------------------
C60: Capital Structure | هيكل رأس المال | J60: % | K60: SR
C61: ----------------------------------------------------------- | J61: ------------------------------------------- | K61: -------------------------------------------
C62: الاشتراكات النقدية | J62: =K62/$K$71 -> 0.15629244 | K62: =Study!H19 -> 34500000
C63: الاشتراك من مدير الصندوق | J63: =K63/$K$71 -> 0 | K63: =Study!H20 -> 0
C64: الأشتراك النقدي من المطور | J64: =K64/$K$71 -> 0.050285392 | K64: =Study!H21 -> 11100000
C65: الأشتراك العيني من المطور | J65: =K65/$K$71 -> 0 | K65: =Study!H22 -> 0
C66: الإشتراك العيني من مالك الأرض | J66: =K66/$K$71 -> 0.28454102 | K66: =Study!H23 -> 62809600
C67: التمويل البنكي | J67: =K67/$K$71 -> 0.2462263 | K67: =Study!H26 -> 54352006
C68: البيع على الخارطة | J68: =K68/$K$71 -> 0.21059593 | K68: =Study!H29 -> 46486957
C69: مصادر أخرى | J69: =K69/$K$71 -> 0.052058917 | K69: =Study!H30 -> 11491488
C70: ------------------------------------------- | J70: ------------------------------------------- | K70: -------------------------------------------
C71: Total Funding الإجمالي | J71: =SUM(J62:J70) -> 1 | K71: =SUM(K62:K70) -> 2.2074005e+08
S83: مصادر أخرى | T83: =SUM(Summary!K68:K70) -> 57978444 | U83: =T83/Summary!$K$71 -> 0.26265485
S84: التمويل | T84: =Summary!K67 -> 54352006 | U84: =T84/Summary!$K$71 -> 0.2462263
S85: اشتراكات المطور | T85: =Summary!K64+Summary!K65 -> 11100000 | U85: =T85/Summary!K71 -> 0.050285392
S86: اشتراكات نقدية | T86: =Summary!K62+Summary!K63+Summary!K66 -> 97309600 | U86: =T86/Summary!K71 -> 0.44083346
T88: =S83 -> مصادر أخرى | U88: =T83 -> 57978444
T89: =S84 -> التمويل | U89: =T84 -> 54352006
T90: الملكية | U90: =T85+T86 -> 108409600
C94: Cost Breakdown | توزيع التكلفة | J94: SR/B.sqm | K94: SR
C95: إجمالي تكلفة الأرض بعد الضرائب - (Tota Land Cost After TAX) | J95: =J96+J97+J98+J99 -> 5980.2824 | K95: =K96+K97+K98+K99 -> 49134000
C96: (Land Cost Before TAX) - تكلفة الأرض قبل الضرائب | J96: =K96/$I$13 -> 5842.259 | K96: =Study!E44 -> 48000000
C97: (Commissions) - السعي | J97: =K97/$I$13 -> 43.816943 | K97: =Study!G44 -> 360000
C98: (Commission Tax) - ضريبة السعي | J98: =K98/$I$13 -> 6.5725414 | K98: =Study!H44 -> 54000
C99: ضريبة التصرفات العقارية - (RETT) | J99: =K99/$I$13 -> 87.633885 | K99: =Study!F44 -> 720000
C100: ------------------------------------------------------------------
C101: (Development) - التطوير | J101: =J102+J103+J104 -> 3494.6481 | K101: =K102+K103+K104 -> 1.1112855e+08
C102: (Hard Cost - Construction) - تكلفة البناء | J102: =K102/$I$14 -> 2461.2105 | K102: =Study!C19 -> 78265608
C103: Soft Costs (Fees,Consultants, Insurance, Permits, Overheads etc) - التكاليف الأخرى | J103: =K103/$I$14 -> 664.25604 | K103: =Study!C102-Study!C98-Study!C100 -> 21123103
C104: =Study!D104 -> 0.15 | J104: =K104/$I$14 -> 369.18158 | K104: =Study!C104 -> 11739841
C105: ------------------------------------------------------------------
C106: Marketing (RASF) - التسويق | J106: =K106/I15 -> 4.7329791 | K106: =Study!C98+Study!C100 -> 46954.911
C107: ------------------------------------------------------------------
C108: إجمالي تكاليف التمويل - (Total Financing Costs) | J108: =J110+J109 -> 224.5907 | K108: =K109+K110 -> 7141903.3
C109: =Study!C192 -> 0.073 | J109: =K109/$I$14 -> 216.04469 | K109: =-Study!E192 -> 6870143.2
C110: =Study!C193 -> 0.005 | J110: =K110/$I$14 -> 8.5460096 | K110: =-Study!F252 -> 271760.03
C111: ------------------------------------------------------------------
C112: (TotaI Fund expenses) - إجمالي تكاليف الصندوق | J112: =J113+J114 -> 332.54515 | K112: =K113+K114 -> 10574816
C113: رسوم الصندوق - (Fund fees) | J113: =K113/$I$14 -> 289.77737 | K113: =Study!C105 -> 9214816
C114: التكاليف الأخرى للصندوق - (Other costs) | J114: =K114/$I$14 -> 42.76778 | K114: =Study!C106 -> 1360000
C115: ------------------------------------------------------------------
C141: Total Costs - إجمالي التكاليف | J141: =K141/I14 -> 665.73263 | K141: =Study!C102 -> 21170058
S144: البند | T144: القيمة
S145: التسوير | T145: =Study!C86 -> 534040
S146: الحفر والمسح والاختبار | T146: =Study!C87 -> 2835360
S147: التأمين | T147: =Study!C88 -> 1330515.3
S148: الرخصة | T148: =Study!C89 -> 62830.56
S149: التصميم | T149: =Study!C90 -> 3913280.4
S150: أثاث الوحدات الفندقية | T150: =Study!C91 -> 6150000
S151: أثاث الوحدات | T151: =Study!C92 -> 0
S152: رسوم الكهرباء | T152: =Study!C93 -> 912500
S153: رسوم الماء وصرف الصحي | T153: =Study!C94 -> 984000
S154: الفرز | T154: =Study!C95 -> 18000
S155: الصيانة و التشغيل | T155: =Study!C96 -> 299000
S156: الاحتياطي | T156: =Study!C97 -> 1173984.1
... S160: الإشراف الهندسي | T160: =Study!C101 -> 1956640.2
C164: Fund Revenue | إيرادات الصندوق | K164: SR
C165: البيع المباشر (Direct Sale) | K165: =Study!C187 -> 0 | S165: حجم التمويل للفترة | T165: =Study!F246 -> 0 | U165: =Study!G246 -> 0 | V165: =Study!H246 -> 0 | W165: =Study!I246 -> 0 | X165: =Study!J246 -> 0 | Y165: =Study!K246 -> 0 | Z165: =Study!L246 -> 2552006 | AA165: =Study!M246 -> 3352006 | ... AQ165: =Study!AC246 -> 0
C166: البيع على الخارطة (Off-Plan Sale) | K166: =Study!C184 -> 46486957 | S166: أصل التمويل | T166: =Study!F248 -> 0 | U166: =Study!G248 -> 0 | V166: =Study!H248 -> 0 | W166: =Study!I248 -> 0 | X166: =Study!J248 -> 0 | Y166: =Study!K248 -> 0 | Z166: =Study!L248 -> 2552006 | AA166: =Study!M248 -> 800000 | ... AQ166: =Study!AC248 -> 0
...
