Workbook

Sheet الدراسة
E1: السدحان 2025-04-20 | AE1: كود الوان الحدود | AF1: الاكواد
E2: الموقع | AE2: #DAD2CC | AF2: #A4907E | AG2: العناوين | AH2: 0 | AI2: الجميع بدون حساب رموز الأخطاء | AJ2: المتوسط الحسابي بدون حساب القيم الصفرية و رموز الأخطاء | AK2: إزالة رموز الخطاء من القسمة
AE3: حجم خط العناوين 10 | AF3: بدون تعبئة | AG3: شكل 1 | AH3: 0 | AI3: =SUMIF(AO1:AO7, "<>#DIV/0!") -> 0 | AJ3: =AVERAGEIFS(AS1:AS7, AS1:AS7, "<>0", AS1:AS7, "<>#DIV/0!") -> #DIV/0! | AK3: {=IFERROR(AN3:AN5/AM3:AM5, "0")} -> 0
AE4: حجم خط الخلايا العادية 8 | AF4: #F0EAE4 | AG4: شكل 2 | AH4: 0 | AK4: 0
AE5: حجم خط الخلايا المنبثقة 7 | AF5: #EDE4D6 | AG5: خلايا الأدخال و الخلايا المتغيرة | AH5: 0 | AK5: 0
AE6: في حالات نادرة يكون حجم الخلايا العادية 7 او 6 بحال عدم وجود مساحة | AF6: اول لون بدرجات الأخضر | AG6: تعقيب | AH6: 0
B15: Feasibility Study Summary | ملخص دراسة الجدوى | F15: Financial Structuring | الهيكلة المالية
B16: البند (Item) | C16: القيمة (Value) | F16: رأس المال - (capital)
B17: إجمالي الإيرادات (Total Revenue) | C17: =SUM(E183:E186) -> 667316475 | F17: المصدر (Source) | G17: SAR | H17: %
B18: إجمالي تكلفة الأرض (Total Land Cost) | C18: =I49 -> 223256250 | F18: (Equity) - الملكية
B19: إجمالي تكلفة البناء (Total Construction Cost) | C19: =J76 -> 181440000 | F19: الاشتراكات النقدية (Cash Subscription) | H19: =G19/$G$34 -> 0
B20: إجمالي التكاليف الأخرى (Total Other cost) | C20: =C101 -> 28577512 | F20: الاشتراك من مدير الصندوق (fund manager's Subscription) | H20: =G20/$G$34 -> 0
B21: إجمالي رسوم الصندوق (Total Fund Fees) | C21: =C106 -> 29224428 | F21: الأشتراك النقدي من المطور (Cash Subscription from Developer) | H21: =G21/$G$34 -> 0
B22: فوائد التمويل (Interest) | C22: =C117 -> 42134525 | F22: الأشتراك العيني من المطور (In-Kind Subscription from Developer) | G22: 0 | H22: =G22/$G$34 -> 0 | I22: 1
B23: التمويل البنكي (Bank Financing) | C23: =G26 -> 259300000 | F23: الإشتراك العيني من مالك الأرض (In-Kind Subscription from Landowner) | G23: =I23*E49 -> 220500000 | H23: =G23/$G$34 -> 0.43695146 | I23: 1
B24: إجمالي تكاليف المشروع (Total project cost) | C24: =SUM(C18:C22) -> 5.0463272e+08 | F24: إجمالي الملكية (Total Equity) | G24: =SUM(G19:G23) -> 220500000 | H24: =G24/$G$34 -> 0.43695146
B25: صافي الدخل (Net Income) | C25: =C17-C24 -> 1.6268376e+08 | F25: التمويل - (Finance)
B26: مدة المشروع المتوقعة - سنوي (Estimated Project Duration - Years) | C26: =D120 -> 3.7863014 | F26: التمويل البنكي (Bank Financing) | G26: =E187 -> 259300000 | H26: =G26/$G$34 -> 0.51383906
B27: معدل العائد الداخلي (IRR) | C27: =C219 -> 0.14642063
B28: العائد على الإستثمار (ROI) | C28: =C25/C24 -> 0.32238053 | F28: تمويل المبيعات - (Sales Financing)
B29: العائد على الملكية (ROE) | C29: =C25/G24 -> 0.73779483 | F29: البيع على الخارطة (Off-Plan Sales) | G29: =J29*I29 -> 0 | H29: =G29/$G$34 -> 0 | I29: =AA140 -> 0 | J29: 1 | K29: =-G35/I29 -> #DIV/0!
B30: العائد على الملكية السنوي (ROE Annually) | C30: =C29/C26 -> 0.19485898 | F30: مصادر أخرى (Other Sources) | G30: =I30*J30 -> 24832715 | H30: =G30/$G$34 -> 0.049209484 | I30: =SUM(J139,L157,AE157) -> 34601595 | J30: 0.71767545 | K30: =-G35/I30 -> 0
F31: إجمالي تمويل المبيعات (Total Sales Financing) | G31: =G30+G29 -> 24832715 | H31: =G31/$G$34 -> 0.049209484
F32: الإجمالي - (Total)
F33: إجمالي مصادر التمويل (Total Financing Sources) | G33: =G24+G26+G31 -> 5.0463272e+08 | H33: =100%=SUM(H24,H26,H31) -> TRUE
F34: إجمالي تكاليف المشروع (Total project cost) | G34: =C113 -> 5.0463272e+08
F35: الفرق (Difference) | G35: =G33-G34 -> 0
B42: تفاصيل الأرض | Land Details
B43: رقم الأرض (Land Number) | C43: المساحة الأرض (Land Area) | D43: التكلفة للمتر (Cost per SQM) | E43: تكلفة الأرض قبل الضرائب (Land Cost Before Taxes) | F43: ضريبة التصرفات العقارية (RETT) | G43: السعي (Commission) | H43: ضريبة السعي (Commission tax) | I43: إجمالي تكلفة الأرض بعد الضرائب (Total Land Cost After Taxes) | J43: معامل البناء (FAR) | K43: إجمالي مسطحات البناء فوق الأرض (Above Grade Gross Building Area)
B44: 1 | C44: 10500 | D44: 21000 | E44: =D44*C44 -> 220500000 | F44: =(E44*$F$50)*$F$51 -> 0 | G44: =(E44*$G$50)*$G$51 -> 2756250 | H44: =(G44*$H$50)*$H$51 -> 0 | I44: =SUM(E44:H44) -> 223256250 | J44: 4 | K44: =J44*C44 -> 42000
B45: 2 | E45: =D45*C45 -> 0 | F45: =(E45*$F$50)*$F$51 -> 0 | G45: =(E45*$G$50)*$G$51 -> 0 | H45: =(G45*$H$50)*$H$51 -> 0 | I45: =SUM(E45:H45) -> 0 | K45: =J45*C45 -> 0
B46: 3 | E46: =D46*C46 -> 0 | F46: =(E46*$F$50)*$F$51 -> 0 | G46: =(E46*$G$50)*$G$51 -> 0 | H46: =(G46*$H$50)*$H$51 -> 0 | I46: =SUM(E46:H46) -> 0 | K46: =J46*C46 -> 0
B47: 4 | E47: =D47*C47 -> 0 | F47: =(E47*$F$50)*$F$51 -> 0 | G47: =(E47*$G$50)*$G$51 -> 0 | H47: =(G47*$H$50)*$H$51 -> 0 | I47: =SUM(E47:H47) -> 0 | K47: =J47*C47 -> 0
B48: 5 | E48: =D48*C48 -> 0 | F48: =(E48*$F$50)*$F$51 -> 0 | G48: =(E48*$G$50)*$G$51 -> 0 | H48: =(G48*$H$50)*$H$51 -> 0 | I48: =SUM(E48:H48) -> 0 | K48: =J48*C48 -> 0
B49: الإجمالي (Total) | C49: =SUM(C44:C48) -> 10500 | D49: =E49/C49 -> 21000 | E49: =SUM(E44:E48) -> 220500000 | F49: =SUM(F44:F48) -> 0 | G49: =SUM(G44:G48) -> 2756250 | H49: =SUM(H44:H48) -> 0 | I49: =SUM(I44:I48) -> 223256250 | J49: =K49/C49 -> 4 | K49: =SUM(K44:K48) -> 42000
F50: 0.05 | G50: 0.025 | H50: 0.15 | K50: =SUM(D61:D71)=K49 -> TRUE
F51: 0 | G51: 0.5 | H51: 0
B57: Construction Details and Costs | تفاصيل البناء و تكاليفة
B58: طول الأرض على الشارع (Land Frontage) | C58: عمق الأرض (Land Depth) | D58: معامل البناء (FAR) | E58: إجمالي المساحة التطويرية (Total Development Area) | F58: إجمالي المساحة المبنية (Gross Built-Up Area) | H58: إجمالي المساحة البنائية فوق مستوى الأرض (Above Grade Gross Building Area) | J58: إجمالي المساحات القابلة للبيع (Net Sellable Area) | K58: المواقف (Parking) | L58: معيار المواقف (Parking Standards)
B59: 0 | C59: 0 | D59: =J49 -> 4 | E59: =SUM(D61:D75) -> 68250 | F59: =SUM(D61:D71,D74:D75) -> 63000 | H59: =SUM(D61:D71) -> 42000 | J59: =F76 -> 35385 | P59: توزيع تكاليف المشروع على المكونات | Cost Breakdown by Component
B60: المكون (Component) | C60: نسبة المكون من المساحة البنائية (GBA-%) | D60: إجمالي المساحة البنائية للمكون (GBA) | E60: نسبة المساحات الصافية القابلة للبيع (NSA-%) | F60: المساحات الصافية القابلة للبيع (NSA) | G60: مساحة الوحدة (Unit Area) | H60: عدد الوحدات (Number of Units) | I60: تكلفة متر البناء (Construction cost Per m²) | J60: اجمالي التكاليف (Total Costs) | K60: =B59/L60 -> 0 | L60: 3.5 | P60: المكون (Component) | Q60: إجمالي تكاليف كل مكون (Total Cost per Component) | R60: توزيع التكلفة لكل م² (Cost per m² Allocation) | S60: إجمالي إيراد كل مكون (Total Revenue per Component) | T60: العائد لكل م² (Return per m²) | U60: صافي دخل كل مكون (Net Income per Component) | V60: نسبة عائد كل مكون (Return % per Component)
B61: سكني (Apartments) | C61: 0.6 | D61: =$K$49*C61 -> 25200 | E61: 0.8 | F61: =E61*D61 -> 20160 | G61: =IFERROR(F61/H61, "0") -> 100.8 | H61: 200 | I61: 3200 | J61: =I61*D61 -> 80640000 | K61: =L61*H61 -> 300 | L61: 1.5 | P61: سكني (Apartments) | Q61: 2.8294018e+08 | R61: 14034.731 | S61: 300736800 | T61: 14917.5 | U61: 17796625 | V61: 0.062898896
B62: فلل (Villas) | D62: =$K$49*C62 -> 0 | F62: =E62*D62 -> 0 | G62: =IFERROR(F62/H62, "0") -> 0 | J62: =I62*D62 -> 0 | K62: =L62*H62 -> 0 | L62: 0 | P62: فلل (Villas) | Q62: 0 | R62: 0 | S62: 0 | T62: 0 | U62: 0 | V62: 0.00%
B63: تاون هاوس (Townhouse) | D63: =$K$49*C63 -> 0 | F63: =E63*D63 -> 0 | G63: =IFERROR(F63/H63, "0") -> 0 | J63: =I63*D63 -> 0 | K63: =L63*H63 -> 0 | L63: 0 | P63: تاون هاوس (Townhouse) | Q63: 0 | R63: 0 | S63: 0 | T63: 0 | U63: 0 | V63: 0.00%
B64: أدوار (Floors) | D64: =$K$49*C64 -> 0 | F64: =E64*D64 -> 0 | G64: =IFERROR(F64/H64, "0") -> 0 | J64: =I64*D64 -> 0 | K64: =L64*H64 -> 0 | L64: 0 | P64: أدوار (Floors) | Q64: 0 | R64: 0 | S64: 0 | T64: 0 | U64: 0 | V64: 0.00%
B65: أستوديوهات (Studios) | D65: =$K$49*C65 -> 0 | F65: =E65*D65 -> 0 | G65: =IFERROR(F65/H65, "0") -> 0 | J65: =I65*D65 -> 0 | K65: =L65*H65 -> 0 | L65: 1 | P65: أستوديوهات (Studios) | Q65: 0 | R65: 0 | S65: 0 | T65: 0 | U65: 0 | V65: 0.00%
B66: مكتبي (Office) | C66: 0.25 | D66: =$K$49*C66 -> 10500 | E66: 0.9 | F66: =E66*D66 -> 9450 | G66: =IFERROR(F66/H66, "0") -> 555.88235 | H66: 17 | I66: 2500 | J66: =I66*D66 -> 26250000 | K66: =F66/L66 -> 378 | L66: 25 | P66: مكتبي (Office) | Q66: 1.4056472e+08 | R66: 14874.574 | S66: 224532000 | T66: 23760 | U66: 83967275 | V66: 0.59735666
B67: تجاري (Retail) | C67: 0.1 | D67: =$K$49*C67 -> 4200 | E67: 0.95 | F67: =E67*D67 -> 3990 | G67: =IFERROR(F67/H67, "0") -> 190 | H67: 21 | I67: 2500 | J67: =I67*D67 -> 10500000 | K67: =F67/L67 -> 88.666667 | L67: 45 | P67: تجاري (Retail) | Q67: 52464567 | R67: 13149.014 | S67: 92647800 | T67: 23220 | U67: 40183233 | V67: 0.76591184
B68: فندقي (Hotel) | D68: =$K$49*C68 -> 0 | F68: =E68*D68 -> 0 | G68: =IFERROR(F68/H68, "0") -> 0 | J68: =I68*D68 -> 0 | K68: =H68/L68 -> 0 | L68: 2 | P68: فندقي (Hotel) | Q68: 0 | R68: 0 | S68: 0 | T68: 0 | U68: 0 | V68: 0.00%
B69: صحي (health) | C69: 0.05 | D69: =$K$49*C69 -> 2100 | E69: 0.85 | F69: =E69*D69 -> 1785 | G69: =IFERROR(F69/H69, "0") -> 892.5 | H69: 2 | I69: 2500 | J69: =I69*D69 -> 5250000 | K69: =F69/L69 -> 51 | L69: 35 | P69: صحي (health) | Q69: 28728536 | R69: 16094.418 | S69: 49399875 | T69: 27675 | U69: 20671339 | V69: 0.71954029
B70: شاليهات (Chalets) | D70: =$K$49*C70 -> 0 | F70: =E70*D70 -> 0 | G70: =IFERROR(F70/H70, "0") -> 0 | J70: =I70*D70 -> 0 | K70: لا يــــنــطــبــق | L70: لا يــــنــطــبــق | P70: شاليهات (Chalets) | Q70: 0 | R70: 0 | S70: 0 | T70: 0 | U70: 0 | V70: 0.00%
B71: المساحات الحركية والخدمية (Circulation & Service Areas) | C71: =1-SUM(C61:C70) -> 0 | D71: =$K$49*C71 -> 0 | E71: لا يــــنــطــبــق | F71: لا يــــنــطــبــق | G71: لا يــــنــطــبــق | H71: لا يــــنــطــبــق | J71: =I71*D71 -> 0 | K71: لا يــــنــطــبــق | L71: لا يــــنــطــبــق | P71: الإجمالي (Total) | Q71: 5.04698e+08 | R71: 14263.049 | S71: 667316475 | T71: 3871.8684 | U71: 1.6261847e+08 | V71: 0.32220946
B73: لاند سكيب* (Landscape) | C73: 0.5 | D73: =$C$49*C73 -> 5250 | E73: لا يــــنــطــبــق | F73: لا يــــنــطــبــق | G73: لا يــــنــطــبــق | H73: لا يــــنــطــبــق | I73: 1200 | J73: =I73*D73 -> 6300000 | K73: لا يــــنــطــبــق | L73: لا يــــنــطــبــق
B74: قبو * (Basement) | C74: 2 | D74: =$C$49*C74 -> 21000 | E74: لا يــــنــطــبــق | F74: لا يــــنــطــبــق | G74: لا يــــنــطــبــق | H74: لا يــــنــطــبــق | I74: 2500 | J74: =I74*D74 -> 52500000 | K74: =D74/L74 -> 466.66667 | L74: 45
B75: بوديوم* (Podium) | D75: =$C$49*C75 -> 0 | E75: لا يــــنــطــبــق | F75: لا يــــنــطــبــق | G75: لا يــــنــطــبــق | H75: لا يــــنــطــبــق | J75: =I75*D75 -> 0 | K75: =D75/L75 -> 0 | L75: 45
B76: الإجمالي (Total) | C76: =SUM(C61:C71) -> 1 | D76: =SUM(D61:D75) -> 68250 | E76: =AVERAGEIFS(E61:E75, E61:E75, "<>0", E61:E75, "<>#DIV/0!") -> 0.875 | F76: =SUMIF(F61:F70, "<>#DIV/0!") -> 35385 | G76: =IFERROR(F76/H76, "0") -> 147.4375 | H76: =SUMIF(H61:H75, "<>#DIV/0!") -> 240 | I76: =J76/D76 -> 2658.4615 | J76: =SUM(J61:J75) -> 181440000 | K76: إجمالي المواقف المطلوبة (Total Required Parking Spaces) | L76: =SUMIF(K61:K69, "<>#DIV/0!") -> 817.66667
B77: من مساحة الأرض* (Based on Land Area) | C77: =C76=100% -> TRUE | H77: إجمالي وحدات المشروع (Total Project Units) | K77: إجمالي المواقف المتوفرة (Total Available Parking Spaces) | L77: =SUM(K60,K74:K75) -> 466.66667
K78: فارق المواقف (Parking Deficit) | L78: =L77-L76 -> -351
B84: Other Cost | التكاليف الأخرى | E84: نسبة البند من الإجمالي (Proportion of Item to Total) | H84: التكاليف الأخرى للصندوق | Other Fund Costs
B85: البند (Item) | C85: القيمة (Value) | D85: المعيار (Standard) | E85: % | H85: السنة (Year) | I85: رسوم انشاء شركة ذات غرض خاص (Custodian - SPV Establishment fee) | J85: رسوم أمين الحفظ (Custodian Fees) | K85: مراجع الحسابات (Auditor) | L85: مستشار الضريبة (Tax advisor) | M85: مستشار شرعي (Shariya consultant fee) | N85: مكافأت أعضاء مجلس الإدارة (Board Members' Compensation)
B86: التسوير (Fencing) | C86: =D86*C44 -> 525000 | D86: 50 | E86: =C86/$C$101 -> 0.018371088 | H86: Y1 | I86: 25000 | J86: 65000 | K86: 40000 | L86: 100000 | M86: 50000 | N86: 12000
B87: الحفر والمسح والاختبار (Excavation, surveying, and testing) | C87: =(D74)*4.5*D87 -> 3024000 | D87: 32 | E87: =C87/$C$101 -> 0.10581747 | H87: Y2 | I87: لا يــــنــطــبــق | J87: 65000 | K87: 40000 | L87: 100000 | M87: 50000 | N87: 12000
B88: التأمين (Insurance) | C88: =D88*C109 -> 3084480 | D88: 0.017 | E88: =C88/$C$101 -> 0.10793382 | H88: Y3 | I88: لا يــــنــطــبــق | J88: 65000 | K88: 40000 | L88: 100000 | M88: 50000 | N88: 12000
B89: الرخصة (License) | C89: =D89*H59 -> 168000 | D89: 4 | E89: =C89/$C$101 -> 0.0058787483 | H89: Y4 | I89: لا يــــنــطــبــق | J89: 65000 | K89: 40000 | L89: 100000 | M89: 50000 | N89: 12000
B90: التصميم (Design) | C90: =D90*C109 -> 4536000 | D90: 0.025 | E90: =C90/$C$101 -> 0.1587262 | H90: Y5 | I90: لا يــــنــطــبــق
B91: أثاث الوحدات الفندقية (Hotel Furniture Units) | C91: =D91*D68 -> 0 | D91: 1000 | E91: =C91/$C$101 -> 0 | H91: Y6 | I91: لا يــــنــطــبــق
B92: أثاث الوحدات (Furniture Units) | C92: =D92*SUM(G61,G65,G66) -> 0 | D92: 0 | E92: =C92/$C$101 -> 0 | H92: الإجمالي لكل بند (Total for Each Item) | I92: =SUM(I86) -> 25000 | J92: =SUM(J86:J91) -> 260000 | K92: =SUM(K86:K91) -> 160000 | L92: =SUM(L86:L91) -> 400000 | M92: =SUM(M86:M91) -> 200000 | N92: =SUM(N86:N91) -> 48000
B93: رسوم الكهرباء (Electricity fees) | C93: =D93*SUM(H61:H67,H69:H70)+(D93*(H68/2)) -> 2676000 | D93: 11150 | E93: =C93/$C$101 -> 0.093640062 | H93: إجمالي الكل (Grand Total) | I93: =SUM(I92:N92) -> 1093000
B94: رسوم الماء وصرف الصحي (Water and sewer fees) | C94: =D94*$H$76 -> 1440000 | D94: 6000 | E94: =C94/$C$101 -> 0.050389271
B95: الفرز (Sorting) | C95: =D95*$H$76 -> 240000 | D95: 1000 | E95: =C95/$C$101 -> 0.0083982119
B96: الصيانة و التشغيل (Maintenance and Operation) | C96: =D96*H76 -> 3120000 | D96: 13000 | E96: =C96/$C$101 -> 0.10917675
B97: الاحتياطي (Contingency) | C97: =D97*C109 -> 3628800 | D97: 0.02 | E97: =C97/$C$101 -> 0.12698096
B98: تسويق المبيعات والتأجير (Sales and Leasing Marketing) | C98: =D98*(J139+L157) -> 692031.9 | D98: 0.02 | E98: =C98/$C$101 -> 0.024215961
B99: تسويق البيع على الخارطة (Off-Plan Sales Marketing) | C99: =D99*V139 -> 0 | D99: 0.03 | E99: =C99/$C$101 -> 0
B100: الإشراف الهندسي (Engineering Supervision) | C100: =D100*C109 -> 5443200 | D100: 0.03 | E100: =C100/$C$101 -> 0.19047145
B101: إجمالي التكاليف الأخرى (Total Other Cost) | C101: =SUMIF(C86:C100, "<>#DIV/0!") -> 28577512
B102: تفاصيل تكاليف الصندوق | Fund Cost Details
B103: تكاليف المطور (Developer costs) | C103: =D103*(C109+C86+C87+C90+C97+C100+C98) -> 19928903 | D103: 0.1 | E103: 0
B104: رسوم الصندوق (Fund fees) | C104: =E104*(C108+C109+C110) -> 8202525.2 | D104: 0.005 | E104: =D104*D120 -> 0.018931507
B105: التكاليف الأخرى للصندوق (Other costs) | C105: =I93 -> 1093000
B106: الإجمالي (Total) | C106: =SUM(C103:C105) -> 29224428
B107: ملخص تكاليف المشروع | Project Costs
B108: اجمالي تكلفة الأرض (Total Land Cost) | C108: =I49 -> 223256250
B109: اجمالي تكلفة البناء (Total construction cost) | C109: =J76 -> 181440000
B110: إجمالي التكاليف الأخرى (Total other costs) | C110: =C101 -> 28577512
B111: إجمالي تكلفة التطوير (Total development cost) | C111: =C109+C110 -> 2.1001751e+08
B112: إجمالي تكاليف الصندوق (Total fund costs) | C112: =C106 -> 29224428
B113: إجمالي تكاليف المشروع (Total project cost) | C113: =C108+C111+C112+C117 -> 5.0463272e+08
B114: الملكية (Equity) | C114: =G24 -> 220500000
B115: التمويل | Finance
B116: التمويل المطلوب (Required financing) | C116: =E187 -> 259300000
B117: فوائد التمويل (Interest) | C117: =-SUM(E190:E191) -> 42134525 | E117: =(W176-G176)/365 -> 4.0027397
B118: الإطار الزمني | Time frame | E118: .
B119: مدة المشروع المتوقعة (Estimated Project Duration) | C119: بالأشهر - Months | D119: بالسنين - Years | E119: ربع سنوي - Quarterly
C120: =((U176-F176)/365)*12 -> 45.435616 | D120: =C120/12 -> 3.7863014 | E120: =C120/3 -> 15.145205
B127: البيع المباشر | Direct Sale | N127: البيع على الخارطة | Off-Plan Sale
B128: المكون (Component) | C128: عدد الوحدات (Number of units) | D128: نسبة البيع (Selling-%) | E128: =E60 -> نسبة المساحات الصافية القابلة للبيع (NSA-%) | F128: =F60 -> المساحات الصافية القابلة للبيع (NSA) | G128: =G60 -> مساحة الوحدة (Unit Area) | H128: سعر بيع المتر (Sale Price per m²) | I128: قيمة الوحدة (Unit Value) | J128: اجمالي المبيعات (Total Sales) | N128: المكون (Component) | O128: عدد الوحدات (Number of units) | P128: نسبة البيع (Selling-%) | Q128: نسبة المساحات الصافية القابلة للبيع (NSA-%) | R128: المساحات الصافية القابلة للبيع (NSA) | S128: مساحة الوحدة (Unit Area) | T128: سعر بيع المتر (Sale Price per m²) | U128: قيمة الوحدة (Unit Value) | V128: اجمالي المبيعات (Total Sales) | W128: رسوم وافي (Wafi fees) | X128: أتعاب المحاسب القانوني والاستشاري الهندسي (Certified Accountant & Engineering Supervision Fees) | Y128: قيمة أستقطاع الضمان (Retention Guarantee Amount) | Z128: تسويق البيع على الخارطة (Off-Plan Sales Marketing) | AA128: صافي المبيعات على الخارطة قبل استرداد قيمة الضمان (Net Off-Plan Sales before Guarantee Refund Recovery)
B129: سكني (Apartments) | D129: =IFERROR(C129/H61, "0.00%") -> 0 | E129: =E61 -> 0.8 | F129: =E129*D129*D61 -> 0 | G129: =IFERROR(F129/C129, "0") -> 0 | I129: =H129*G129 -> 0 | J129: =I129*C129 -> 0 | N129: سكني (Apartments) | P129: =IFERROR(O129/H61, "0.00%") -> 0 | Q129: =E61 -> 0.8 | R129: =Q129*P129*D61 -> 0 | S129: =IFERROR(R129/O129, "0") -> 0 | U129: =T129*S129 -> 0 | V129: =(U129*O129) -> 0 | W129: =V129*$D$304 -> 0 | X129: =(V129*$D$305)+(V129*$D$306) -> 0 | Y129: =V129*$D$307 -> 0 | Z129: =V129*$D$99 -> 0 | AA129: =V129-(SUM(W129:Y129)) -> 0
B130: فلل (Villas) | D130: =IFERROR(C130/H62, "0.00%") -> 0.00% | E130: =E62 -> 0 | F130: =F62 -> 0 | G130: =IFERROR(F130/C130, "0") -> 0 | I130: =H130*G130 -> 0 | J130: =I130*C130 -> 0 | N130: فلل (Villas) | P130: =IFERROR(O130/H62, "0.00%") -> 0.00% | Q130: =E62 -> 0 | R130: =Q130*P130*D62 -> 0 | S130: =IFERROR(R130/O130, "0") -> 0 | U130: =T130*S130 -> 0 | V130: =(U130*O130) -> 0 | W130: =V130*$D$304 -> 0 | X130: =(V130*$D$305)+(V130*$D$306) -> 0 | Y130: =V130*$D$307 -> 0 | Z130: =V130*$D$99 -> 0 | AA130: =V130-(SUM(W130:Y130)) -> 0
B131: تاون هاوس (Townhouse) | D131: =IFERROR(C131/H63, "0.00%") -> 0.00% | E131: =E63 -> 0 | F131: =F63 -> 0 | G131: =IFERROR(F131/C131, "0") -> 0 | I131: =H131*G131 -> 0 | J131: =I131*C131 -> 0 | N131: تاون هاوس (Townhouse) | P131: =IFERROR(O131/H63, "0.00%") -> 0.00% | Q131: =E63 -> 0 | R131: =Q131*P131*D63 -> 0 | S131: =IFERROR(R131/O131, "0") -> 0 | U131: =T131*S131 -> 0 | V131: =(U131*O131) -> 0 | W131: =V131*$D$304 -> 0 | X131: =(V131*$D$305)+(V131*$D$306) -> 0 | Y131: =V131*$D$307 -> 0 | Z131: =V131*$D$99 -> 0 | AA131: =V131-(SUM(W131:Y131)) -> 0
...

Sheet الملخص
B7: شركة رصف للاستثمار | J7: RASF Investment Co.
B8: =الدراسة!E1 -> السدحان 2025-04-20 | I8: =B8 -> السدحان 2025-04-20
B9: Units shown are SAR except where stated | الوحدات المعروضة هي بالريال سعودي باستثناء ما هو مذكور | D9: NSA.m² : Net Sellable Area|TDA.m² : Total Development Area|LA.m² : Total Land Area NSA.m² | المساحات الصافية القابلة للبيع | TDA.m² : إجمالي المساحة التطويرية | LA.m² : مساحة الأرض الإجمالية
B13: Summary | ملخص
H14: (Area) - المساحة | I14: (SR/m²) - ر.س/م² | J14: الإجمالي - (Total)
B15: Land purchase cost - base price (excl. taxes & commissions) - تكلفة شراء الأرض - السعر الأساسي (باستثناء الضرائب والعمولات) | H15: =الدراسة!C49 -> 10500 | I15: =الدراسة!D49 -> 21000 | J15: =الدراسة!E49 -> 220500000
B16: (Total project cost - including land, works, overheads and fees) - التكلفة الإجمالية للمشروع - بما في ذلك الأرض والأعمال والنفقات العامة والرسوم | H16: =الدراسة!E59 -> 68250 | I16: =J16/H16 -> 7393.8859 | J16: =الدراسة!C24 -> 5.0463272e+08
B17: إجمالي الإيرادات - (Total Revenue) | H17: =الدراسة!J59 -> 35385 | I17: =J17/H17 -> 18858.739 | J17: =الدراسة!C17 -> 667316475
B19: نمو قيمة الأرض - Land Value Uplift | H19: وقت الشراء | I19: وقت البيع | J19: الفارق
H21: =J69/H15 -> 21262.5 | I21: =((J69/J114)*J17)/H15 -> 28117.116 | J21: =I21-H21 -> 6854.6159
B23: المؤشرات المالية | Financial Indicators | C23: معدل العائد الداخلي IRR | E23: العائد على الإستثمار ROI | G23: العائد على الملكية ROE | I23: العائد على الملكية سنوياَ ROE Annualy
C26: =الدراسة!C27 -> 0.14642063 | E26: =الدراسة!C28 -> 0.32238053 | G26: =الدراسة!C29 -> 0.73779483 | I26: =الدراسة!C30 -> 0.19485898
C29: عدد الوحدات (Number of Units) | D29: مساحة الوحدة (Unit Area) | G29: =الدراسة!Q60 -> إجمالي تكاليف كل مكون (Total Cost per Component) | H29: =الدراسة!T60 -> العائد لكل م² (Return per m²) | I29: صافي دخل كل مكون (Net Income per Component) | J29: نسبة عائد كل مكون (Return % per Component)
B30: التفاصيل الفنية و المالية لجميع للمكونات | Technical and Financial Details For All Components
B31: (Apartments) - سكني | C31: =الدراسة!H61 -> 200 | D31: =الدراسة!G61 -> 100.8 | G31: =الدراسة!Q61 -> 2.8294018e+08 | H31: =الدراسة!T61 -> 14917.5 | I31: =الدراسة!U61 -> 17796625 | J31: =الدراسة!V61 -> 0.062898896
B32: مكتبي - (Office) | C32: =الدراسة!H66 -> 17 | D32: =الدراسة!G66 -> 555.88235 | G32: =الدراسة!Q66 -> 1.4056472e+08 | H32: =الدراسة!T66 -> 23760 | I32: =الدراسة!U66 -> 83967275 | J32: =الدراسة!V66 -> 0.59735666
B33: تجاري - (Retail) | C33: =الدراسة!H67 -> 21 | D33: =الدراسة!G67 -> 190 | G33: =الدراسة!Q67 -> 52464567 | H33: =الدراسة!T67 -> 23220 | I33: =الدراسة!U67 -> 40183233 | J33: =الدراسة!V67 -> 0.76591184
B34: صحي - (health) | C34: =الدراسة!H69 -> 2 | D34: =الدراسة!G69 -> 892.5 | G34: =الدراسة!Q69 -> 28728536 | H34: =الدراسة!T69 -> 27675 | I34: =الدراسة!U69 -> 20671339 | J34: =الدراسة!V69 -> 0.71954029
B37: الإطار الزمني (بالسنوات) - Time frame (Years) | C37: 1 | D37: 2 | E37: 3 | F37: 4 | I37: =الدراسة!D120 -> 3.7863014
B38: التكاليف الأخرى - ( Other costs) | C38: =SUM(الدراسة!F195:I208) -> -12153960 | D38: =SUM(الدراسة!J195:M208) -> -4250880 | E38: =SUM(الدراسة!N195:Q208) -> -9601994.6 | F38: =SUM(الدراسة!R195:U208) -> -2570677.3 | G38: =SUM(الدراسة!V195:Y208) -> 0 | H38: =SUM(الدراسة!Z195:AC208) -> 0
B39: تكاليف البناء - (Construction cost) | C39: =SUM(الدراسة!F194:I194) -> -27216000 | D39: =SUM(الدراسة!J194:M194) -> -72576000 | E39: =SUM(الدراسة!N194:Q194) -> -81648000 | F39: =SUM(الدراسة!R194:U194) -> 0 | G39: =SUM(الدراسة!V194:Y194) -> 0 | H39: =SUM(الدراسة!Z194:AC194) -> 0
B40: (Lease-up and wholesale) - التأجير والبيع | C40: =SUM(الدراسة!F183:I185) -> 0 | D40: =SUM(الدراسة!J183:M185) -> 0 | E40: =SUM(الدراسة!N183:Q185) -> 9886170 | F40: =SUM(الدراسة!R183:U185) -> 39544680 | G40: =SUM(الدراسة!V183:Y185) -> 0 | H40: =SUM(الدراسة!Z183:AC185) -> 0
B43: Capital Structure | هيكل رأس المال | I43: % | J43: SR
B44: الإشتراك العيني من مالك الأرض - (In-Kind Subscription from Landowner) | I44: =J44/$J$47 -> 0.43695146 | J44: =الدراسة!G23 -> 220500000
B45: التمويل البنكي - (Bank Financing) | I45: =J45/$J$47 -> 0.51383906 | J45: =الدراسة!G26 -> 259300000
B46: مصادر أخرى - (Other Sources) | I46: =J46/$J$47 -> 0.049209484 | J46: =الدراسة!G30 -> 24832715
B47: Total Funding الإجمالي | I47: =SUM(I44:I46) -> 1 | J47: =SUM(J44:J46) -> 5.0463272e+08
AA67: مصادر أخرى | AB67: =SUM(J46:J46) -> 24832715 | AC67: =AB67/$J$47 -> 0.049209484 | AD67: =الدراسة!B192 -> تكلفة الأرض (Land Cost) | AE67: =-الدراسة!C192 -> 220500000
B68: Cost Breakdown | توزيع التكلفة | I68: SR/TDA.m² | J68: SR | AA68: التمويل | AB68: =J45 -> 259300000 | AC68: =AB68/$J$47 -> 0.51383906 | AD68: =الدراسة!B194 -> تكاليف مسطحات البناء (Construction Costs) | AE68: =-الدراسة!C194 -> 181440000
B69: إجمالي تكلفة الأرض بعد الضرائب - (Tota Land Cost After TAX) | I69: =I70+I71 -> 3271.1538 | J69: =J70+J71 -> 223256250 | AD69: =الدراسة!B195 -> التسوير (Fence - surrounding the land) | AE69: =-الدراسة!C195 -> 525000
B70: (Land Cost Before TAX) - تكلفة الأرض قبل الضرائب | I70: =J70/$H$16 -> 3230.7692 | J70: =الدراسة!E44 -> 220500000 | AA70: اشتراكات نقدية من مالك الأرض | AB70: =+J44 -> 220500000 | AC70: =AB70/J47 -> 0.43695146 | AD70: =الدراسة!B196 -> الحفر والمسح والاختبار (Excavation, surveying, and testing) | AE70: =-الدراسة!C196 -> 3024000
B71: (Commissions) - العمولة | I71: =J71/$H$16 -> 40.384615 | J71: =الدراسة!G44 -> 2756250 | AD71: =الدراسة!B197 -> التأمين (Insurance) | AE71: =-الدراسة!C197 -> 3084480
AA72: =AA67 -> مصادر أخرى | AB72: =AB67 -> 24832715 | AD72: =الدراسة!B200 -> أثاث الوحدات الفندقية (Apartment furniture) | AE72: =-الدراسة!C200 -> 0
B73: (Development) - التطوير | I73: =I74+I75+I76 -> 3359.0386 | J73: =J74+J75+J76 -> 2.2925438e+08 | AA73: =AA68 -> التمويل | AB73: =AB68 -> 259300000 | AD73: =الدراسة!B201 -> أثاث الوحدات (Apartment furniture) | AE73: =-الدراسة!C201 -> 0
B74: (Hard Cost - Construction) - تكلفة البناء | I74: =J74/$H$16 -> 2658.4615 | J74: =الدراسة!C19 -> 181440000 | AA74: الملكية | AB74: =AB69+AB70 -> 220500000 | AD74: =الدراسة!B202 -> رسوم كهرباء (Electricity fees) | AE74: =-الدراسة!C202 -> 2676000
B75: Soft Costs (Fees,Consultants, Insurance, Permits, Overheads etc) - التكاليف الأخرى | I75: =J75/$H$16 -> 408.57846 | J75: =الدراسة!C101-الدراسة!C98-الدراسة!C99 -> 27885480 | AD75: =الدراسة!B203 -> رسوم الماء وصرف الصحي (Water and sewer fees) | AE75: =-الدراسة!C203 -> 1440000
B76: 0.12 | I76: =J76/$H$16 -> 291.99858 | J76: =الدراسة!C103 -> 19928903 | AD76: =الدراسة!B204 -> الفرز (Sorting) | AE76: =-الدراسة!C204 -> 240000
AD77: =الدراسة!B205 -> الصيانة و التشغيل (Maintenance and Operation) | AE77: =-الدراسة!C205 -> 3120000
B78: Marketing (RASF) - التسويق | I78: =J78/H16 -> 10.139662 | J78: =الدراسة!C98+الدراسة!C99 -> 692031.9 | AD78: =الدراسة!B206 -> الاحتياطي (Contingency) | AE78: =-الدراسة!C206 -> 3628800
AD79: =الدراسة!B207 -> التسويق المبيعات والتأجير (Sales and Leasing Marketing) | AE79: =-الدراسة!C207 -> 692031.9
B80: إجمالي تكاليف التمويل - (Total Financing Costs) | I80: =I82+I81 -> 617.35568 | J80: =J82+J81 -> 42134525 | AD80: =الدراسة!B208 -> الإشراف الهندسي (Engineering Supervision) | AE80: =-الدراسة!C208 -> 5443200
B81: =الدراسة!C190 -> 0.073 | I81: =J81/$H$16 -> 598.35934 | J81: =-الدراسة!E190 -> 40838025
B82: =الدراسة!C191 -> 0.005 | I82: =J82/$H$16 -> 18.996337 | J82: =-الدراسة!E191 -> 1296500
B84: (TotaI Fund expenses) - إجمالي تكاليف الصندوق | I84: =I85+I86 -> 136.19817 | J84: =J85+J86 -> 9295525.2
B85: =الدراسة!D104 -> 0.005 | I85: =J85/$H$16 -> 120.18352 | J85: =الدراسة!C104 -> 8202525.2
B86: التكاليف الأخرى للصندوق - (Other costs) | I86: =J86/$H$16 -> 16.014652 | J86: =الدراسة!C105 -> 1093000
B114: Total Costs - إجمالي التكاليف | I114: =J114/H16 -> 7393.8859 | J114: =J84+J80+J73+J69+J78 -> 5.0463272e+08
B137: Fund Economics | اقتصاديات الصندوق | J137: SR
B138: إجمالي إيرادات التأجير السنوي - (Total Annual Rental Revenue) | J138: =الدراسة!C183 -> 49430850
B139: المخارجة - (Buyout) | J139: =الدراسة!C186 -> 617885625
B140: إجمالي الإيرادات - (Total Revenue) | J140: =SUM(J138:J139) -> 667316475
B144: جدول تحليل الحساسية | Sensitivity Analysis Table | C144: متشائم (Pessimistic) | D144: منخفض (Low) | F144: متوسط (Normal) | I144: متفائل (Optimistic) | J144: متفائل جداً (Very optimistic)
B145: نسبة الارتفاع او الانخفاض (Rate of Increase or Decrease) | C145: 0.1 | D145: 0.05 | F145: 0 | I145: 0.05 | J145: 0.1
B146: صافي الربح - (Net Income) | C146: =F146-(F146*$C$145) -> 1.3306905e+08 | D146: =F146-(F146*$D$145) -> 1.4046178e+08 | F146: =الدراسة!C214 -> 1.478545e+08 | I146: =F146+(F146*$I$145) -> 1.5524723e+08 | J146: =F146+(F146*$J$145) -> 1.6263996e+08
B147: العائد على الإستثمار - (ROI) | C147: =F147-(F147*$C$145) -> 0.29014247 | D147: =F147-(F147*$D$145) -> 0.3062615 | F147: =الدراسة!C220 -> 0.32238053 | I147: =F147+(F147*$I$145) -> 0.33849955 | J147: =F147+(F147*$J$145) -> 0.35461858
B148: العائد على الملكية - (ROE) | C148: =F148-(F148*$C$145) -> 0.66401535 | D148: =F148-(F148*$D$145) -> 0.70090509 | F148: =الدراسة!C221 -> 0.73779483 | I148: =F148+(F148*$I$145) -> 0.77468457 | J148: =F148+(F148*$J$145) -> 0.81157431
B149: العائد على الملكية سنويا - (ROE Annualy) | C149: =F149-(F149*$C$145) -> 0.17537308 | D149: =F149-(F149*$D$145) -> 0.18511603 | F149: =الدراسة!C222 -> 0.19485898 | I149: =F149+(F149*$I$145) -> 0.20460193 | J149: =F149+(F149*$J$145) -> 0.21434488
