Workbook
Name AuditFailsCommercial: [1]Audit!$G$12
Name AuditFailsStructural: [1]Audit!$G$11
Name AuditOK: [1]Audit!$G$13

Sheet Cover Page
H1: Legal Disclaimer and Warning: This financial model is confidential property of Rasf Investment, and all rights are fully reserved. It has been shared with you for a specific and authorized purpose only. Any copying, sharing, modification, or use of this file for any other purpose without prior written consent from Rasf Investment is strictly prohibited. If such unauthorized use occurs, legal action will be taken against you in a court of law.
A16: تفاصيل الدراسة (Study Details) | I16: درة الغدير - مشروع مختلط (Mix Use Development - RASF - Alghadeer)
D19: ------------------------------------ | L19: ------------------------------------
A20: التاريخ (Date) | I20: 46147
D23: ------------------------------------ | L23: ------------------------------------
A24: محتويات الدراسة (Study Contents) | I24: Study

Sheet Study
AE2: توزيع تكاليف المشروع على مكونات البيع المباشر و التأجير السنوي و اليومي | BH2: جدول المؤشرات العامة للمشروع | General Project Indicators Table | BL2: الحدود المرجعية أو المثلى للمؤشرات (Reference Ranges for Indicators) | BN2: سعر المتر بناءً على فترة الاسترداد - (التأجير السنوي) | BQ2: سعر المتر بناءً على فترة الاسترداد - (التأجير اليومي) | BV2: اسم المشروع | BW2: برج جدة | CA2: حالة المشروع | CB2: تاريخ الانتهاء المتوقع
AE3: المكون | AF3: توزيع تكاليف الأرض | AG3: جزء من تكاليف البناء | AH3: نسبة توزيع تكاليف اللاندسكيب | AI3: توزيع تكاليف اللاندسكيب | AJ3: توزيع تكاليف البوديم و القبو | AK3: توزيع تكاليف الحفر والمسح و الاختبار | AL3: توزيع تكاليف المساحات الحركية والخدمية | AM3: نسب التكاليف السابقة من التكاليف الموجودة بالجدول | AN3: نسب التكاليف السابقة من التكاليف الكلية | AO3: نسب المكون من البيع المباشر أو المخارجة من الإجمالي | AP3: توزيع التكاليف الأخرى | AQ3: توزيع تكاليف أخرى إضافية | AR3: توزيع تكاليف التمويل | AS3: توزيع تكاليف الصندوق | AT3: توزيع التكاليف التشغيلية | AU3: إجمالي تكاليف كل مكون | AV3: توزيع التكلفة على الأمتار البيعية | AW3: نسبة تكاليف كل مكون من إجمالي المشروع | AX3: إجمالي إيراد كل مكون | AY3: صافي العائد لكل م² بيعي | AZ3: صافي دخل كل مكون | BA3: العائد النسبي للمكون | BB3: هامش الربح من إجمالي الإرادات | BC3: نسبة صافي دخل كل مكون من إجمالي صافي دخل المشروع | BD3: نسبة صافي دخل كل مكون | BN3: المكون (Component) | BO3: سعر المتر | BP3: فترة الأسترداد - بالسنوات | BQ3: المكون (Component) | BR3: سعر المتر | BS3: فترة الأسترداد - بالسنوات | BV3: اسم الصندوق (fund Name) | BW3: إتقان | CA3: مرحلة توقيع العقود | CB3: ?
AE4: سكني | AF4: =I41 -> 15362564 | AG4: =J57*AO4 -> 7800408 | AH4: 0 | AI4: =($J$69*AH4)*AO4 -> 0 | AL4: =(((D57-F57)/$I$55)*$J$67)*AO4 -> 0 | AM4: =SUM(AF4:AG4,AI4:AL4)/$AM$14 -> 0.14502019 | AN4: =SUM(AF4:AG4,AI4:AL4)/$AN$14 -> 0.11361589 | AO4: =D125 -> 1 | AP4: =(AN4*SUM($C$82,$C$84:$C$85,$C$92:$C$93))+((H143+X143)/($H$153+$X$153))*$C$95+(SUM($D$89:$D$91)*G57*AO4) -> 749188.5 | AQ4: =(($A$88+$C$94)*AM4)+((C86+C97)*15%) -> 887297.5 | AR4: =AM4*$C$115 -> 1035720.2 | AS4: =AN4*$C$103 -> 2535299.6 | AT4: =SUM(I143,Y143) -> 123565.55 | AU4: =SUM(AF4:AG4,AI4:AL4,AP4:AT4) -> 28494043 | AV4: =IFERROR((AU4-AT4)/E125, "0") -> 9413.5425 | AW4: =(AU4-AT4)/($C$19) -> 0.12852438 | AX4: =SUM(J125,H143,O125,X143) -> 31818130 | AY4: =IFERROR(AZ4/E125, "0.00") -> 1102.9575 | AZ4: =AX4-AU4 -> 3324086.8 | BA4: =IFERROR(BD4/AW4, "0.00") -> 0.91163333 | BB4: =IFERROR(AZ4/AX4, "0.00%") -> 0.10447147 | BC4: =AZ4/$C$21 -> 0.038691214 | BD4: =IFERROR(AZ4/(AU4-AT4), "0.00%") -> 0.11716711 | BE4: سكني | BN4: سكني (Apartments) | BO4: =IFERROR((AU4-AT4) / (C143 * D143 * G143 * (1 - $I$154) * BP4), 0) -> 0 | BQ4: سكني (Apartments) | BR4: =IFERROR((AU4-AT4) / ((R143 * S143 * (1 - $Y$154) * 365 * BS4) * (1 + W143)), 0) -> 0 | BV4: =B15 -> إجمالي تكلفة البناء (Total Construction Cost) | BW4: =J72 -> 78265608
AE5: فلل | AF5: =I42 -> 27351260 | AG5: =J58*AO5 -> 0 | AH5: 0 | AI5: =($J$69*AH5)*AO5 -> 0 | AJ5: =((K58/$L$72)*($J$70+$J$71))*AO5 -> 0 | AK5: =((K58/$L$72)*$C$83)*AO5 -> 0 | AL5: =(((D58-F58)/$I$55)*$J$67)*AO5 -> 0 | AM5: =SUM(AF5:AG5,AI5:AL5)/$AM$14 -> 0.17124249 | AN5: =SUM(AF5:AG5,AI5:AL5)/$AN$14 -> 0.13415971 | AO5: =D126 -> 0 | AP5: =(AN5*SUM($C$82,$C$84:$C$85,$C$92:$C$93))+((H144+X144)/($H$153+$X$153))*$C$95+(SUM($D$89:$D$91)*G58*AO5) -> 456192.67 | AQ5: =(($A$88+$C$94)*AM5)+((C86+C97)*15%) -> 888528.77 | AR5: =AM5*$C$115 -> 1222997.3 | AS5: =AN5*$C$103 -> 2993728 | AT5: =SUM(I144,Y144) -> 0 | AU5: =SUM(AF5:AG5,AI5:AL5,AP5:AT5) -> 32912707 | AV5: =IFERROR((AU5-AT5)/E126, "0") -> 9854.1038 | AW5: =(AU5-AT5)/($C$19) -> 0.14910165 | AX5: =SUM(J126,H144,O126,X144) -> 0 | AY5: =IFERROR(AZ5/E126, "0.00") -> -9854.1038 | AZ5: =AX5-AU5 -> -32912707 | BA5: =IFERROR(BD5/AW5, "0.00") -> -6.7068337 | BB5: =IFERROR(AZ5/AX5, "0.00%") -> 0.00% | BC5: =AZ5/$C$21 -> -0.38309246 | BD5: =IFERROR(AZ5/(AU5-AT5), "0.00%") -> -1 | BE5: فلل | BH5: مؤشرات التكاليف والكفاءة (Costs & Efficiency Indicators) | BN5: فلل (Villas) | BO5: =IFERROR((AU5-AT5) / (C144 * D144 * G144 * (1 - $I$154) * BP5), 0) -> 0 | BQ5: فلل (Villas) | BR5: =IFERROR((AU5-AT5) / ((R144 * S144 * (1 - $Y$154) * 365 * BS5) * (1 + W144)), 0) -> 0 | BV5: =B19 -> إجمالي التكاليف الرأسمالية للمشروع (Total Capital Expenditures) | BW5: =C19 -> 2.2074005e+08
AE6: تاون هاوس | AF6: =((F59/$J$55)*$I$45)*AO6 -> 0 | AG6: =J59*AO6 -> 0 | AH6: 0 | AI6: =($J$69*AH6)*AO6 -> 0 | AJ6: =((K59/$L$72)*($J$70+$J$71))*AO6 -> 0 | AK6: =((K59/$L$72)*$C$83)*AO6 -> 0 | AL6: =(((D59-F59)/$I$55)*$J$67)*AO6 -> 0 | AM6: =SUM(AF6:AG6,AI6:AL6)/$AM$14 -> 0 | AN6: =SUM(AF6:AG6,AI6:AL6)/$AN$14 -> 0 | AO6: =D127 -> 1 | AP6: =(AN6*SUM($C$82,$C$84:$C$86,$C$92:$C$93,$C$97))+((H145+X145)/($H$153+$X$153))*$C$95+(SUM($D$89:$D$91)*G59*AO6) -> 0 | AQ6: =(($A$88+$C$94)*AM6) -> 0 | AR6: =AM6*$C$115 -> 0 | AS6: =AN6*$C$103 -> 0 | AT6: =SUM(I145,Y145) -> 0 | AU6: =SUM(AF6:AG6,AI6:AL6,AP6:AT6) -> 0 | AV6: =IFERROR((AU6-AT6)/E127, "0") -> 0 | AW6: =(AU6-AT6)/($C$19) -> 0 | AX6: =SUM(J127,H145,O127,X145) -> 0 | AY6: =IFERROR(AZ6/E127, "0.00") -> 0.00 | AZ6: =AX6-AU6 -> 0 | BA6: =IFERROR(BD6/AW6, "0.00") -> 0.00 | BB6: =IFERROR(AZ6/AX6, "0.00%") -> 0.00% | BC6: =AZ6/$C$21 -> 0 | BD6: =IFERROR(AZ6/(AU6-AT6), "0.00%") -> 0.00% | BE6: تاون هاوس | BH6: التكلفة لكل م² من إجمالي المساحات التطويرية (Cost per m² of Total Built-Up Area) | BI6: =C19/G55 -> 6941.5896 | BL6: - | BN6: تاون هاوس (Townhouse) | BO6: =IFERROR((AU6-AT6) / (C145 * D145 * G145 * (1 - $I$154) * BP6), 0) -> 0 | BQ6: تاون هاوس (Townhouse) | BR6: =IFERROR((AU6-AT6) / ((R145 * S145 * (1 - $Y$154) * 365 * BS6) * (1 + W145)), 0) -> 0 | BV6: =B13 -> إجمالي الإيرادات (Total Revenue) | BW6: =C13 -> 3.1318259e+08
AE7: أدوار | AF7: =((F60/$J$55)*$I$45)*AO7 -> 0 | AG7: =J60*AO7 -> 0 | AH7: 0 | AI7: =($J$69*AH7)*AO7 -> 0 | AJ7: =((K60/$L$72)*($J$70+$J$71))*AO7 -> 0 | AK7: =((K60/$L$72)*$C$83)*AO7 -> 0 | AL7: =(((D60-F60)/$I$55)*$J$67)*AO7 -> 0 | AM7: =SUM(AF7:AG7,AI7:AL7)/$AM$14 -> 0 | AN7: =SUM(AF7:AG7,AI7:AL7)/$AN$14 -> 0 | AO7: =D128 -> 1 | AP7: =(AN7*SUM($C$82,$C$84:$C$86,$C$92:$C$93,$C$97))+((H146+X146)/($H$153+$X$153))*$C$95+(SUM($D$89:$D$91)*G60*AO7) -> 0 | AQ7: =(($A$88+$C$94)*AM7) -> 0 | AR7: =AM7*$C$115 -> 0 | AS7: =AN7*$C$103 -> 0 | AT7: =SUM(I146,Y146) -> 0 | AU7: =SUM(AF7:AG7,AI7:AL7,AP7:AT7) -> 0 | AV7: =IFERROR((AU7-AT7)/E128, "0") -> 0 | AW7: =(AU7-AT7)/($C$19) -> 0 | AX7: =SUM(J128,H146,O128,X146) -> 0 | AY7: =IFERROR(AZ7/E128, "0.00") -> 0.00 | AZ7: =AX7-AU7 -> 0 | BA7: =IFERROR(BD7/AW7, "0.00") -> 0.00 | BB7: =IFERROR(AZ7/AX7, "0.00%") -> 0.00% | BC7: =AZ7/$C$21 -> 0 | BD7: =IFERROR(AZ7/(AU7-AT7), "0.00%") -> 0.00% | BE7: أدوار | BH7: التكلفة لكل م² من إجمالي المساحات القابلة للبيع (Cost per m² of Saleable Area) | BI7: =C19/J55 -> 22250.24 | BL7: - | BN7: أدوار (Floors) | BO7: =IFERROR((AU7-AT7) / (C146 * D146 * G146 * (1 - $I$154) * BP7), 0) -> 0 | BQ7: أدوار (Floors) | BR7: =IFERROR((AU7-AT7) / ((R146 * S146 * (1 - $Y$154) * 365 * BS7) * (1 + W146)), 0) -> 0 | BV7: =B30 -> العائد على الملكية السنوي (ROE Annually) | BW7: =C28 -> 0.7924872
AE8: أستوديوهات | AF8: =((F61/$J$55)*$I$45)*AO8 -> 0 | AG8: =J61*AO8 -> 0 | AH8: 0 | AI8: =($J$69*AH8)*AO8 -> 0 | AJ8: =((K61/$L$72)*($J$70+$J$71))*AO8 -> 0 | AK8: =((K61/$L$72)*$C$83)*AO8 -> 0 | AL8: =(((D61-F61)/$I$55)*$J$67)*AO8 -> 0 | AM8: =SUM(AF8:AG8,AI8:AL8)/$AM$14 -> 0 | AN8: =SUM(AF8:AG8,AI8:AL8)/$AN$14 -> 0 | AO8: =D129 -> 1 | AP8: =(AN8*SUM($C$82,$C$84:$C$86,$C$92:$C$93,$C$97))+((H147+X147)/($H$153+$X$153))*$C$95+(SUM($D$89:$D$91)*G61*AO8) -> 0 | AQ8: =(($A$88+$C$94)*AM8) -> 0 | AR8: =AM8*$C$115 -> 0 | AS8: =AN8*$C$103 -> 0 | AT8: =SUM(I147,Y147) -> 0 | AU8: =SUM(AF8:AG8,AI8:AL8,AP8:AT8) -> 0 | AV8: =IFERROR((AU8-AT8)/E129, "0") -> 0 | AW8: =(AU8-AT8)/($C$19) -> 0 | AX8: =SUM(J129,H147,O129,X147) -> 0 | AY8: =IFERROR(AZ8/E129, "0.00") -> 0.00 | AZ8: =AX8-AU8 -> 0 | BA8: =IFERROR(BD8/AW8, "0.00") -> 0.00 | BB8: =IFERROR(AZ8/AX8, "0.00%") -> 0.00% | BC8: =AZ8/$C$21 -> 0 | BD8: =IFERROR(AZ8/(AU8-AT8), "0.00%") -> 0.00% | BE8: أستوديوهات | BH8: إجمالي التكاليف الصلبة (Total Hard Costs) | BI8: =-SUM(C192:C194,C198:C199) -> 87785008 | BJ8: =BI8/($C$19+$C$20) -> 0.38625975 | BL8: - | BN8: أستوديوهات (Studios) | BO8: =IFERROR((AU8-AT8) / (C147 * D147 * G147 * (1 - $I$154) * BP8), 0) -> 0 | BQ8: أستوديوهات (Studios) | BR8: =IFERROR((AU8-AT8) / ((R147 * S147 * (1 - $Y$154) * 365 * BS8) * (1 + W147)), 0) -> 0 | CA8: -
AE9: مكتبي | AF9: =((F62/$J$55)*$I$45)*AO9 -> 0 | AG9: =J62*AO9 -> 0 | AI9: =($J$69*AH9)*AO9 -> 0 | AJ9: =((K62/$L$72)*($J$70+$J$71))*AO9 -> 0 | AK9: =((K62/$L$72)*$C$83)*AO9 -> 0 | AL9: =(((D62-F62)/$I$55)*$J$67)*AO9 -> 0 | AM9: =SUM(AF9:AG9,AI9:AL9)/$AM$14 -> 0 | AN9: =SUM(AF9:AG9,AI9:AL9)/$AN$14 -> 0 | AO9: =D130 -> 1 | AP9: =(AN9*SUM($C$82,$C$84:$C$86,$C$92:$C$93,$C$97))+((H148+X148)/($H$153+$X$153))*$C$95+(SUM($D$89:$D$91)*G62*AO9) -> 0 | AQ9: =(($A$88+$C$94)*AM9) -> 0 | AR9: =AM9*$C$115 -> 0 | AS9: =AN9*$C$103 -> 0 | AT9: =SUM(I148,Y148) -> 0 | AU9: =SUM(AF9:AG9,AI9:AL9,AP9:AT9) -> 0 | AV9: =IFERROR((AU9-AT9)/E130, "0") -> 0 | AW9: =(AU9-AT9)/($C$19) -> 0 | AX9: =SUM(J130,H148,O130,X148) -> 0 | AY9: =IFERROR(AZ9/E130, "0.00") -> 0.00 | AZ9: =AX9-AU9 -> 0 | BA9: =IFERROR(BD9/AW9, "0.00") -> 0.00 | BB9: =IFERROR(AZ9/AX9, "0.00%") -> 0.00% | BC9: =AZ9/$C$21 -> 0 | BD9: =IFERROR(AZ9/(AU9-AT9), "0.00%") -> 0.00% | BE9: مكتبي | BH9: إجمالي التكاليف اللينة (Total Soft Costs) | BI9: =-SUM(C195:C197,C200:C203,C205:C208,C210:C212) -> 32791331 | BJ9: =BI9/($C$19+$C$20) -> 0.14428399 | BL9: - | BN9: مكتبي (Office) | BO9: =IFERROR((AU9-AT9) / (C148 * D148 * G148 * (1 - $I$154) * BP9), 0) -> 0 | BQ9: مكتبي (Office) | BR9: =IFERROR((AU9-AT9) / ((R148 * S148 * (1 - $Y$154) * 365 * BS9) * (1 + W148)), 0) -> 0 | BV9: اشتراكات رصف | BW9: نسبة الحصة | BX9: مبلغ الاشتراك | BY9: الآلية | BZ9: صافي الربح | CA9: مبلغ الاشتراك + صافي الربح | CB9: ملاحظات
AE10: تجاري | AF10: =((F63/$J$55)*$I$45)*AO10 -> 0 | AG10: =J63*AO10 -> 0 | AI10: =($J$69*AH10)*AO10 -> 0 | AJ10: =((K63/$L$72)*($J$70+$J$71))*AO10 -> 0 | AK10: =((K63/$L$72)*$C$83)*AO10 -> 0 | AL10: =(((D63-F63)/$I$55)*$J$67)*AO10 -> 0 | AM10: =SUM(AF10:AG10,AI10:AL10)/$AM$14 -> 0 | AN10: =SUM(AF10:AG10,AI10:AL10)/$AN$14 -> 0 | AO10: =D131 -> 1 | AP10: =(AN10*SUM($C$82,$C$84:$C$86,$C$92:$C$93,$C$97))+((H149+X149)/($H$153+$X$153))*$C$95+(SUM($D$89:$D$91)*G63*AO10) -> 0 | AQ10: =(($A$88+$C$94)*AM10) -> 0 | AR10: =AM10*$C$115 -> 0 | AS10: =AN10*$C$103 -> 0 | AT10: =SUM(I149,Y149) -> 0 | AU10: =SUM(AF10:AG10,AI10:AL10,AP10:AT10) -> 0 | AV10: =IFERROR((AU10-AT10)/E131, "0") -> 0 | AW10: =(AU10-AT10)/($C$19) -> 0 | AX10: =SUM(J131,H149,O131,X149) -> 0 | AY10: =IFERROR(AZ10/E131, "0.00") -> 0.00 | AZ10: =AX10-AU10 -> 0 | BA10: =IFERROR(BD10/AW10, "0.00") -> 0.00 | BB10: =IFERROR(AZ10/AX10, "0.00%") -> 0.00% | BC10: =AZ10/$C$21 -> 0 | BD10: =IFERROR(AZ10/(AU10-AT10), "0.00%") -> 0.00% | BE10: تجاري | BH10: إجمالي التكاليف التي لا تندرج كصلبة أو لينة (Total costs that do not fall under hard or soft costs) | BI10: =-SUM(E188:E189,C190:C191,C204,C209) -> 1.0669303e+08 | BJ10: =BI10/($C$19+$C$20) -> 0.46945626 | BL10: - | BN10: تجاري (Retail) | BO10: =IFERROR((AU10-AT10) / (C149 * D149 * G149 * (1 - $I$154) * BP10), 0) -> 0 | BQ10: تجاري (Retail) | BR10: =IFERROR((AU10-AT10) / ((R149 * S149 * (1 - $Y$154) * 365 * BS10) * (1 + W149)), 0) -> 0 | BV10: الحصة العينية من التطوير | BW10: 1 | BX10: =H18*BW10 -> 0 | BY10: استثمار عيني | BZ10: =BX10*$BW$7 -> 0 | CA10: =BZ10+BX10 -> 0 | CB10: -
B11: Feasibility Study Summary | ملخص دراسة الجدوى | G11: Financial Structuring | الهيكلة المالية | AE11: فندقي | AF11: =I40 -> 49134000 | AG11: =J64*AO11 -> 36900000 | AH11: 1 | AI11: =($J$69*AH11)*AO11 -> 6162000 | AJ11: =J70 -> 14176800 | AK11: =C83 -> 2835360 | AL11: =(((D64-F64)/$I$55)*$J$67)*AO11 -> 0 | AM11: =SUM(AF11:AG11,AI11:AL11)/$AM$14 -> 0.68373732 | AN11: =SUM(AF11:AG11,AI11:AL11)/$AN$14 -> 0.53567315 | AO11: =D132 -> 1 | AP11: =(AN11*SUM($C$82,$C$84:$C$85,$C$92:$C$93))+((H150+X150)/($H$153+$X$153))*$C$95+((SUM($D$90:$D$91)*G64*AO11)+(D89*G64/2*AO11)) -> 4250586.9 | AQ11: =(((($C$94)*AM11))+C87)+((C86+C97)*70%) -> 10291049 | AR11: =AM11*$C$115 -> 4883185.8 | AS11: =AN11*$C$103 -> 11953363 | AT11: =SUM(I150,Y150) -> 6405750 | AU11: =SUM(AF11:AG11,AI11:AL11,AP11:AT11) -> 1.4699209e+08 | AV11: =IFERROR((AU11-AT11)/E132, "0") -> 39413.049 | AW11: =(AU11-AT11)/($C$19) -> 0.63688644 | AX11: =SUM(J132,H150,O132,X150) -> 2.348775e+08 | AY11: =IFERROR(AZ11/E132, "0.00") -> 24638.465 | AZ11: =AX11-AU11 -> 87885405 | BA11: =IFERROR(BD11/AW11, "0.00") -> 0.98154817 | BB11: =IFERROR(AZ11/AX11, "0.00%") -> 0.3741755 | BC11: =AZ11/$C$21 -> 1.0229555 | BD11: =IFERROR(AZ11/(AU11-AT11), "0.00%") -> 0.62513472 | BE11: فندقي | BH11: إجمالي التكاليف المباشرة (Total Direct Costs) | BI11: =-SUM(C190:C194,C198:C202,C209) -> 1.8807665e+08 | BJ11: =BI11/($C$19+$C$20) -> 0.82754949 | BL11: غالبًا تمثل 70% – 85% من إجمالي التكاليف | BN11: فندقي (Hotel) | BO11: =IFERROR((AU11-AT11) / (C150 * D150 * G150 * (1 - $I$154) * BP11), 0) -> 0 | BQ11: فندقي (Hotel) | BR11: =IFERROR((AU11-AT11) / ((R150 * S150 * (1 - $Y$154) * 365 * BS11) * (1 + W150)), 0) -> 0 | BV11: الحصة من التطوير | BW11: 0 | BX11: - | BY11: - | BZ11: =H18*BW11 -> 0 | CA11: =BZ11 -> 0 | CB11: -
B12: البند (Item) | C12: القيمة (Value) | G12: رأس المال - (capital) | AE12: صحي | AF12: =((F65/$J$55)*$I$45)*AO12 -> 0 | AG12: =J65*AO12 -> 0 | AI12: =($J$69*AH12)*AO12 -> 0 | AJ12: =((K65/$L$72)*($J$70+$J$71))*AO12 -> 0 | AK12: =((K65/$L$72)*$C$83)*AO12 -> 0 | AL12: =(((D65-F65)/$I$55)*$J$67)*AO12 -> 0 | AM12: =SUM(AF12:AG12,AI12:AL12)/$AM$14 -> 0 | AN12: =SUM(AF12:AG12,AI12:AL12)/$AN$14 -> 0 | AO12: =D133 -> 1 | AP12: =(AN12*SUM($C$82,$C$84:$C$86,$C$92:$C$93,$C$97))+((H151+X151)/($H$153+$X$153))*$C$95+(SUM($D$89:$D$91)*G65*AO12) -> 0 | AQ12: =(($A$88+$C$94)*AM12) -> 0 | AR12: =AM12*$C$115 -> 0 | AS12: =AN12*$C$103 -> 0 | AT12: =SUM(I151,Y151) -> 0 | AU12: =SUM(AF12:AG12,AI12:AL12,AP12:AT12) -> 0 | AV12: =IFERROR((AU12-AT12)/E133, "0") -> 0 | AW12: =(AU12-AT12)/($C$19) -> 0 | AX12: =SUM(J133,H151,O133,X151) -> 0 | AY12: =IFERROR(AZ12/E133, "0.00") -> 0.00 | AZ12: =AX12-AU12 -> 0 | BA12: =IFERROR(BD12/AW12, "0.00") -> 0.00 | BB12: =IFERROR(AZ12/AX12, "0.00%") -> 0.00% | BC12: =AZ12/$C$21 -> 0 | BD12: =IFERROR(AZ12/(AU12-AT12), "0.00%") -> 0.00% | BE12: صحي | BH12: إجمالي التكاليف غير المباشرة (Total Indirect Costs) | BI12: =-SUM(E188:E189,C195:C197,C203:C208,C210:C212) -> 39192718 | BJ12: =BI12/($C$19+$C$20) -> 0.17245051 | BL12: من 15% إلى 25% من إجمالي التكاليف غالبًا | BN12: صحي (health) | BO12: =IFERROR((AU12-AT12) / (C151 * D151 * G151 * (1 - $I$154) * BP12), 0) -> 0 | BQ12: صحي (health) | BR12: =IFERROR((AU12-AT12) / ((R151 * S151 * (1 - $Y$154) * 365 * BS12) * (1 + W151)), 0) -> 0 | BV12: الحصة العينية من المقاولات | BW12: 1 | BX12: =(E99*C191)*BW12 -> 0 | BY12: - | BZ12: =BX12*$BW$7 -> 0 | CA12: =BZ12+BX12 -> 0 | CB12: -
B13: إجمالي الإيرادات (Total Revenue) | C13: =SUM(C180:C184) -> 3.1318259e+08 | G13: المصدر (Source) | H13: SAR | I13: % | AE13: شاليهات | AF13: =((F66/$J$55)*$I$45)*AO13 -> 0 | AG13: =J66*AO13 -> 0 | AI13: =($J$69*AH13)*AO13 -> 0 | AJ13: =((K66/$L$72)*($J$70+$J$71))*AO13 -> 0 | AK13: =((K66/$L$72)*$C$83)*AO13 -> 0 | AL13: =(((D66-F66)/$I$55)*$J$67)*AO13 -> 0 | AM13: =SUM(AF13:AG13,AI13:AL13)/$AM$14 -> 0 | AN13: =SUM(AF13:AG13,AI13:AL13)/$AN$14 -> 0 | AO13: =D134 -> 1 | AP13: =(AN13*SUM($C$82,$C$84:$C$86,$C$92:$C$93,$C$97))+((H152+X152)/($H$153+$X$153))*$C$95+(SUM($D$89:$D$91)*G66*AO13) -> 0 | AQ13: =(($A$88+$C$94)*AM13) -> 0 | AR13: =AM13*$C$115 -> 0 | AS13: =AN13*$C$103 -> 0 | AT13: =SUM(I152,Y152) -> 0 | AU13: =SUM(AF13:AG13,AI13:AL13,AP13:AT13) -> 0 | AV13: =IFERROR((AU13-AT13)/E134, "0") -> 0 | AW13: =(AU13-AT13)/($C$19) -> 0 | AX13: =SUM(J134,H152,O134,X152) -> 0 | AY13: =IFERROR(AZ13/E134, "0.00") -> 0.00 | AZ13: =AX13-AU13 -> 0 | BA13: =IFERROR(BD13/AW13, "0.00") -> 0.00 | BB13: =IFERROR(AZ13/AX13, "0.00%") -> 0.00% | BC13: =AZ13/$C$21 -> 0 | BD13: =IFERROR(AZ13/(AU13-AT13), "0.00%") -> 0.00% | BE13: شاليهات | BH13: إجمالي التكاليف التشغيلية (Total Operating Costs) | BI13: =C20 -> 6529315.6 | BJ13: =BI13/SUM(C19:C20) -> 0.028729413 | BL13: - | BN13: شاليهات (Chalets) | BO13: =IFERROR((AU13-AT13) / (C152 * D152 * G152 * (1 - $I$154) * BP13), 0) -> 0 | BQ13: شاليهات (Chalets) | BR13: =IFERROR((AU13-AT13) / ((R152 * S152 * (1 - $Y$154) * 365 * BS13) * (1 + W152)), 0) -> 0 | BV13: الحصة من المقاولات | BW13: 0 | BX13: - | BY13: - | BZ13: =(E100*C192)*BW13 -> 0 | CA13: =BZ13 -> 0 | CB13: -
B14: إجمالي تكلفة الأرض (Total Land Cost) | C14: =I45 -> 91847824 | G14: (Equity) - الملكية | AE14: الإجمالي | AF14: =SUMIF(AF4:AF13, "<>#DIV/0!") -> 91847824 | AG14: =SUMIF(AG4:AG13, "<>#DIV/0!") -> 44700408 | AH14: =SUM(AH4:AH13) -> 1 | AI14: =SUM(AI4:AI13) -> 6162000 | AJ14: =SUMIF(AJ4:AJ13, "<>#DIV/0!") -> 14176800 | AK14: =SUMIF(AK4:AK13, "<>#DIV/0!") -> 2835360 | AL14: =SUM(AL4:AL13) -> 0 | AM14: =SUM(AF14:AG14,AI14:AL14) -> 159722392 | AN14: =SUM(AF4:AG13,AI4:AL13,AF22:AG31,AI22:AL31) -> 2.0387089e+08 | AO14: - | AP14: =SUM(AP4:AQ13) -> 17522844 | AR14: =SUMIF(AR4:AR13, "<>#DIV/0!") -> 7141903.3 | AS14: =SUMIF(AS4:AS13, "<>#DIV/0!") -> 17482390 | AT14: =SUM(AT4:AT13) -> 6529315.6 | AU14: =SUM(AU4:AU13) -> 2.0839884e+08 | AV14: =IFERROR(AU14/E135, "0") -> 21006.267 | AW14: =SUMIF(AW4:AW13, "<>#DIV/0!") -> 0.91451247 | AX14: =SUMIF(AX4:AX13, "<>#DIV/0!") -> 2.6669563e+08 | AY14: =AZ14/E135 -> 5876.2217 | AZ14: =SUMIF(AZ4:AZ13, "<>#DIV/0!") -> 58296785 | BA14: - | BB14: =IFERROR(AZ14/AX14, "0.00%") -> 0.2185892 | BC14: =SUM(BC4:BC13) -> 0.6785543 | BD14: =IFERROR(AZ14/AU14, "0.00%") -> 0.27973661 | BH14: إجمالي قيمة ونسبة تكاليف الأرض من إجمالي تكاليف المشروع (Land Cost as Value and % of Total Project Cost) | BI14: =I45 -> 91847824 | BJ14: =BI14/$C$19 -> 0.41609044 | BL14: من 10% إلى 25% غالبًا | BV14: العمولات 2.5% من المبيعات | BW14: 0.025 | BX14: - | BY14: بيع على الخارطة + بيع مباشر + مخارجة | BZ14: =BW14*(J135+AC135+O135) -> 7233969.4 | CA14: =BZ14 -> 7233969.4 | CB14: -
B15: إجمالي تكلفة البناء (Total Construction Cost) | C15: =J72 -> 78265608 | G15: الاشتراكات النقدية (Cash Subscription) | H15: 34500000 | I15: =H15/$H$30 -> 0.15629244 | AF15: =IF(ABS(SUM(Study!AF14,Study!AF32)-SUM(Study!I45))<=0.00000001,"TRUE",SUM(Study!AF14,Study!AF32)-SUM(Study!I45)) -> 30922095 | AG15: =IF(ABS(SUM(Study!AG14,Study!AG32)-SUM(J57:J67))<=0.00000001,"TRUE",SUM(Study!AG14,Study!AG32)-SUM(J57:J67)) -> TRUE | AH15: =IF(ABS(SUM(Study!AH14)-SUM(1))<=0.00000001,"TRUE",SUM(Study!AH14)-SUM(1)) -> TRUE | AI15: =IF(ABS(SUM(Study!AI14,Study!AI32)-SUM(Study!J69))<=0.00000001,"TRUE",SUM(Study!AI14,Study!AI32)-SUM(Study!J69)) -> TRUE | AJ15: =IF(ABS(SUM(Study!AJ14,Study!AJ32)-SUM(J70:J71))<=0.00000001,"TRUE",SUM(Study!AJ14,Study!AJ32)-SUM(J70:J71)) -> TRUE | AK15: =IF(ABS(SUM(Study!AK14,Study!AK32)-SUM(Study!C83))<=0.00000001,"TRUE",SUM(Study!AK14,Study!AK32)-SUM(Study!C83)) -> TRUE | AL15: =IF(ABS(SUM(Study!AL14,Study!AL32)-SUM(Study!J67))<=0.00000001,"TRUE",SUM(Study!AL14,Study!AL32)-SUM(Study!J67)) -> TRUE | AM15: =IF(ABS(SUM(Study!AM4:AM13)-SUM(1))<=0.00000001,"TRUE",SUM(Study!AM4:AM13)-SUM(1)) -> TRUE | AN15: =IF(ABS(SUM(Study!AN4:AN13,Study!AN22:AN31)-SUM(1))<=0.00000001,"TRUE",SUM(Study!AN4:AN13,Study!AN22:AN31)-SUM(1)) -> TRUE | AO15: =IF(ABS(SUM(Study!AO4:AO13,Study!AO22:AO31)-SUM(10))<=0.00000001,"TRUE",SUM(Study!AO4:AO13,Study!AO22:AO31)-SUM(10)) -> TRUE | AP15: =IF(ABS(SUM(Study!AP4:AQ13,Study!AP22:AQ31)-SUM(Study!C82,Study!C84:C97))<=0.1,"TRUE",SUM(Study!AP4:AQ13,Study!AP22:AQ31)-SUM(Study!C82,Study!C84:C97)) -> 1437638.7 | AR15: =IF(ABS(SUM(Study!AR14)-SUM(Study!C115))<=0.00000001,"TRUE",SUM(Study!AR14)-SUM(Study!C115)) -> TRUE | AS15: =IF(ABS(SUM(Study!AS14,Study!AS32)-SUM(Study!C103))<=1,"TRUE",SUM(Study!AS14,Study!AS32)-SUM(Study!C103)) -> TRUE | AT15: =IF(ABS(SUM(Study!AT14)-SUM(Study!C20))<=0.01,"TRUE",SUM(Study!AT14)-SUM(Study!C20)) -> TRUE | AU15: =IF(ABS(SUM(Study!AU14,Study!AU32)-SUM(Study!C19:C20))<=0.25,"TRUE",SUM(Study!AU14,Study!AU32)-SUM(Study!C19:C20)) -> -18870521 | AV15: =AV14=AV14 -> TRUE | AW15: =IF(ABS(SUM(Study!AW14,Study!AW32)-SUM(1))<=0.01,"TRUE",SUM(Study!AW14,Study!AW32)-SUM(1)) -> -0.085487528 | AX15: =IF(ABS(SUM(Study!AX14,Study!AX32)-SUM(Study!C13))<=0.01,"TRUE",SUM(Study!AX14,Study!AX32)-SUM(Study!C13)) -> TRUE | AY15: =AY14=AY14 -> TRUE | AZ15: =IF(ABS(SUM(Study!AZ14,Study!AZ32)-SUM(Study!C21))<=0.2,"TRUE",SUM(Study!AZ14,Study!AZ32)-SUM(Study!C21)) -> -27616435 | BA15: =BA14=BA14 -> TRUE | BB15: =BB14=BB14 -> TRUE | BC15: =IF(ABS(SUM(Study!BC14,Study!BC32)-SUM(1))<=0.01,"TRUE",SUM(Study!BC14,Study!BC32)-SUM(1)) -> -0.3214457 | BD15: =BD14=BD14 -> TRUE | BH15: إجمالي قيمة ونسبة تكاليف البناء من إجمالي تكاليف المشروع (Construction Cost as Value and % of Total Project Cost) | BI15: =J72 -> 78265608 | BJ15: =BI15/$C$19 -> 0.35456007 | BL15: المتوسط غالبًا بين 45% إلى 65% | BV15: نسبة رصف من المستثمرين | BW15: 0 | BX15: =BW15*H17 -> 0 | BY15: - | BZ15: =BX15*$BW$7 -> 0 | CA15: =BZ15+BX15 -> 0 | CB15: -
B16: إجمالي التكاليف الأخرى (Total Other cost) | C16: =C98 -> 21170058 | G16: الاشتراك من مدير الصندوق (fund manager's Subscription) | I16: =H16/$H$30 -> 0 | BH16: إجمالي قيمة ونسبة التكاليف الأخرى من إجمالي تكاليف المشروع (Other Costs as % of Total Project Cost) | BI16: =C98 -> 21170058 | BJ16: =BI16/$C$19 -> 0.095904925 | BL16: غالبًا بين 10% – 20% | BV16: الحصة من فارق قيمة الأرض | BW16: 1 | BX16: =K19*BW16 -> 0 | BY16: - | BZ16: =BX16*$BW$7 -> 0 | CA16: =BZ16+BX16 -> 0 | CB16: -
B17: إجمالي رسوم الصندوق (Total Fund Fees) | C17: =C103 -> 22314657 | G17: الأشتراك النقدي من المطور (Cash Subscription from Developer) | H17: 11100000 | I17: =H17/$H$30 -> 0.050285392 | J17: =H30*5% -> 11037003 | BH17: إجمالي قيمة ونسبة تكاليف فوائد التمويل من إجمالي تكاليف المشروع (Financing Interest as Value and % of Total Project Cost) | BI17: =C115 -> 7141903.3 | BJ17: =BI17/$C$19 -> 0.032354361 | BL17: من 5% – 12% حسب مدة التمويل والفوائد | BV17: اشتراكات نقدية / مصاريف سابقة | BW17: 0 | BX17: =H15*BW17 -> 0 | BY17: - | BZ17: =BX17*$BW$7 -> 0 | CA17: =BZ17+BX17 -> 0 | CB17: -
B18: فوائد التمويل (Interest) | C18: =C115 -> 7141903.3 | G18: الأشتراك العيني من المطور (In-Kind Subscription from Developer) | H18: =J18*((D100+E100)*-E192) -> 0 | I18: =H18/$H$30 -> 0 | J18: 0 | BH18: إجمالي قيمة ونسبة تكاليف الصندوق من إجمالي تكاليف المشروع (Fund Management Cost as Value and % of Total Project Cost) | BI18: =C103 -> 22314657 | BJ18: =BI18/$C$19 -> 0.10109021 | BL18: تتراوح من 1% – 7% حسب شروط الصندوق
B19: إجمالي التكاليف الرأسمالية للمشروع (Total Capital Expenditures) | C19: =SUM(C14:C18) -> 2.2074005e+08 | G19: الإشتراك العيني من مالك الأرض (In-Kind Subscription from Landowner) | H19: =(J19*E45)+K19 -> 62809600 | I19: =H19/$H$30 -> 0.28454102 | J19: 0.7 | BH19: مؤشرات الإيرادات والربحية | Revenue & Profitability Indicators | BL19: - | BV19: إجمالي رصف | BX19: =SUM(BX10:BX17) -> 0 | BY19: - | BZ19: =SUM(BZ10:BZ17) -> 7233969.4 | CA19: =SUM(CA10:CA17) -> 7233969.4 | CB19: -
B20: إجمالي التكاليف التشغيلية (Total Operating Expenses) | C20: =-SUM(E209) -> 6529315.6 | G20: إجمالي الملكية (Total Equity) | H20: =SUM(H15:H19) -> 108409600 | I20: =H20/$H$30 -> 0.49111885 | AE20: توزيع تكاليف مكونات البيع على الخارطة | BH20: متوسط سعر بيع الأمتار البيعية (Average Selling Price per Sellable m²) | BI20: =SUM(C180,C183:C184)/J55 -> 29166.897 | BL20: - | BV20: مستثمرين رصف | BX20: 0 | BY20: 0.7 | BZ20: =BX20*BW7*BY20 -> 0 | CA20: =BZ20+BX20 -> 0 | CB20: -
B21: صافي الدخل (Net Income) | C21: =C13-(C19+C20) -> 85913221 | G21: التمويل البنكي - (Bank Financing) | AE21: المكون | AF21: توزيع تكاليف الأرض | AG21: تكاليف البناء | AH21: نسبة تزيع تكاليف اللاند سكيب | AI21: توزيع تكاليف اللاندسكيب | AJ21: توزيع تكاليف البوديم و القبو | AK21: توزيع تكاليف الحفر والمسح و الاختبار | AL21: توزيع تكاليف المساحات الحركية والخدمية | AM21: نسب التكاليف السابقة من التكاليف الموجودة بالجدول | AN21: نسب التكاليف السابقة من التكاليف الكلية | AO21: نسبة بيع المكون على الخارطة من الإجمالي | AP21: توزيع التكاليف الأخرى | AQ21: توزيع تكاليف أخرى إضافية | AR21: توزيع تكاليف التمويل | AS21: توزيع تكاليف الصندوق | AT21: تكاليف بيع الخارطة | AU21: إجمالي تكاليف كل مكون | AV21: توزيع التكلفة على الأمتار البيعية | AW21: نسبة تكاليف كل مكون من إجمالي المشروع | AX21: إجمالي إيراد كل مكون | AY21: صافي العائد لكل م² بيعي | AZ21: صافي دخل كل مكون | BA21: العائد النسبي للمكون | BB21: هامش الربح من إجمالي الإرادات | BC21: نسبة صافي دخل كل مكون من إجمالي صافي دخل المشروع | BD21: نسبة صافي دخل كل مكون | BH21: متوسط قيمة و نسبة الربح لكل م² (Average Profit Value and % per m²) | BI21: =BI20-BI7 -> 6916.6566 | BJ21: =BI21/BI7 -> 0.31085761 | BL21: - | BV21: الاجمالي | BX21: =SUM(BX19:BX20) -> 0 | BY21: - | BZ21: =SUM(BZ19:BZ20) -> 7233969.4 | CA21: =BZ21+BX21 -> 7233969.4 | CB21: -
B22: أهــــــــــــــــــم مؤشــــــــرات الدراســــــــــة | G22: إجمالي التمويل البنكي (Total Bank Financing) | H22: =E185 -> 54352006 | I22: =H22/$H$30 -> 0.2462263 | AE22: سكني (بيع على الخارطة) | AF22: =((F57/$J$55)*$I$45)*AO22 -> 0 | AG22: =J57*AO22 -> 0 | AH22: 0.15 | AI22: =($J$69*AH22)*AO22 -> 0 | AJ22: =((K57/$L$72)*($J$70+$J$71))*AO22 -> 0 | AK22: =((K57/$L$72)*$C$83)*AO22 -> 0 | AL22: =(((D57-F57)/$I$55)*$J$67)*AO22 -> 0 | AN22: =SUM(AF22:AG22,AI22:AL22)/$AN$32 -> 0 | AO22: =S125 -> 0 | AP22: =(AN22*SUM($C$82,$C$84:$C$86,$C$92:$C$93,$C$97))+(SUM($D$89:$D$91)*G57*AO22) -> 0 | AR22: لا يــــنــطــبــق | AS22: =AN22*$C$103 -> 0 | AT22: لا يــــنــطــبــق | AV22: =IFERROR((AU22)/T125, "0") -> 0 | AX22: =AC125 -> 0 | AY22: =IFERROR(AZ22/T125, "0.00") -> 0.00 | BA22: =IFERROR(BD22/AW22, "0.00") -> 0.00 | BB22: =IFERROR(AZ22/AX22, "0.00%") -> 0.00% | BD22: =IFERROR(AZ22/(AU22), "0.00%") -> 0.00% | BE22: سكني | BH22: العائد على المتر البيعي (شامل عوائد الإيجار) (Total Return per Saleable m² including Rental Income) | BI22: =C21/F72 -> 8659.9138 | BJ22: =BI22/BI7 -> 0.3892054 | BL22: -
B23: مدة المشروع المتوقعة - سنوي (Estimated Project Duration - Years) | C23: =B118 -> 5 | AE23: فلل (بيع على الخارطة) | AF23: =((F58/$J$55)*$I$45)*AO23 -> 30922095 | AG23: =J58*AO23 -> 13226400 | AH23: 0 | AI23: =($J$69*AH23)*AO23 -> 0 | AJ23: =((K58/$L$72)*($J$70+$J$71))*AO23 -> 0 | AK23: =((K58/$L$72)*$C$83)*AO23 -> 0 | AL23: =(((D58-F58)/$I$55)*$J$67)*AO23 -> 0 | AN23: =SUM(AF23:AL23)/$AN$32 -> 0.21655125 | AO23: =S126 -> 1 | AP23: =(AN23*SUM($C$82,$C$84:$C$86,$C$92:$C$93,$C$97))+(SUM($D$89:$D$91)*G58*AO23) -> 2249493 | AR23: لا يــــنــطــبــق | AS23: =AN23*$C$103 -> 4832266.8 | AT23: لا يــــنــطــبــق | AV23: =IFERROR((AU23-AT23)/T126, "0") -> 0 | AX23: =AC126 -> 46486957 | AY23: =IFERROR(AZ23/T126, "0.00") -> 0 | BA23: =IFERROR(BD23/AW23, "0.00") -> 0.00 | BB23: =IFERROR(AZ23/AX23, "0.00%") -> 0 | BD23: =IFERROR(AZ23/(AU23), "0.00%") -> 0.00% | BE23: فلل | BH23: نسبة صافي الربح من الإيرادات (Net Profit as % of Revenues) | BI23: =C21/C13 -> 0.27432311 | BL23: مثالي إن كان بين 20% إلى 35% (أقل من 15% يُعد ضعيف، وأكثر من 40% نادر وممتاز)
B24: معدل العائد الداخلي (IRR) | C24: =C219 -> 0.13308131 | G24: تمويل تشغيلي خارج هيكل رأس المال - (Off-Capital-Structure Operational Financing) | AE24: تاون هاوس (بيع على الخارطة) | AF24: =((F59/$J$55)*$I$45)*AO24 -> 0 | AG24: =J59*AO24 -> 0 | AH24: 0 | AI24: =($J$69*AH24)*AO24 -> 0 | AJ24: =((K59/$L$72)*($J$70+$J$71))*AO24 -> 0 | AK24: =((K59/$L$72)*$C$83)*AO24 -> 0 | AL24: =(((D59-F59)/$I$55)*$J$67)*AO24 -> 0 | AN24: =SUM(AF24:AL24)/$AN$32 -> 0 | AO24: =S127 -> 0.00% | AP24: =(AN24*SUM($C$82,$C$84:$C$86,$C$92:$C$93,$C$97))+(SUM($D$89:$D$91)*G59*AO24) -> 0 | AR24: لا يــــنــطــبــق | AS24: =AN24*$C$103 -> 0 | AT24: لا يــــنــطــبــق | AV24: =IFERROR((AU24-AT24)/T127, "0") -> 0 | AX24: =AC127 -> 0 | AY24: =IFERROR(AZ24/T127, "0.00") -> 0.00 | BA24: =IFERROR(BD24/AW24, "0.00") -> 0.00 | BB24: =IFERROR(AZ24/AX24, "0.00%") -> 0.00% | BD24: =IFERROR(AZ24/(AU24), "0.00%") -> 0.00% | BE24: تاون هاوس | BH24: نقطة التعادل - عدد الأمتار البيعية اللازمة لتغطية التكاليف (Sellable Area Required for Cost Recovery) | BI24: =C19/BI20 -> 7568.1706 | BJ24: =BI24/F72 -> 0.76285936 | BL24: -
G25: البيع على الخارطة (Off-Plan Sales) | H25: =K25*J25 -> 46486957 | I25: =H25/$H$30 -> 0.21059593 | J25: =AC135 -> 46486957 | K25: 1 | L25: =-H31/J25 -> 0 | AE25: أدوار (بيع على الخارطة) | AF25: =((F60/$J$55)*$I$45)*AO25 -> 0 | AG25: =J60*AO25 -> 0 | AH25: 0 | AI25: =($J$69*AH25)*AO25 -> 0 | AJ25: =((K60/$L$72)*($J$70+$J$71))*AO25 -> 0 | AK25: =((K60/$L$72)*$C$83)*AO25 -> 0 | AL25: =(((D60-F60)/$I$55)*$J$67)*AO25 -> 0 | AN25: =SUM(AF25:AL25)/$AN$32 -> 0 | AO25: =S128 -> 0.00% | AP25: =(AN25*SUM($C$82,$C$84:$C$86,$C$92:$C$93,$C$97))+(SUM($D$89:$D$91)*G60*AO25) -> 0 | AR25: لا يــــنــطــبــق | AS25: =AN25*$C$103 -> 0 | AT25: لا يــــنــطــبــق | AV25: =IFERROR((AU25-AT25)/T128, "0") -> 0 | AX25: =AC128 -> 0 | AY25: =IFERROR(AZ25/T128, "0.00") -> 0.00 | BA25: =IFERROR(BD25/AW25, "0.00") -> 0.00 | BB25: =IFERROR(AZ25/AX25, "0.00%") -> 0.00% | BD25: =IFERROR(AZ25/(AU25), "0.00%") -> 0.00% | BE25: أدوار | BH25: مؤشرات التمويل والمخاطر | Financing & Risk Indicators | BJ25: 0 | BL25: -
B26: العائد على الإستثمار (ROI) | C26: =C21/C19 -> 0.3892054 | G26: مصادر أخرى (Other Sources) | H26: =K26*J26 -> 11491488 | I26: =H26/$H$30 -> 0.052058917 | J26: =SUM(J135,M153,AC153) -> 17294496 | K26: 0.66445927 | L26: =-H31/J26 -> 0 | AE26: استديوهات (بيع على الخارطة) | AF26: =((F61/$J$55)*$I$45)*AO26 -> 0 | AG26: =J61*AO26 -> 0 | AH26: 0 | AI26: =($J$69*AH26)*AO26 -> 0 | AJ26: =((K61/$L$72)*($J$70+$J$71))*AO26 -> 0 | AK26: =((K61/$L$72)*$C$83)*AO26 -> 0 | AL26: =(((D61-F61)/$I$55)*$J$67)*AO26 -> 0 | AN26: =SUM(AF26:AL26)/$AN$32 -> 0 | AO26: =S129 -> 0.00% | AP26: =(AN26*SUM($C$82,$C$84:$C$86,$C$92:$C$93,$C$97))+(SUM($D$89:$D$91)*G61*AO26) -> 0 | AR26: لا يــــنــطــبــق | AS26: =AN26*$C$103 -> 0 | AT26: لا يــــنــطــبــق | AV26: =IFERROR((AU26-AT26)/T129, "0") -> 0 | AX26: =AC129 -> 0 | AY26: =IFERROR(AZ26/T129, "0.00") -> 0.00 | BA26: =IFERROR(BD26/AW26, "0.00") -> 0.00 | BB26: =IFERROR(AZ26/AX26, "0.00%") -> 0.00% | BD26: =IFERROR(AZ26/(AU26), "0.00%") -> 0.00% | BE26: أستوديوهات | BH26: القيم والنسب الخاصة بالتمويل البنكي (Bank Financing Limits & Conditions) | BI26: =(BJ28+BJ27)-H22 -> 53513192 | BJ26: =H22/(BJ28+BJ27) -> 0.50388825 | BL26: -
G27: إجمالي التمويل التشغيلي (Total Operational Financing) | H27: =SUM(H25:H26) -> 57978444 | I27: =H27/$H$30 -> 0.26265485 | AE27: مكتبي (بيع على الخارطة) | AF27: =((F62/$J$55)*$I$45)*AO27 -> 0 | AG27: =J62*AO27 -> 0 | AH27: 0.35 | AI27: =($J$69*AH27)*AO27 -> 0 | AJ27: =((K62/$L$72)*($J$70+$J$71))*AO27 -> 0 | AK27: =((K62/$L$72)*$C$83)*AO27 -> 0 | AL27: =(((D62-F62)/$I$55)*$J$67)*AO27 -> 0 | AN27: =SUM(AF27:AL27)/$AN$32 -> 1.7167728e-09 | AO27: =S130 -> 0.00% | AP27: =(AN27*SUM($C$82,$C$84:$C$86,$C$92:$C$93,$C$97))+(SUM($D$89:$D$91)*G62*AO27) -> 0.015914983 | AR27: لا يــــنــطــبــق | AS27: =AN27*$C$103 -> 0.038309197 | AT27: لا يــــنــطــبــق | AV27: =IFERROR((AU27-AT27)/T130, "0") -> 0 | AX27: =AC130 -> 0 | AY27: =IFERROR(AZ27/T130, "0.00") -> 0.00 | BA27: =IFERROR(BD27/AW27, "0.00") -> 0.00 | BB27: =IFERROR(AZ27/AX27, "0.00%") -> 0.00% | BD27: =IFERROR(AZ27/(AU27), "0.00%") -> 0.00% | BE27: مكتبي | BI27: 0.6 | BJ27: =(I45*80%)*BI27 -> 44086956 | BL27: -
B28: العائد على الملكية (ROE) | C28: =(C21/H20) -> 0.7924872 | G28: الإجمالي - (Total) | AE28: تجاري (بيع على الخارطة) | AF28: =((F63/$J$55)*$I$45)*AO28 -> 0 | AG28: =J63*AO28 -> 0 | AH28: 0.35 | AI28: =($J$69*AH28)*AO28 -> 0 | AJ28: =((K63/$L$72)*($J$70+$J$71))*AO28 -> 0 | AK28: =((K63/$L$72)*$C$83)*AO28 -> 0 | AL28: =(((D63-F63)/$I$55)*$J$67)*AO28 -> 0 | AN28: =SUM(AF28:AL28)/$AN$32 -> 1.7167728e-09 | AO28: =S131 -> 0.00% | AP28: =(AN28*SUM($C$82,$C$84:$C$86,$C$92:$C$93,$C$97))+(SUM($D$89:$D$91)*G63*AO28) -> 0.015914983 | AR28: لا يــــنــطــبــق | AS28: =AN28*$C$103 -> 0.038309197 | AT28: لا يــــنــطــبــق | AV28: =IFERROR((AU28-AT28)/T131, "0") -> 0 | AX28: =AC131 -> 0 | AY28: =IFERROR(AZ28/T131, "0.00") -> 0.00 | BA28: =IFERROR(BD28/AW28, "0.00") -> 0.00 | BB28: =IFERROR(AZ28/AX28, "0.00%") -> 0.00% | BD28: =IFERROR(AZ28/(AU28), "0.00%") -> 0.00% | BE28: تجاري | BI28: 0.7 | BJ28: =SUM(J72,C82:C86,C89:C91,C92:C92,C97)*BI28 -> 63778242 | BL28: -
G29: إجمالي مصادر التمويل (Total Financing Sources) | H29: =H20+H22+H27 -> 2.2074005e+08 | I29: =IF(ABS(SUM(1)-SUM(Study!I20,Study!I22,Study!I27))<=0.001,"TRUE",SUM(1)-SUM(Study!I20,Study!I22,Study!I27)) -> TRUE | AE29: فندقي (بيع على الخارطة) | AF29: =((F64/$J$55)*$I$45)*AO29 -> 0 | AG29: =J64*AO29 -> 0 | AH29: 0.15 | AI29: =($J$69*AH29)*AO29 -> 0 | AJ29: =((K64/$L$72)*($J$70+$J$71))*AO29 -> 0 | AK29: =((K64/$L$72)*$C$83)*AO29 -> 0 | AL29: =(((D64-F64)/$I$55)*$J$67)*AO29 -> 0 | AN29: =SUM(AF29:AL29)/$AN$32 -> 7.3575979e-10 | AO29: =S132 -> 0 | AP29: =(AN29*SUM($C$82,$C$84:$C$86,$C$92:$C$93,$C$97))+((SUM($D$90:$D$91)*G64*AO29)+(D89*G64/2*AO29)) -> 0.006820707 | AR29: لا يــــنــطــبــق | AS29: =AN29*$C$103 -> 0.016418227 | AT29: لا يــــنــطــبــق | AV29: =IFERROR((AU29-AT29)/T132, "0") -> 0 | AX29: =AC132 -> 0 | AY29: =IFERROR(AZ29/T132, "0.00") -> 0.00 | BA29: =IFERROR(BD29/AW29, "0.00") -> 0.00 | BB29: =IFERROR(AZ29/AX29, "0.00%") -> 0.00% | BD29: =IFERROR(AZ29/(AU29), "0.00%") -> 0.00% | BE29: فندقي | BI29: =BJ29/D115 -> 0.039885606 | BJ29: =BI30/H22 -> 0.13140091 | BL29: -
B30: العائد على الملكية السنوي (ROE Annually) | C30: =C28/C23 -> 0.15849744 | G30: إجمالي التكاليف الرأسمالية للمشروع (Total Capital Expenditures) | H30: =C19 -> 2.2074005e+08 | AE30: صحي (بيع على الخارطة) | AF30: =((F65/$J$55)*$I$45)*AO30 -> 0 | AG30: =J65*AO30 -> 0 | AH30: =AH12 -> 0 | AI30: =($J$69*AH30)*AO30 -> 0 | AJ30: =((K65/$L$72)*($J$70+$J$71))*AO30 -> 0 | AK30: =((K65/$L$72)*$C$83)*AO30 -> 0 | AL30: =(((D65-F65)/$I$55)*$J$67)*AO30 -> 0 | AN30: =SUM(AF30:AL30)/$AN$32 -> 0 | AO30: =S133 -> 0.00% | AP30: =(AN30*SUM($C$82,$C$84:$C$86,$C$92:$C$93,$C$97))+(SUM($D$89:$D$91)*G65*AO30) -> 0 | AR30: لا يــــنــطــبــق | AS30: =AN30*$C$103 -> 0 | AT30: لا يــــنــطــبــق | AV30: =IFERROR((AU30-AT30)/T133, "0") -> 0 | AX30: =AC133 -> 0 | AY30: =IFERROR(AZ30/T133, "0.00") -> 0.00 | BA30: =IFERROR(BD30/AW30, "0.00") -> 0.00 | BB30: =IFERROR(AZ30/AX30, "0.00%") -> 0.00% | BD30: =IFERROR(AZ30/(AU30), "0.00%") -> 0.00% | BE30: صحي | BI30: =C18 -> 7141903.3 | BL30: -
G31: الفرق (Difference) | H31: =H29-H30 -> 0 | AE31: شاليهات (بيع على الخارطة) | AF31: =((F66/$J$55)*$I$45)*AO31 -> 0 | AG31: =J66*AO31 -> 0 | AH31: =AH13 -> 0 | AI31: =($J$69*AH31)*AO31 -> 0 | AJ31: =((K66/$L$72)*($J$70+$J$71))*AO31 -> 0 | AK31: =((K66/$L$72)*$C$83)*AO31 -> 0 | AL31: =(((D66-F66)/$I$55)*$J$67)*AO31 -> 0 | AN31: =SUM(AF31:AL31)/$AN$32 -> 0 | AO31: =S134 -> 0.00% | AP31: =(AN31*SUM($C$82,$C$84:$C$86,$C$92:$C$93,$C$97))+(SUM($D$89:$D$91)*G66*AO31) -> 0 | AR31: لا يــــنــطــبــق | AS31: =AN31*$C$103 -> 0 | AT31: لا يــــنــطــبــق | AV31: =IFERROR((AU31-AT31)/T134, "0") -> 0 | AX31: =AC134 -> 0 | AY31: =IFERROR(AZ31/T134, "0.00") -> 0.00 | BA31: =IFERROR(BD31/AW31, "0.00") -> 0.00 | BB31: =IFERROR(AZ31/AX31, "0.00%") -> 0.00% | BD31: =IFERROR(AZ31/(AU31), "0.00%") -> 0.00% | BE31: شاليهات | BH31: نسبة المخاطرة التمويلية (Loan to Value Ratio - LTV) | BI31: =H22/(SUM(C180:C184)) -> 0.17354734 | BJ31: =1-BI31 -> 0.82645266 | BL31: بين (50%) و (70%) = طبيعي أقل من (50%) = منخفض (اعتماد كبير على تمويل ذاتي) أكثر من (70%) = مرتفع (مخاطرة عالية على البنك)
AE32: الإجمالي | AF32: =SUM(AF22:AF31) -> 30922095 | AG32: =SUM(AG22:AG31) -> 13226400 | AH32: =SUM(AH22:AH31) -> 1 | AI32: =SUM(AI22:AI31) -> 0 | AJ32: =SUM(AJ22:AJ31) -> 0 | AK32: =SUM(AK22:AK31) -> 0 | AL32: =SUM(AL22:AL31) -> 0 | AM32: =SUM(AF32:AG32,AI32:AL32) -> 44148495 | AN32: =SUM(AF4:AG13,AI4:AL13,AF22:AG31,AI22:AL31) -> 2.0387089e+08 | AO32: - | AR32: - | AS32: =SUM(AS22:AS31) -> 4832266.9 | AT32: =SUM(AT22:AT31) -> 0 | AV32: =IFERROR(AU32/T135, "0") -> 0 | AX32: =SUM(AX22:AX31) -> 46486957 | AY32: =AZ32/T135 -> 0 | AZ32: =SUMIF(AZ22:AZ31, "<>#DIV/0!") -> 0 | BA32: - | BB32: =IFERROR(AZ32/AX32, "0.00%") -> 0 | BD32: =IFERROR(AZ32/AU32, "0.00%") -> 0.00% | BH32: مؤشر المخاطر التمويلية (Leverage Risk Indicator) | BI32: =H22/H20 -> 0.50135787 | BL32: يفضل أن يكون ≤ 1.5 (كلما ارتفع زادت المخاطرة)
AF33: =I45-AF14=AF32 -> FALSE | AG33: =SUM(J57:J67)-AG14=AG32 -> TRUE | AH33: =SUM(AH22:AH31)=AH32 -> TRUE | AI33: =ABS((J69 - AI14) - AI32) <= 0.9 -> TRUE | AJ33: =(J70+J71)-AJ14=AJ32 -> TRUE | AK33: =ABS((C83 - AK14) - AK32) <= 0.9 -> TRUE | AL33: =J67-AL14=AL32 -> TRUE | AM33: =SUM(AF22:AG31,AI22:AL31)=AM32 -> TRUE | AN33: =SUM(AI22:AL31,AF22:AG31,AF4:AG13,AI4:AL13)=AN32 -> TRUE | AO33: =SUM(AO4:AO13,AO22:AO31)=1000% -> TRUE | AR33: =AR32=AR32 -> TRUE | AS33: =ABS((C103 - AS14) - AS32) <= 0.9 -> TRUE | AT33: =AT32=AT32 -> TRUE | AV33: =AV32=AV32 -> TRUE | AX33: =AX32=AC135 -> TRUE | AY33: =AY32=AY32 -> TRUE | AZ33: =AZ32=AZ32 -> TRUE | BA33: =BA32=BA32 -> TRUE | BB33: =BB32=BB32 -> TRUE | BD33: =BD32=BD32 -> TRUE | BH33: قيمة ونسبة تمويل مبيعات الخارطة من تكاليف المشروع خلال فترة البيع (Value and % of Off-Plan Sales Financing for Project Costs During Sales Period) | BI33: =AX22 -> 0 | BJ33: =C180/-(SUM(G188:S212)) -> 0.49384503 | BL33: من 30% إلى 60% من التكاليف أثناء البيع يعتبر جيد جداً
BH34: هامش الأمان (Safety Margin) | BI34: =(C13-C19)/C13 -> 0.29517138 | BL34: المستهدف الجيد ≥ 20% (بمعنى أن القيمة السوقية أعلى بـ 20% من التكلفة)
BH35: مؤشرات الأرض والزمن | Land & Time Indicators | BJ35: 0 | BL35: -
BH36: تكلفة متر الأرض شاملة الضريبة والسعي (Land Cost per m² - Including Tax and Commission) | BI36: =I45/C45 -> 11179.141 | BJ36: =D45 -> 10921.13 | BL36: -
BH37: سعر متر الأرض عند البيع (Land Price per m² at Sale) | BI37: =((I45/C19)*C13)/C45 -> 15860.793 | BL37: -
B38: تفاصيل الأرض | Land Details | AE38: إجمالي توزيع التكاليف على جميع المكونات | BH38: قيمة ارتفاع سعر متر الأرض عند البيع (Land Price Appreciation Value) | BI38: =BI37-BI36 -> 4681.6523 | BL38: -
B39: رقم الأرض (Land Number) | C39: المساحة الأرض (Land Area) | D39: التكلفة للمتر (Cost per SQM) | E39: تكلفة الأرض قبل الضرائب (Land Cost Before Taxes) | F39: ضريبة التصرفات العقارية (RETT) | G39: السعي (Commission) | H39: ضريبة السعي (Commission tax) | I39: إجمالي تكلفة الأرض بعد الضرائب (Total Land Cost After Taxes) | K39: معامل البناء (FAR) | L39: إجمالي مسطحات البناء فوق الأرض (Above Grade Gross Building Area) | AE39: المكون | AF39: توزيع تكاليف الأرض | AG39: تكاليف البناء | AH39: نسبة تزيع تكاليف اللاند سكيب | AI39: توزيع تكاليف اللاندسكيب | AJ39: توزيع تكاليف البوديم و القبو | AK39: توزيع تكاليف الحفر والمسح و الاختبار | AL39: توزيع تكاليف المساحات الحركية والخدمية | AM39: نسب التكاليف السابقة من التكاليف الموجودة بالجدول | AN39: نسب التكاليف السابقة من التكاليف الكلية | AO39: نسب المكونات من البيع المباشر أو المخارجة من الإجمالي | AP39: توزيع التكاليف الأخرى | AQ39: توزيع تكاليف أخرى إضافية | AR39: توزيع تكاليف التمويل | AS39: توزيع تكاليف الصندوق | AT39: توزيع التكاليف التشغيلية | AU39: إجمالي تكاليف كل مكون | AV39: توزيع التكلفة على المساحات الصافية القابلة للبيع | AW39: نسبة تكاليف كل مكون من إجمالي المشروع | AX39: إجمالي إيراد كل مكون | AY39: صافي العائد لكل م² بيعي | AZ39: صافي دخل كل مكون | BA39: العائد النسبي للمكون | BB39: هامش الربح من إجمالي الإرادات | BC39: نسبة صافي دخل كل مكون من إجمالي صافي دخل المشروع | BD39: نسبة صافي دخل كل مكون | BH39: نسبة ارتفاع سعر متر الأرض (Land Price Appreciation Rate) | BI39: =BI38/BI36 -> 0.41878461 | BL39: من 10% إلى 40% خلال 3–5 سنوات يعتبر جيد
B40: 1 | C40: 3000 | D40: 16000 | E40: =D40*C40 -> 48000000 | F40: =(E40*$F$46)*$F$47 -> 720000 | G40: =(E40*$G$46)*$G$47 -> 360000 | H40: =(G40*$H$46)*$H$47 -> 54000 | I40: =SUM(E40:H40) -> 49134000 | K40: 2.05 | L40: =K40*C40 -> 6150 | M40: فندقي | AE40: سكني | AF40: =SUM(AF4,AF22) -> 15362564 | AG40: =SUM(AG4,AG22) -> 7800408 | AH40: =AH4 -> 0 | AI40: =SUM(AI4,AI22) -> 0 | AJ40: =SUM(AJ4,AJ22) -> 0 | AK40: =SUM(AK4,AK22) -> 0 | AL40: =SUM(AL4,AL22) -> 0 | AM40: - | AN40: =SUM(AN4,AN22) -> 0.11361589 | AO40: =SUM(AO4,AO22) -> 1 | AP40: =SUM(AP4,AP22) -> 749188.5 | AQ40: =SUM(AQ4,AQ22) -> 887297.5 | AR40: =SUM(AR4,AR22) -> 1035720.2 | AS40: =SUM(AS4,AS22) -> 2535299.6 | AT40: =SUM(AT4,AT22) -> 123565.55 | AU40: =SUM(AU4,AU22) -> 28494043 | AV40: =IFERROR((AU40-AT40)/F57, "0") -> 9413.5425 | AW40: =SUM(AW4,AW22) -> 0.12852438 | AX40: =SUM(AX22,AX4) -> 31818130 | AY40: =IFERROR(AZ40/F57, "0.00") -> 1102.9575 | AZ40: =SUM(AZ22,AZ4) -> 3324086.8 | BA40: =IFERROR(BD40/AW40, "0.00") -> 0.91163333 | BB40: =IFERROR(AZ40/AX40, "0.00%") -> 0.10447147 | BC40: =AZ40/$C$21 -> 0.038691214 | BD40: =IFERROR(AZ40/(AU40-AT40), "0.00%") -> 0.11716711 | BE40: سكني | BH40: كفاءة المساحة البيعية من المساحات المبنية فوق الأرض (Saleable Efficiency Ratio of Above-Ground Built-Up Area) | BI40: =F72/I55 -> 0.63159036 | BL40: المستهدف المثالي ≥ 70% (الممتاز يتجاوز 75–80%)
B41: 2 | C41: 1876 | D41: 8000 | E41: =D41*C41 -> 15008000 | F41: =(E41*$F$46)*$F$47 -> 225120 | G41: =(E41*$G$46)*$G$47 -> 112560 | H41: =(G41*$H$46)*$H$47 -> 16884 | I41: =SUM(E41:H41) -> 15362564 | K41: 1.89 | L41: =K41*C41 -> 3545.64 | M41: شقق | AE41: فلل | AF41: =SUM(AF5,AF23) -> 58273355 | AG41: =SUM(AG5,AG23) -> 13226400 | AH41: =AH5 -> 0 | AI41: =SUM(AI5,AI23) -> 0 | AJ41: =SUM(AJ5,AJ23) -> 0 | AK41: =SUM(AK5,AK23) -> 0 | AL41: =SUM(AL5,AL23) -> 0 | AM41: - | AN41: =SUM(AN5,AN23) -> 0.35071096 | AO41: =SUM(AO5,AO23) -> 1 | AP41: =SUM(AP5,AP23) -> 2705685.7 | AQ41: =SUM(AQ5,AQ23) -> 888528.77 | AR41: =SUM(AR5,AR23) -> 1222997.3 | AS41: =SUM(AS5,AS23) -> 7825994.9 | AT41: =SUM(AT5,AT23) -> 0 | AU41: =SUM(AU5,AU23) -> 32912707 | AV41: =IFERROR((AU41-AT41)/F58, "0") -> 9854.1038 | AW41: =SUM(AW5,AW23) -> 0.14910165 | AX41: =SUM(AX23,AX5) -> 46486957 | AY41: =IFERROR(AZ41/F58, "0.00") -> -9854.1038 | AZ41: =SUM(AZ23,AZ5) -> -32912707 | BA41: =IFERROR(BD41/AW41, "0.00") -> -6.7068337 | BB41: =IFERROR(AZ41/AX41, "0.00%") -> -0.70799874 | BC41: =AZ41/$C$21 -> -0.38309246 | BD41: =IFERROR(AZ41/(AU41-AT41), "0.00%") -> -1 | BE41: فلل | BH41: مدة البيع - بالسنوات (غير شامل بيع الخارطة) (Sales Duration – Years) | BI41: =COUNTIFS(F183:AC183,">500")/4 -> 0 | BJ41: =BI41/B118 -> 0 | BL41: الطبيعي من 1 إلى 1.5 سنوات
B42: 3 | C42: 3340 | D42: 8000 | E42: =D42*C42 -> 26720000 | F42: =(E42*$F$46)*$F$47 -> 400800 | G42: =(E42*$G$46)*$G$47 -> 200400 | H42: =(G42*$H$46)*$H$47 -> 30060 | I42: =SUM(E42:H42) -> 27351260 | K42: 1.8 | L42: =K42*C42 -> 6012 | M42: فلل | AE42: تاون هاوس | AF42: =SUM(AF6,AF24) -> 0 | AG42: =SUM(AG6,AG24) -> 0 | AH42: =AH6 -> 0 | AI42: =SUM(AI6,AI24) -> 0 | AJ42: =SUM(AJ6,AJ24) -> 0 | AK42: =SUM(AK6,AK24) -> 0 | AL42: =SUM(AL6,AL24) -> 0 | AM42: - | AN42: =SUM(AN6,AN24) -> 0 | AO42: =SUM(AO6,AO24) -> 1 | AP42: =SUM(AP6,AP24) -> 0 | AQ42: =SUM(AQ6,AQ24) -> 0 | AR42: =SUM(AR6,AR24) -> 0 | AS42: =SUM(AS6,AS24) -> 0 | AT42: =SUM(AT6,AT24) -> 0 | AU42: =SUM(AU6,AU24) -> 0 | AV42: =IFERROR((AU42-AT42)/F59, "0") -> 0 | AW42: =SUM(AW6,AW24) -> 0 | AX42: =SUM(AX24,AX6) -> 0 | AY42: =IFERROR(AZ42/F59, "0.00") -> 0.00 | AZ42: =SUM(AZ24,AZ6) -> 0 | BA42: =IFERROR(BD42/AW42, "0.00") -> 0.00 | BB42: =IFERROR(AZ42/AX42, "0.00%") -> 0.00% | BC42: =AZ42/$C$21 -> 0 | BD42: =IFERROR(AZ42/(AU42-AT42), "0.00%") -> 0.00% | BE42: تاون هاوس | BH42: توزيع الأرباح | Profit Distribution | BL42: -
B43: 4 | E43: =D43*C43 -> 0 | F43: =(E43*$F$46)*$F$47 -> 0 | G43: =(E43*$G$46)*$G$47 -> 0 | H43: =(G43*$H$46)*$H$47 -> 0 | I43: =SUM(E43:H43) -> 0 | L43: =K43*C43 -> 0 | AE43: أدوار | AF43: =SUM(AF7,AF25) -> 0 | AG43: =SUM(AG7,AG25) -> 0 | AH43: =AH7 -> 0 | AI43: =SUM(AI7,AI25) -> 0 | AJ43: =SUM(AJ7,AJ25) -> 0 | AK43: =SUM(AK7,AK25) -> 0 | AL43: =SUM(AL7,AL25) -> 0 | AM43: - | AN43: =SUM(AN7,AN25) -> 0 | AO43: =SUM(AO7,AO25) -> 1 | AP43: =SUM(AP7,AP25) -> 0 | AQ43: =SUM(AQ7,AQ25) -> 0 | AR43: =SUM(AR7,AR25) -> 0 | AS43: =SUM(AS7,AS25) -> 0 | AT43: =SUM(AT7,AT25) -> 0 | AU43: =SUM(AU7,AU25) -> 0 | AV43: =IFERROR((AU43-AT43)/F60, "0") -> 0 | AW43: =SUM(AW7,AW25) -> 0 | AX43: =SUM(AX25,AX7) -> 0 | AY43: =IFERROR(AZ43/F60, "0.00") -> 0.00 | AZ43: =SUM(AZ25,AZ7) -> 0 | BA43: =IFERROR(BD43/AW43, "0.00") -> 0.00 | BB43: =IFERROR(AZ43/AX43, "0.00%") -> 0.00% | BC43: =AZ43/$C$21 -> 0 | BD43: =IFERROR(AZ43/(AU43-AT43), "0.00%") -> 0.00% | BE43: أدوار | BH43: المستفيد (Beneficiaries) | BI43: نسبة المساهمة من إجمالي الملكية (Equity Ownership Percentage) | BJ43: صافي الربح للمستفيدين (Net Profit for Beneficiaries) | BL43: رأس المال + الأرباح
B44: 5 | E44: =D44*C44 -> 0 | F44: =(E44*$F$46)*$F$47 -> 0 | G44: =(E44*$G$46)*$G$47 -> 0 | H44: =(G44*$H$46)*$H$47 -> 0 | I44: =SUM(E44:H44) -> 0 | L44: =K44*C44 -> 0 | AE44: استديوهات | AF44: =SUM(AF8,AF26) -> 0 | AG44: =SUM(AG8,AG26) -> 0 | AH44: =AH8 -> 0 | AI44: =SUM(AI8,AI26) -> 0 | AJ44: =SUM(AJ8,AJ26) -> 0 | AK44: =SUM(AK8,AK26) -> 0 | AL44: =SUM(AL8,AL26) -> 0 | AM44: - | AN44: =SUM(AN8,AN26) -> 0 | AO44: =SUM(AO8,AO26) -> 1 | AP44: =SUM(AP8,AP26) -> 0 | AQ44: =SUM(AQ8,AQ26) -> 0 | AR44: =SUM(AR8,AR26) -> 0 | AS44: =SUM(AS8,AS26) -> 0 | AT44: =SUM(AT8,AT26) -> 0 | AU44: =SUM(AU8,AU26) -> 0 | AV44: =IFERROR((AU44-AT44)/F61, "0") -> 0 | AW44: =SUM(AW8,AW26) -> 0 | AX44: =SUM(AX26,AX8) -> 0 | AY44: =IFERROR(AZ44/F61, "0.00") -> 0.00 | AZ44: =SUM(AZ26,AZ8) -> 0 | BA44: =IFERROR(BD44/AW44, "0.00") -> 0.00 | BB44: =IFERROR(AZ44/AX44, "0.00%") -> 0.00% | BC44: =AZ44/$C$21 -> 0 | BD44: =IFERROR(AZ44/(AU44-AT44), "0.00%") -> 0.00% | BE44: أستوديوهات | BH44: الاشتراكات النقدية (Cash Subscription) | BI44: =H15/$H$20 -> 0.3182375 | BJ44: =BI44*$C$21 -> 27340809 | BL44: =BJ44+H15 -> 61840809
B45: الإجمالي (Total) | C45: =SUM(C40:C44) -> 8216 | D45: =E45/C45 -> 10921.13 | E45: =SUM(E40:E44) -> 89728000 | F45: =SUM(F40:F44) -> 1345920 | G45: =SUM(G40:G44) -> 672960 | H45: =SUM(H40:H44) -> 100944 | I45: =SUM(I40:I44) -> 91847824 | K45: =L45/C45 -> 1.9118354 | L45: =SUM(L40:L44) -> 15707.64 | AE45: مكتبي | AF45: =SUM(AF9,AF27) -> 0 | AG45: =SUM(AG9,AG27) -> 0 | AH45: =AH9 -> 0 | AI45: =SUM(AI9,AI27) -> 0 | AJ45: =SUM(AJ9,AJ27) -> 0 | AK45: =SUM(AK9,AK27) -> 0 | AL45: =SUM(AL9,AL27) -> 0 | AM45: - | AN45: =SUM(AN9,AN27) -> 1.7167728e-09 | AO45: =SUM(AO9,AO27) -> 1 | AP45: =SUM(AP9,AP27) -> 0.015914983 | AQ45: =SUM(AQ9,AQ27) -> 0 | AR45: =SUM(AR9,AR27) -> 0 | AS45: =SUM(AS9,AS27) -> 0.038309197 | AT45: =SUM(AT9,AT27) -> 0 | AU45: =SUM(AU9,AU27) -> 0 | AV45: =IFERROR((AU45-AT45)/F62, "0") -> 0 | AW45: =SUM(AW9,AW27) -> 0 | AX45: =SUM(AX27,AX9) -> 0 | AY45: =IFERROR(AZ45/F62, "0.00") -> 0.00 | AZ45: =SUM(AZ27,AZ9) -> 0 | BA45: =IFERROR(BD45/AW45, "0.00") -> 0.00 | BB45: =IFERROR(AZ45/AX45, "0.00%") -> 0.00% | BC45: =AZ45/$C$21 -> 0 | BD45: =IFERROR(AZ45/(AU45-AT45), "0.00%") -> 0.00% | BE45: مكتبي | BH45: الاشتراك من مدير الصندوق (fund manager's Subscription) | BI45: =H16/$H$20 -> 0 | BJ45: =BI45*$C$21 -> 0 | BL45: =BJ45+H16 -> 0
F46: 0.05 | G46: 0.025 | H46: 0.15 | AE46: تجاري | AF46: =SUM(AF10,AF28) -> 0 | AG46: =SUM(AG10,AG28) -> 0 | AH46: =AH10 -> 0 | AI46: =SUM(AI10,AI28) -> 0 | AJ46: =SUM(AJ10,AJ28) -> 0 | AK46: =SUM(AK10,AK28) -> 0 | AL46: =SUM(AL10,AL28) -> 0 | AM46: - | AN46: =SUM(AN10,AN28) -> 1.7167728e-09 | AO46: =SUM(AO10,AO28) -> 1 | AP46: =SUM(AP10,AP28) -> 0.015914983 | AQ46: =SUM(AQ10,AQ28) -> 0 | AR46: =SUM(AR10,AR28) -> 0 | AS46: =SUM(AS10,AS28) -> 0.038309197 | AT46: =SUM(AT10,AT28) -> 0 | AU46: =SUM(AU10,AU28) -> 0 | AV46: =IFERROR((AU46-AT46)/F63, "0") -> 0 | AW46: =SUM(AW10,AW28) -> 0 | AX46: =SUM(AX28,AX10) -> 0 | AY46: =IFERROR(AZ46/F63, "0.00") -> 0.00 | AZ46: =SUM(AZ28,AZ10) -> 0 | BA46: =IFERROR(BD46/AW46, "0.00") -> 0.00 | BB46: =IFERROR(AZ46/AX46, "0.00%") -> 0.00% | BC46: =AZ46/$C$21 -> 0 | BD46: =IFERROR(AZ46/(AU46-AT46), "0.00%") -> 0.00% | BE46: تجاري | BH46: الأشتراك النقدي من المطور (Cash Subscription from Developer) | BI46: =H17/$H$20 -> 0.10238946 | BJ46: =BI46*$C$21 -> 8796608 | BL46: =BJ46+H17 -> 19896608
F47: 0.3 | G47: =F47 -> 0.3 | H47: 1 | AE47: فندقي | AF47: =SUM(AF11,AF29) -> 49134000 | AG47: =SUM(AG11,AG29) -> 36900000 | AH47: =AH11 -> 1 | AI47: =SUM(AI11,AI29) -> 6162000 | AJ47: =SUM(AJ11,AJ29) -> 14176800 | AK47: =SUM(AK11,AK29) -> 2835360 | AL47: =SUM(AL11,AL29) -> 0 | AM47: - | AN47: =SUM(AN11,AN29) -> 0.53567315 | AO47: =SUM(AO11,AO29) -> 1 | AP47: =SUM(AP11,AP29) -> 4250586.9 | AQ47: =SUM(AQ11,AQ29) -> 10291049 | AR47: =SUM(AR11,AR29) -> 4883185.8 | AS47: =SUM(AS11,AS29) -> 11953363 | AT47: =SUM(AT11,AT29) -> 6405750 | AU47: =SUM(AU11,AU29) -> 1.4699209e+08 | AV47: =IFERROR((AU47-AT47)/F64, "0") -> 39413.049 | AW47: =SUM(AW11,AW29) -> 0.63688644 | AX47: =SUM(AX29,AX11) -> 2.348775e+08 | AY47: =IFERROR(AZ47/F64, "0.00") -> 24638.465 | AZ47: =SUM(AZ29,AZ11) -> 87885405 | BA47: =IFERROR(BD47/AW47, "0.00") -> 0.98154817 | BB47: =IFERROR(AZ47/AX47, "0.00%") -> 0.3741755 | BC47: =AZ47/$C$21 -> 1.0229555 | BD47: =IFERROR(AZ47/(AU47-AT47), "0.00%") -> 0.62513472 | BE47: فندقي | BH47: الأشتراك العيني من المطور (In-Kind Subscription from Developer) | BI47: =H18/$H$20 -> 0 | BJ47: =BI47*$C$21 -> 0 | BL47: =BJ47+H18 -> 0
AE48: صحي | AF48: =SUM(AF12,AF30) -> 0 | AG48: =SUM(AG12,AG30) -> 0 | AH48: =AH12 -> 0 | AI48: =SUM(AI12,AI30) -> 0 | AJ48: =SUM(AJ12,AJ30) -> 0 | AK48: =SUM(AK12,AK30) -> 0 | AL48: =SUM(AL12,AL30) -> 0 | AM48: - | AN48: =SUM(AN12,AN30) -> 0 | AO48: =SUM(AO12,AO30) -> 1 | AP48: =SUM(AP12,AP30) -> 0 | AQ48: =SUM(AQ12,AQ30) -> 0 | AR48: =SUM(AR12,AR30) -> 0 | AS48: =SUM(AS12,AS30) -> 0 | AT48: =SUM(AT12,AT30) -> 0 | AU48: =SUM(AU12,AU30) -> 0 | AV48: =IFERROR((AU48-AT48)/F65, "0") -> 0 | AW48: =SUM(AW12,AW30) -> 0 | AX48: =SUM(AX30,AX12) -> 0 | AY48: =IFERROR(AZ48/F65, "0.00") -> 0.00 | AZ48: =SUM(AZ30,AZ12) -> 0 | BA48: =IFERROR(BD48/AW48, "0.00") -> 0.00 | BB48: =IFERROR(AZ48/AX48, "0.00%") -> 0.00% | BC48: =AZ48/$C$21 -> 0 | BD48: =IFERROR(AZ48/(AU48-AT48), "0.00%") -> 0.00% | BE48: صحي | BH48: الإشتراك العيني من مالك الأرض (In-Kind Subscription from Landowner) | BI48: =H19/$H$20 -> 0.57937304 | BJ48: =BI48*$C$21 -> 49775804 | BL48: =BJ48+H19 -> 1.125854e+08
AE49: شاليهات | AF49: =SUM(AF13,AF31) -> 0 | AG49: =SUM(AG13,AG31) -> 0 | AH49: =AH13 -> 0 | AI49: =SUM(AI13,AI31) -> 0 | AJ49: =SUM(AJ13,AJ31) -> 0 | AK49: =SUM(AK13,AK31) -> 0 | AL49: =SUM(AL13,AL31) -> 0 | AM49: - | AN49: =SUM(AN13,AN31) -> 0 | AO49: =SUM(AO13,AO31) -> 1 | AP49: =SUM(AP13,AP31) -> 0 | AQ49: =SUM(AQ13,AQ31) -> 0 | AR49: =SUM(AR13,AR31) -> 0 | AS49: =SUM(AS13,AS31) -> 0 | AT49: =SUM(AT13,AT31) -> 0 | AU49: =SUM(AU13,AU31) -> 0 | AV49: =IFERROR((AU49-AT49)/F66, "0") -> 0 | AW49: =SUM(AW13,AW31) -> 0 | AX49: =SUM(AX31,AX13) -> 0 | AY49: =IFERROR(AZ49/F66, "0.00") -> 0.00 | AZ49: =SUM(AZ31,AZ13) -> 0 | BA49: =IFERROR(BD49/AW49, "0.00") -> 0.00 | BB49: =IFERROR(AZ49/AX49, "0.00%") -> 0.00% | BC49: =AZ49/$C$21 -> 0 | BD49: =IFERROR(AZ49/(AU49-AT49), "0.00%") -> 0.00% | BE49: شاليهات | BH49: - | BI49: =SUM(BI44:BI48)=100% -> TRUE | BJ49: =SUM(BJ44:BJ48)=C21 -> TRUE | BL49: =SUM(BL44:BL48) -> 1.9432282e+08
AE50: الإجمالي | AF50: =SUM(AF40:AF49) -> 1.2276992e+08 | AG50: =SUM(AG40:AG49) -> 57926808 | AH50: =SUM(AH40:AH49) -> 1 | AI50: =SUM(AI40:AI49) -> 6162000 | AJ50: =SUM(AJ40:AJ49) -> 14176800 | AK50: =SUM(AK40:AK49) -> 2835360 | AL50: =SUM(AL40:AL49) -> 0 | AM50: - | AN50: =SUM(AN40:AN49) -> 1 | AO50: - | AP50: =SUM(AP40:AQ49) -> 19772337 | AR50: =SUM(AR40:AR49) -> 7141903.3 | AS50: =SUM(AS40:AS49) -> 22314657 | AT50: =SUM(AT40:AT49) -> 6529315.6 | AU50: =SUM(AU40:AU49) -> 2.0839884e+08 | AV50: =AU50/F72 -> 21006.267 | AW50: =SUM(AW40:AW49) -> 0.91451247 | AX50: =SUM(AX40:AX49) -> 3.1318259e+08 | AY50: =AZ50/F72 -> 5876.2217 | AZ50: =SUM(AZ40:AZ49) -> 58296785 | BA50: - | BB50: =IFERROR(AZ50/AX50, "0.00%") -> 0.18614312 | BC50: - | BD50: =IFERROR(AZ50/AU50, "0.00%") -> 0.27973661
AF51: =AF50=I45 -> FALSE | AG51: =AG50=SUM(J57:J67) -> TRUE | AH51: =AH50=100% -> TRUE | AI51: =AI50=J69 -> TRUE | AJ51: =AJ50=SUM(J70:J71) -> TRUE | AK51: =AK50=C83 -> TRUE | AL51: =AL50=J67 -> TRUE | AM51: =AM50=AM50 -> TRUE | AN51: =ABS(AN50 - 1) <= 0.0001 -> TRUE | AO51: =AO50=AO50 -> TRUE | AP51: =ABS(AP50 - (C98 - C83)) <= 0.9 -> FALSE | AR51: =AR50=C115 -> TRUE | AS51: =ABS(AS50 - C103) <= 0.9 -> TRUE | AT51: =AT50=C20 -> TRUE | AU51: =ABS(AU50 - (C19 + C20)) <= 0.9 -> FALSE | AV51: =AV50=AV50 -> TRUE | AW51: =ABS(AW50 - 1) <= 0.0001 -> FALSE | AX51: =AX50=C13 -> TRUE | AY51: =AY50=AY50 -> TRUE | AZ51: =ABS(AZ50 - C21) <= 0.9 -> FALSE | BA51: =BA50=BA50 -> TRUE | BB51: =BB50=BB50 -> TRUE | BC51: =BC50=BC50 -> TRUE | BD51: =BD50=BD50 -> TRUE
B52: Construction Details and Costs | تفاصيل البناء و تكاليفة
B54: طول الأرض على الشارع (Land Frontage) | C54: عمق الأرض (Land Depth) | D54: عدد أدوار المشروع (Total Project Floors) | E54: عدد عماير المشروع (Total Project Building) | F54: معامل البناء (FAR) | G54: إجمالي المساحة التطويرية (Total Development Area) | H54: إجمالي المساحة المبنية (Gross Built-Up Area) | I54: إجمالي المساحة البنائية فوق مستوى الأرض (Above Grade Gross Building Area) | J54: إجمالي المساحات القابلة للبيع (Net Sellable Area) | K54: المواقف (Parking) | L54: معيار المواقف (Parking Standards)
B55: 0 | C55: 0 | D55: 0 | E55: 0 | F55: =K45 -> 1.9118354 | G55: =SUM(D57:D71) -> 31799.64 | H55: =SUM(D57:D67,D70:D71) -> 23583.64 | I55: =SUM(D57:D67) -> 15707.64 | J55: =F72 -> 9920.794
B56: المكون (Component) | C56: نسبة المكون من المساحة البنائية (GBA-%) | D56: إجمالي المساحة البنائية للمكون (GBA) | E56: نسبة المساحات الصافية القابلة للبيع (NSA-%) | F56: المساحات الصافية القابلة للبيع (NSA) | G56: عدد الوحدات (Number of Units) | H56: مساحة الوحدة (Unit Area) | I56: تكلفة متر البناء (Construction cost Per m²) | J56: اجمالي التكاليف (Total Costs) | K56: =B55/L56 -> 0 | L56: 3.5
B57: سكني (Apartments) | C57: 0.2257271 | D57: =$L$45*C57 -> 3545.64 | E57: 0.85 | F57: =E57*D57 -> 3013.794 | G57: 12 | H57: =IFERROR(F57/G57, "0.00") -> 251.1495 | I57: 2200 | J57: =I57*D57 -> 7800408 | K57: =L57*G57 -> 12 | L57: 1
B58: فلل* (Villas) | C58: 0.38274368 | D58: =$L$45*C58 -> 6012 | E58: 1 | F58: =C73*$C$42 -> 3340 | G58: 11 | H58: =IFERROR(F58/G58, "0.00") -> 303.63636 | I58: 2200 | J58: =I58*D58 -> 13226400 | K58: =L58*G58 -> 0 | L58: 0
B59: تاون هاوس* (Townhouse) | C59: 0 | D59: =$L$45*C59 -> 0 | E59: 0 | F59: =C74*$C$45 -> 0 | H59: =IFERROR(F59/G59, "0.00") -> 0.00 | J59: =I59*D59 -> 0 | K59: =L59*G59 -> 0 | L59: 0
B60: أدوار (Floors) | C60: 0 | D60: =$L$45*C60 -> 0 | E60: 0 | F60: =E60*D60 -> 0 | H60: =IFERROR(F60/G60, "0.00") -> 0.00 | J60: =I60*D60 -> 0 | K60: =L60*G60 -> 0 | L60: 0
B61: أستوديوهات (Studios) | C61: 0 | D61: =$L$45*C61 -> 0 | E61: 0 | F61: =E61*D61 -> 0 | H61: =IFERROR(F61/G61, "0.00") -> 0.00 | J61: =I61*D61 -> 0 | K61: =L61*G61 -> 0 | L61: 1
B62: مكتبي (Office) | C62: 0 | D62: =$L$45*C62 -> 0 | E62: 0 | F62: =E62*D62 -> 0 | H62: =IFERROR(F62/G62, "0.00") -> 0.00 | J62: =I62*D62 -> 0 | K62: =F62/L62 -> 0 | L62: 25
B63: تجاري (Retail) | C63: 0 | D63: =$L$45*C63 -> 0 | E63: 0 | F63: =E63*D63 -> 0 | H63: =IFERROR(F63/G63, "0.00") -> 0.00 | J63: =I63*D63 -> 0 | K63: =F63/L63 -> 0 | L63: 45
B64: فندقي (Hotel) | C64: 0.39152922 | D64: =$L$45*C64 -> 6150 | E64: 0.58 | F64: =E64*D64 -> 3567 | G64: 100 | H64: =IFERROR(F64/G64, "0.00") -> 35.67 | I64: 6000 | J64: =I64*D64 -> 36900000 | K64: =G64/L64 -> 50 | L64: 2
B65: صحي (health) | C65: 0 | D65: =$L$45*C65 -> 0 | F65: =E65*D65 -> 0 | H65: =IFERROR(F65/G65, "0.00") -> 0.00 | J65: =I65*D65 -> 0 | K65: =F65/L65 -> 0 | L65: 35
B66: شاليهات (Chalets) | D66: =$L$45*C66 -> 0 | F66: =E66*D66 -> 0 | H66: =IFERROR(F66/G66, "0.00") -> 0.00 | J66: =I66*D66 -> 0 | K66: 0 | L66: لا يــــنــطــبــق
B67: المساحات الحركية والخدمية (Circulation & Service Areas) | C67: =100%-SUM(C57:C66) -> 0 | D67: =$L$45*C67 -> 0 | E67: لا يــــنــطــبــق | F67: لا يــــنــطــبــق | G67: لا يــــنــطــبــق | H67: لا يــــنــطــبــق | J67: =I67*D67 -> 0 | K67: لا يــــنــطــبــق | L67: لا يــــنــطــبــق
B68: - | C68: - | D68: - | E68: - | F68: - | G68: - | H68: - | I68: - | J68: - | K68: - | L68: -
B69: لاند سكيب* (Landscape) | C69: 1 | D69: =$C$45*C69 -> 8216 | E69: لا يــــنــطــبــق | F69: لا يــــنــطــبــق | G69: لا يــــنــطــبــق | H69: لا يــــنــطــبــق | I69: 750 | J69: =I69*D69 -> 6162000 | K69: لا يــــنــطــبــق | L69: لا يــــنــطــبــق
B70: البدروم* (Basement) | C70: 0.95861733 | D70: {=SUM(C40:C42*C70)} -> 7876 | E70: لا يــــنــطــبــق | F70: لا يــــنــطــبــق | G70: لا يــــنــطــبــق | H70: لا يــــنــطــبــق | I70: 1800 | J70: =I70*D70 -> 14176800 | K70: =D70/L70 -> 175.02222 | L70: 45
B71: بوديوم* (Podium) | C71: 0 | D71: =$C$45*C71 -> 0 | E71: لا يــــنــطــبــق | F71: لا يــــنــطــبــق | G71: لا يــــنــطــبــق | H71: لا يــــنــطــبــق | I71: 0 | J71: =I71*D71 -> 0 | K71: =D71/L71 -> 0 | L71: 45
B72: الإجمالي (Total) | C72: =SUM(C57:C67) -> 1 | D72: =SUM(D57:D71) -> 31799.64 | E72: =SUMPRODUCT(E57:E66, C57:C66) / SUM(C57:C66) -> 0.80169866 | F72: =SUMIF(F57:F66, "<>#DIV/0!") -> 9920.794 | G72: =SUMIF(G57:G71, "<>#DIV/0!") -> 123 | H72: =IFERROR(F72/G72, "0.00") -> 80.656862 | I72: =J72/D72 -> 2461.2105 | J72: =SUM(J57:J71) -> 78265608 | K72: إجمالي المواقف المطلوبة (Total Required Parking Spaces) | L72: =SUMIF(K57:K65, "<>#DIV/0!") -> 62
B73: من مساحة الأرض* (Based on Land Area) | C73: 1 | K73: إجمالي المواقف المتوفرة (Total Available Parking Spaces) | L73: =SUM(K56,K70:K71) -> 175.02222
C74: 0 | K74: فارق المواقف (Parking Deficit) | L74: =L73-L72 -> 113.02222
B80: Other Cost | التكاليف الأخرى | E80: نسبة البند من الإجمالي (Percentage)
B81: البند (Item) | C81: القيمة (Value) | D81: المعيار (Standard) | E81: %
B82: التسوير (Fencing) | C82: =D82*C45 -> 534040 | D82: 65 | E82: =C82/$C$98 -> 0.025226195
B83: الحفر والمسح والاختبار (Excavation, surveying, and testing) | C83: =(D70)*4.5*D83 -> 2835360 | D83: 80 | E83: =C83/$C$98 -> 0.13393256
B84: التأمين (Insurance) | C84: =D84*C106 -> 1330515.3 | D84: 0.017 | E84: =C84/$C$98 -> 0.062848923
B85: الرخصة (License) | C85: =D85*I55 -> 62830.56 | D85: 4 | E85: =C85/$C$98 -> 0.0029678974
B86: التصميم (Design) | C86: =D86*C106 -> 3913280.4 | D86: 0.05 | E86: =C86/$C$98 -> 0.18484977
B87: أثاث الوحدات الفندقية (Hotel Furniture Units) | C87: =D87*D64 -> 6150000 | D87: 1000 | E87: =C87/$C$98 -> 0.29050464
B88: أثاث الوحدات (Furniture Units) | C88: =D88*SUM(H57,H61,H62) -> 0 | D88: 0 | E88: =C88/$C$98 -> 0
B89: رسوم الكهرباء (Electricity fees) | C89: =D89*SUM(G57:G63,G65:G66)+(D89*(G64/2)) -> 912500 | D89: 12500 | E89: =C89/$C$98 -> 0.04310333
B90: رسوم الماء وصرف الصحي (Water and sewer fees) | C90: =D90*$G$72 -> 984000 | D90: 8000 | E90: =C90/$C$98 -> 0.046480742
B91: الفرز (Sorting) | C91: =D91*(C125+C126) -> 18000 | D91: 1500 | E91: =C91/$C$98 -> 0.00085025747
B92: الصيانة و التشغيل (Maintenance and Operation) | C92: =D92*(G57+G58) -> 299000 | D92: 13000 | E92: =C92/$C$98 -> 0.014123721
B93: الاحتياطي (Contingency) | C93: =D93*C106 -> 1173984.1 | D93: 0.015 | E93: =C93/$C$98 -> 0.055454932
B94: تسويق المبيعات (Sales Marketing) | C94: =D94*(J135+M153) -> 46954.911 | D94: 0.02 | E94: =C94/$C$98 -> 0.0022179869
B95: تسويق التأجير (Leasing Marketing) | C95: =D95*(SUM(C181:C182)) -> 952952.44 | D95: 0.04 | E95: =C95/$C$98 -> 0.045014163
B96: تسويق البيع على الخارطة (Off-Plan Sales Marketing) | C96: =D96*Y135 -> 0 | D96: 0 | E96: =C96/$C$98 -> 0
B97: الإشراف الهندسي (Engineering Supervision) | C97: =D97*C106 -> 1956640.2 | D97: 0.025 | E97: =C97/$C$98 -> 0.092424886
B98: إجمالي التكاليف الأخرى (Total Other Cost) | C98: =SUMIF(C82:C97, "<>#DIV/0!") -> 21170058
B99: تفاصيل تكاليف الصندوق | Fund Cost Details
B100: تكاليف المطور (Developer costs) | C100: =D100*C106 -> 11739841 | D100: 0.15
B101: رسوم الصندوق (Fund fees) | C101: =-E327 -> 9214816
B102: التكاليف الأخرى للصندوق (Other costs) | C102: =-E211 -> 1360000
B103: الإجمالي (Total) | C103: =SUM(C100,C101,C102) -> 22314657
B104: ملخص تكاليف المشروع | Project Costs
B105: اجمالي تكلفة الأرض (Total Land Cost) | C105: =I45 -> 91847824
B106: اجمالي تكلفة البناء (Total construction cost) | C106: =J72 -> 78265608
B107: إجمالي التكاليف الأخرى (Total other costs) | C107: =C98 -> 21170058
...

Sheet Summary
B1: رصف للاستثمار | RASF Investment
B6: Values shown are SAR except where stated | القيم المعروضة هي بالريال سعودي باستثناء ما هو مذكور | E6: NSA.m² | Net Sellable Area|TDA.m² | Total Development Area|LA.m² | Total Land Area NSA.m² | المساحات الصافية القابلة للبيع |TDA.m² | إجمالي المساحة التطويرية | LA.m² | مساحة الأرض الإجمالية
C10: Summary | ملخص
I12: (Area) - المساحة | J12: (SR/m²) - ر.س/م² | K12: الإجمالي - (Total)
C13: تكلفة شراء الأرض - باستثناء الضرائب والعمولات (Land purchase cost - except taxes & commissions) | I13: =Study!C45 -> 8216 | J13: =Study!D45 -> 10921.13 | K13: =I13*J13 -> 89728000
C14: التكلفة الإجمالية للمشروع (Total project cost) | I14: =Study!G55 -> 31799.64 | J14: =K14/I14 -> 6941.5896 | K14: =Study!C19 -> 2.2074005e+08
C15: إجمالي الإيرادات (Total Revenue) | I15: =Study!J55 -> 9920.794 | J15: =K15/I15 -> 31568.299 | K15: =Study!C13 -> 3.1318259e+08
C17: نمو قيمة الأرض للمتر - Land Value Uplift per SQM | I17: وقت الشراء | J17: وقت البيع | K17: الفارق
I19: =K95/I13 -> 5980.2824 | J19: =((K95/K14)*K15)/I13 -> 8484.7326 | K19: =J19-I19 -> 2504.4502
C21: المؤشرات المالية | Financial Indicators | H21: معدل العائد الداخلي IRR | I21: العائد على الإستثمار ROI | J21: العائد على الملكية ROE | K21: العائد على الملكية سنوياَ ROE Annualy
H24: =Study!C24 -> 0.13308131 | I24: =Study!C26 -> 0.3892054 | J24: =Study!C28 -> 0.7924872 | K24: =Study!C30 -> 0.15849744
C27: التفاصيل الفنية و المالية لجميع للمكونات | Technical and Financial Details For All Components | D27: عدد الوحدات (Number of Units) | E27: مساحة الوحدة (One Unit Area) | H27: إجمالي تكاليف كل مكون (Total cost per component) | I27: صافي العائد لكل م² بيعي (Net return per NSA.m²) | J27: صافي دخل كل مكون (Net Income per Component) | K27: نسبة عائد كل مكون (Return % per Component)
C29: سكني (Apartments) | D29: =Study!G57 -> 12 | E29: =Study!H57 -> 251.1495 | H29: =Study!AU40 -> 28494043 | I29: =Study!AY4 -> 1102.9575 | J29: =Study!AZ4 -> 3324086.8 | K29: =Study!BD4 -> 0.11716711
C30: فلل (Villas) | D30: =Study!G58 -> 11 | E30: =Study!H58 -> 303.63636 | H30: =Study!AU41 -> 32912707 | I30: =Study!AY5 -> -9854.1038 | J30: =Study!AZ5 -> -32912707 | K30: =Study!BD5 -> -1
C31: تاون هاوس (Townhouse) | D31: =Study!G59 -> 0 | E31: =Study!H59 -> 0.00 | H31: =Study!AU42 -> 0 | I31: =Study!AY6 -> 0.00 | J31: =Study!AZ6 -> 0 | K31: =Study!BD6 -> 0.00%
C32: أدوار (Floors) | D32: =Study!G60 -> 0 | E32: =Study!H60 -> 0.00 | H32: =Study!AU43 -> 0 | I32: =Study!AY7 -> 0.00 | J32: =Study!AZ7 -> 0 | K32: =Study!BD7 -> 0.00%
C33: أستوديوهات (Studios) | D33: =Study!G61 -> 0 | E33: =Study!H61 -> 0.00 | H33: =Study!AU44 -> 0 | I33: =Study!AY8 -> 0.00 | J33: =Study!AZ8 -> 0 | K33: =Study!BD8 -> 0.00%
C34: مكتبي (Office) | D34: =Study!G62 -> 0 | E34: =Study!H62 -> 0.00 | H34: =Study!AU45 -> 0 | I34: =Study!AY9 -> 0.00 | J34: =Study!AZ9 -> 0 | K34: =Study!BD9 -> 0.00%
C35: تجاري (Retail) | D35: =Study!G63 -> 0 | E35: =Study!H63 -> 0.00 | H35: =Study!AU46 -> 0 | I35: =Study!AY10 -> 0.00 | J35: =Study!AZ10 -> 0 | K35: =Study!BD10 -> 0.00%
C36: فندقي (Hotel) | D36: =Study!G64 -> 100 | E36: =Study!H64 -> 35.67 | H36: =Study!AU47 -> 1.4699209e+08 | I36: =Study!AY11 -> 24638.465 | J36: =Study!AZ11 -> 87885405 | K36: =Study!BD11 -> 0.62513472
C37: صحي (health) | D37: =Study!G65 -> 0 | E37: =Study!H65 -> 0.00 | H37: =Study!AU48 -> 0 | I37: =Study!AY12 -> 0.00 | J37: =Study!AZ12 -> 0 | K37: =Study!BD12 -> 0.00%
C38: شاليهات (Chalets) | D38: =Study!G66 -> 0 | E38: =Study!H66 -> 0.00 | H38: =Study!AU49 -> 0 | I38: =Study!AY13 -> 0.00 | J38: =Study!AZ13 -> 0 | K38: =Study!BD13 -> 0.00%
E40: 1 | F40: 2 | G40: 3 | H40: 4 | I40: 5 | J40: 6 | K40: =Study!B118 -> 5
C42: رخصة البناء و التصميم (Design & License) | D42: =Study!C340 -> 46388 | E42: =IF(ABS(SUM(OFFSET(Study!$F$196,0,(COLUMN()-COLUMN($E$42))*4,2,4)))<0.01,"",SUM(OFFSET(Study!$F$196,0,(COLUMN()-COLUMN($E$42))*4,2,4))) -> -2608853.6 | F42: =IF(ABS(SUM(OFFSET(Study!$F$196,0,(COLUMN()-COLUMN($E$42))*4,2,4)))<0.01,"",SUM(OFFSET(Study!$F$196,0,(COLUMN()-COLUMN($E$42))*4,2,4))) -> -1367257.4 | G42: =IF(ABS(SUM(OFFSET(Study!$F$196,0,(COLUMN()-COLUMN($E$42))*4,2,4)))<0.01,"",SUM(OFFSET(Study!$F$196,0,(COLUMN()-COLUMN($E$42))*4,2,4))) | H42: =IF(ABS(SUM(OFFSET(Study!$F$196,0,(COLUMN()-COLUMN($E$42))*4,2,4)))<0.01,"",SUM(OFFSET(Study!$F$196,0,(COLUMN()-COLUMN($E$42))*4,2,4))) | I42: =IF(ABS(SUM(OFFSET(Study!$F$196,0,(COLUMN()-COLUMN($E$42))*4,2,4)))<0.01,"",SUM(OFFSET(Study!$F$196,0,(COLUMN()-COLUMN($E$42))*4,2,4))) | J42: =IF(ABS(SUM(OFFSET(Study!$F$196,0,(COLUMN()-COLUMN($E$42))*4,2,4)))<0.01,"",SUM(OFFSET(Study!$F$196,0,(COLUMN()-COLUMN($E$42))*4,2,4))) | K42: =Study!H340 -> 46934
C43: -------------------------------------------
C44: فوائد التمويل (Interest) | D44: =Study!C341 -> 47027 | E44: =IF(ABS(SUM(OFFSET(Study!$F$188,0,(COLUMN()-COLUMN($E$44))*4,2,4)))<0.0001,"",SUM(OFFSET(Study!$F$188,0,(COLUMN()-COLUMN($E$44))*4,2,4))) -> -271760.03 | F44: =IF(ABS(SUM(OFFSET(Study!$F$188,0,(COLUMN()-COLUMN($E$44))*4,2,4)))<0.0001,"",SUM(OFFSET(Study!$F$188,0,(COLUMN()-COLUMN($E$44))*4,2,4))) -> -46574.109 | G44: =IF(ABS(SUM(OFFSET(Study!$F$188,0,(COLUMN()-COLUMN($E$44))*4,2,4)))<0.0001,"",SUM(OFFSET(Study!$F$188,0,(COLUMN()-COLUMN($E$44))*4,2,4))) -> -551296.44 | H44: =IF(ABS(SUM(OFFSET(Study!$F$188,0,(COLUMN()-COLUMN($E$44))*4,2,4)))<0.0001,"",SUM(OFFSET(Study!$F$188,0,(COLUMN()-COLUMN($E$44))*4,2,4))) -> -2381771.4 | I44: =IF(ABS(SUM(OFFSET(Study!$F$188,0,(COLUMN()-COLUMN($E$44))*4,2,4)))<0.0001,"",SUM(OFFSET(Study!$F$188,0,(COLUMN()-COLUMN($E$44))*4,2,4))) -> -3890501.3 | J44: =IF(ABS(SUM(OFFSET(Study!$F$188,0,(COLUMN()-COLUMN($E$44))*4,2,4)))<0.0001,"",SUM(OFFSET(Study!$F$188,0,(COLUMN()-COLUMN($E$44))*4,2,4))) | K44: =Study!H341 -> 48213
C45: -------------------------------------------
C46: تكاليف البناء (Construction Costs) | D46: =Study!C342 -> 46844 | E46: =IF(ABS(SUM(OFFSET(Study!$F$192,0,(COLUMN()-COLUMN($E$46))*4,1,4)))<0.0001,"",SUM(OFFSET(Study!$F$192,0,(COLUMN()-COLUMN($E$46))*4,1,4))) | F46: =IF(ABS(SUM(OFFSET(Study!$F$192,0,(COLUMN()-COLUMN($E$46))*4,1,4)))<0.0001,"",SUM(OFFSET(Study!$F$192,0,(COLUMN()-COLUMN($E$46))*4,1,4))) -> -16435778 | G46: =IF(ABS(SUM(OFFSET(Study!$F$192,0,(COLUMN()-COLUMN($E$46))*4,1,4)))<0.0001,"",SUM(OFFSET(Study!$F$192,0,(COLUMN()-COLUMN($E$46))*4,1,4))) -> -39915460 | H46: =IF(ABS(SUM(OFFSET(Study!$F$192,0,(COLUMN()-COLUMN($E$46))*4,1,4)))<0.0001,"",SUM(OFFSET(Study!$F$192,0,(COLUMN()-COLUMN($E$46))*4,1,4))) -> -21914370 | I46: =IF(ABS(SUM(OFFSET(Study!$F$192,0,(COLUMN()-COLUMN($E$46))*4,1,4)))<0.0001,"",SUM(OFFSET(Study!$F$192,0,(COLUMN()-COLUMN($E$46))*4,1,4))) | J46: =IF(ABS(SUM(OFFSET(Study!$F$192,0,(COLUMN()-COLUMN($E$46))*4,1,4)))<0.0001,"",SUM(OFFSET(Study!$F$192,0,(COLUMN()-COLUMN($E$46))*4,1,4))) | K46: =Study!H342 -> 47848
C47: -------------------------------------------
C48: الخدمات (Infrastructure services) | D48: =Study!C343 -> 47757 | E48: =IF(ABS(SUM(OFFSET(Study!$F$200,0,(COLUMN()-COLUMN($E$48))*4,3,4)))<0.0001,"",SUM(OFFSET(Study!$F$200,0,(COLUMN()-COLUMN($E$48))*4,3,4))) | F48: =IF(ABS(SUM(OFFSET(Study!$F$200,0,(COLUMN()-COLUMN($E$48))*4,3,4)))<0.0001,"",SUM(OFFSET(Study!$F$200,0,(COLUMN()-COLUMN($E$48))*4,3,4))) | G48: =IF(ABS(SUM(OFFSET(Study!$F$200,0,(COLUMN()-COLUMN($E$48))*4,3,4)))<0.0001,"",SUM(OFFSET(Study!$F$200,0,(COLUMN()-COLUMN($E$48))*4,3,4))) | H48: =IF(ABS(SUM(OFFSET(Study!$F$200,0,(COLUMN()-COLUMN($E$48))*4,3,4)))<0.0001,"",SUM(OFFSET(Study!$F$200,0,(COLUMN()-COLUMN($E$48))*4,3,4))) -> -1914500 | I48: =IF(ABS(SUM(OFFSET(Study!$F$200,0,(COLUMN()-COLUMN($E$48))*4,3,4)))<0.0001,"",SUM(OFFSET(Study!$F$200,0,(COLUMN()-COLUMN($E$48))*4,3,4))) | J48: =IF(ABS(SUM(OFFSET(Study!$F$200,0,(COLUMN()-COLUMN($E$48))*4,3,4)))<0.0001,"",SUM(OFFSET(Study!$F$200,0,(COLUMN()-COLUMN($E$48))*4,3,4))) | K48: =Study!H343 -> 47848
C49: -------------------------------------------
C50: الأثاث (furniture) | D50: =Study!C344 -> 47849 | E50: =IF(ABS(SUM(OFFSET(Study!$F$198,0,(COLUMN()-COLUMN($E$50))*4,2,4)))<0.0001,"",SUM(OFFSET(Study!$F$198,0,(COLUMN()-COLUMN($E$50))*4,2,4))) | F50: =IF(ABS(SUM(OFFSET(Study!$F$198,0,(COLUMN()-COLUMN($E$50))*4,2,4)))<0.0001,"",SUM(OFFSET(Study!$F$198,0,(COLUMN()-COLUMN($E$50))*4,2,4))) | G50: =IF(ABS(SUM(OFFSET(Study!$F$198,0,(COLUMN()-COLUMN($E$50))*4,2,4)))<0.0001,"",SUM(OFFSET(Study!$F$198,0,(COLUMN()-COLUMN($E$50))*4,2,4))) | H50: =IF(ABS(SUM(OFFSET(Study!$F$198,0,(COLUMN()-COLUMN($E$50))*4,2,4)))<0.0001,"",SUM(OFFSET(Study!$F$198,0,(COLUMN()-COLUMN($E$50))*4,2,4))) | I50: =IF(ABS(SUM(OFFSET(Study!$F$198,0,(COLUMN()-COLUMN($E$50))*4,2,4)))<0.0001,"",SUM(OFFSET(Study!$F$198,0,(COLUMN()-COLUMN($E$50))*4,2,4))) -> -6150000 | J50: =IF(ABS(SUM(OFFSET(Study!$F$198,0,(COLUMN()-COLUMN($E$50))*4,2,4)))<0.0001,"",SUM(OFFSET(Study!$F$198,0,(COLUMN()-COLUMN($E$50))*4,2,4))) | K50: =Study!H344 -> 48029
C51: -------------------------------------------
C52: البيع على الخارطة (Off-Plan Sale) | D52: =Study!C345 -> 46753 | E52: =IF(ABS(SUM(OFFSET(Study!$F$180,0,(COLUMN()-COLUMN($E$52))*4,1,4)))<0.0001,"",SUM(OFFSET(Study!$F$180,0,(COLUMN()-COLUMN($E$52))*4,1,4))) | F52: =IF(ABS(SUM(OFFSET(Study!$F$180,0,(COLUMN()-COLUMN($E$52))*4,1,4)))<0.0001,"",SUM(OFFSET(Study!$F$180,0,(COLUMN()-COLUMN($E$52))*4,1,4))) -> 14273087 | G52: =IF(ABS(SUM(OFFSET(Study!$F$180,0,(COLUMN()-COLUMN($E$52))*4,1,4)))<0.0001,"",SUM(OFFSET(Study!$F$180,0,(COLUMN()-COLUMN($E$52))*4,1,4))) -> 30956330 | H52: =IF(ABS(SUM(OFFSET(Study!$F$180,0,(COLUMN()-COLUMN($E$52))*4,1,4)))<0.0001,"",SUM(OFFSET(Study!$F$180,0,(COLUMN()-COLUMN($E$52))*4,1,4))) -> 1257540.4 | I52: =IF(ABS(SUM(OFFSET(Study!$F$180,0,(COLUMN()-COLUMN($E$52))*4,1,4)))<0.0001,"",SUM(OFFSET(Study!$F$180,0,(COLUMN()-COLUMN($E$52))*4,1,4))) | J52: =IF(ABS(SUM(OFFSET(Study!$F$180,0,(COLUMN()-COLUMN($E$52))*4,1,4)))<0.0001,"",SUM(OFFSET(Study!$F$180,0,(COLUMN()-COLUMN($E$52))*4,1,4))) | K52: =Study!H345 -> 47848
C53: -------------------------------------------
C54: إيرادات التأجير (Rental Revenue) | D54: =Study!C346 -> 47849 | E54: =IF(ABS(SUM(OFFSET(Study!$F$181,0,(COLUMN()-COLUMN($E$54))*4,2,4)))<0.0001,"",SUM(OFFSET(Study!$F$181,0,(COLUMN()-COLUMN($E$54))*4,2,4))) | F54: =IF(ABS(SUM(OFFSET(Study!$F$181,0,(COLUMN()-COLUMN($E$54))*4,2,4)))<0.0001,"",SUM(OFFSET(Study!$F$181,0,(COLUMN()-COLUMN($E$54))*4,2,4))) | G54: =IF(ABS(SUM(OFFSET(Study!$F$181,0,(COLUMN()-COLUMN($E$54))*4,2,4)))<0.0001,"",SUM(OFFSET(Study!$F$181,0,(COLUMN()-COLUMN($E$54))*4,2,4))) | H54: =IF(ABS(SUM(OFFSET(Study!$F$181,0,(COLUMN()-COLUMN($E$54))*4,2,4)))<0.0001,"",SUM(OFFSET(Study!$F$181,0,(COLUMN()-COLUMN($E$54))*4,2,4))) | I54: =IF(ABS(SUM(OFFSET(Study!$F$181,0,(COLUMN()-COLUMN($E$54))*4,2,4)))<0.0001,"",SUM(OFFSET(Study!$F$181,0,(COLUMN()-COLUMN($E$54))*4,2,4))) -> 23823811 | J54: =IF(ABS(SUM(OFFSET(Study!$F$181,0,(COLUMN()-COLUMN($E$54))*4,2,4)))<0.0001,"",SUM(OFFSET(Study!$F$181,0,(COLUMN()-COLUMN($E$54))*4,2,4))) | K54: =Study!H346 -> 48213
C55: -------------------------------------------
C56: البيع المباشر (Direct Sale) | D56: =Study!C347 | E56: =IF(ABS(SUM(OFFSET(Study!$F$183,0,(COLUMN()-COLUMN($E$56))*4,1,4)))<0.0001,"",SUM(OFFSET(Study!$F$183,0,(COLUMN()-COLUMN($E$56))*4,1,4))) | F56: =IF(ABS(SUM(OFFSET(Study!$F$183,0,(COLUMN()-COLUMN($E$56))*4,1,4)))<0.0001,"",SUM(OFFSET(Study!$F$183,0,(COLUMN()-COLUMN($E$56))*4,1,4))) | G56: =IF(ABS(SUM(OFFSET(Study!$F$183,0,(COLUMN()-COLUMN($E$56))*4,1,4)))<0.0001,"",SUM(OFFSET(Study!$F$183,0,(COLUMN()-COLUMN($E$56))*4,1,4))) | H56: =IF(ABS(SUM(OFFSET(Study!$F$183,0,(COLUMN()-COLUMN($E$56))*4,1,4)))<0.0001,"",SUM(OFFSET(Study!$F$183,0,(COLUMN()-COLUMN($E$56))*4,1,4))) | I56: =IF(ABS(SUM(OFFSET(Study!$F$183,0,(COLUMN()-COLUMN($E$56))*4,1,4)))<0.0001,"",SUM(OFFSET(Study!$F$183,0,(COLUMN()-COLUMN($E$56))*4,1,4))) | J56: =IF(ABS(SUM(OFFSET(Study!$F$183,0,(COLUMN()-COLUMN($E$56))*4,1,4)))<0.0001,"",SUM(OFFSET(Study!$F$183,0,(COLUMN()-COLUMN($E$56))*4,1,4))) | K56: =Study!H347
C57: -------------------------------------------
C58: المخارجة (Buyout) | D58: =Study!C348 -> 48122 | E58: =IF(ABS(SUM(OFFSET(Study!$F$184,0,(COLUMN()-COLUMN($E$58))*4,1,4)))<0.0001,"",SUM(OFFSET(Study!$F$184,0,(COLUMN()-COLUMN($E$58))*4,1,4))) | F58: =IF(ABS(SUM(OFFSET(Study!$F$184,0,(COLUMN()-COLUMN($E$58))*4,1,4)))<0.0001,"",SUM(OFFSET(Study!$F$184,0,(COLUMN()-COLUMN($E$58))*4,1,4))) | G58: =IF(ABS(SUM(OFFSET(Study!$F$184,0,(COLUMN()-COLUMN($E$58))*4,1,4)))<0.0001,"",SUM(OFFSET(Study!$F$184,0,(COLUMN()-COLUMN($E$58))*4,1,4))) | H58: =IF(ABS(SUM(OFFSET(Study!$F$184,0,(COLUMN()-COLUMN($E$58))*4,1,4)))<0.0001,"",SUM(OFFSET(Study!$F$184,0,(COLUMN()-COLUMN($E$58))*4,1,4))) | I58: =IF(ABS(SUM(OFFSET(Study!$F$184,0,(COLUMN()-COLUMN($E$58))*4,1,4)))<0.0001,"",SUM(OFFSET(Study!$F$184,0,(COLUMN()-COLUMN($E$58))*4,1,4))) -> 2.4287182e+08 | J58: =IF(ABS(SUM(OFFSET(Study!$F$184,0,(COLUMN()-COLUMN($E$58))*4,1,4)))<0.0001,"",SUM(OFFSET(Study!$F$184,0,(COLUMN()-COLUMN($E$58))*4,1,4))) | K58: =Study!H348 -> 48213
C59: -------------------------------------------
C60: Capital Structure | هيكل رأس المال | J60: % | K60: SR
C61: ----------------------------------------------------------- | J61: ------------------------------------------- | K61: -------------------------------------------
C62: الاشتراكات النقدية | J62: =K62/$K$71 -> 0.15629244 | K62: =Study!H15 -> 34500000
C63: الاشتراك من مدير الصندوق | J63: =K63/$K$71 -> 0 | K63: =Study!H16 -> 0
C64: الأشتراك النقدي من المطور | J64: =K64/$K$71 -> 0.050285392 | K64: =Study!H17 -> 11100000
C65: الأشتراك العيني من المطور | J65: =K65/$K$71 -> 0 | K65: =Study!H18 -> 0
C66: الإشتراك العيني من مالك الأرض | J66: =K66/$K$71 -> 0.28454102 | K66: =Study!H19 -> 62809600
C67: التمويل البنكي | J67: =K67/$K$71 -> 0.2462263 | K67: =Study!H22 -> 54352006
C68: البيع على الخارطة | J68: =K68/$K$71 -> 0.21059593 | K68: =Study!H25 -> 46486957
C69: مصادر أخرى | J69: =K69/$K$71 -> 0.052058917 | K69: =Study!H26 -> 11491488
C70: ------------------------------------------- | J70: ------------------------------------------- | K70: -------------------------------------------
C71: Total Funding الإجمالي | J71: =SUM(J62:J70) -> 1 | K71: =SUM(K62:K70) -> 2.2074005e+08
S83: مصادر أخرى | T83: =SUM(Summary!K68:K70) -> 57978444 | U83: =T83/Summary!$K$71 -> 0.26265485
S84: التمويل | T84: =Summary!K67 -> 54352006 | U84: =T84/Summary!$K$71 -> 0.2462263
S85: اشتراكات المطور | T85: =Summary!K64+Summary!K65 -> 11100000 | U85: =T85/Summary!K71 -> 0.050285392
S86: اشتراكات نقدية | T86: =Summary!K62+Summary!K63+Summary!K66 -> 97309600 | U86: =T86/Summary!K71 -> 0.44083346
T88: =S83 -> مصادر أخرى | U88: =T83 -> 57978444
T89: =S84 -> التمويل | U89: =T84 -> 54352006
T90: الملكية | U90: =T85+T86 -> 108409600
C94: Cost Breakdown | توزيع التكلفة | J94: SR/B.sqm | K94: SR
C95: إجمالي تكلفة الأرض بعد الضرائب - (Tota Land Cost After TAX) | J95: =J96+J97+J98+J99 -> 5980.2824 | K95: =K96+K97+K98+K99 -> 49134000
C96: (Land Cost Before TAX) - تكلفة الأرض قبل الضرائب | J96: =K96/$I$13 -> 5842.259 | K96: =Study!E40 -> 48000000
C97: (Commissions) - السعي | J97: =K97/$I$13 -> 43.816943 | K97: =Study!G40 -> 360000
C98: (Commission Tax) - ضريبة السعي | J98: =K98/$I$13 -> 6.5725414 | K98: =Study!H40 -> 54000
C99: ضريبة التصرفات العقارية - (RETT) | J99: =K99/$I$13 -> 87.633885 | K99: =Study!F40 -> 720000
C100: ------------------------------------------------------------------
C101: (Development) - التطوير | J101: =J102+J103+J104 -> 3494.6481 | K101: =K102+K103+K104 -> 1.1112855e+08
C102: (Hard Cost - Construction) - تكلفة البناء | J102: =K102/$I$14 -> 2461.2105 | K102: =Study!C15 -> 78265608
C103: Soft Costs (Fees,Consultants, Insurance, Permits, Overheads etc) - التكاليف الأخرى | J103: =K103/$I$14 -> 664.25604 | K103: =Study!C98-Study!C94-Study!C96 -> 21123103
C104: =Study!D100 -> 0.15 | J104: =K104/$I$14 -> 369.18158 | K104: =Study!C100 -> 11739841
C105: ------------------------------------------------------------------
C106: Marketing (RASF) - التسويق | J106: =K106/I15 -> 4.7329791 | K106: =Study!C94+Study!C96 -> 46954.911
C107: ------------------------------------------------------------------
C108: إجمالي تكاليف التمويل - (Total Financing Costs) | J108: =J110+J109 -> 224.5907 | K108: =K109+K110 -> 7141903.3
C109: =Study!C188 -> 0.073 | J109: =K109/$I$14 -> 216.04469 | K109: =-Study!E188 -> 6870143.2
C110: =Study!C189 -> 0.005 | J110: =K110/$I$14 -> 8.5460096 | K110: =-Study!F248 -> 271760.03
C111: ------------------------------------------------------------------
C112: (TotaI Fund expenses) - إجمالي تكاليف الصندوق | J112: =J113+J114 -> 332.54515 | K112: =K113+K114 -> 10574816
C113: رسوم الصندوق - (Fund fees) | J113: =K113/$I$14 -> 289.77737 | K113: =Study!C101 -> 9214816
C114: التكاليف الأخرى للصندوق - (Other costs) | J114: =K114/$I$14 -> 42.76778 | K114: =Study!C102 -> 1360000
C115: ------------------------------------------------------------------
C141: Total Costs - إجمالي التكاليف | J141: =K141/I14 -> 665.73263 | K141: =Study!C98 -> 21170058
S144: البند | T144: القيمة
S145: التسوير | T145: =Study!C82 -> 534040
S146: الحفر والمسح والاختبار | T146: =Study!C83 -> 2835360
S147: التأمين | T147: =Study!C84 -> 1330515.3
S148: الرخصة | T148: =Study!C85 -> 62830.56
S149: التصميم | T149: =Study!C86 -> 3913280.4
S150: أثاث الوحدات الفندقية | T150: =Study!C87 -> 6150000
S151: أثاث الوحدات | T151: =Study!C88 -> 0
S152: رسوم الكهرباء | T152: =Study!C89 -> 912500
S153: رسوم الماء وصرف الصحي | T153: =Study!C90 -> 984000
S154: الفرز | T154: =Study!C91 -> 18000
S155: الصيانة و التشغيل | T155: =Study!C92 -> 299000
S156: الاحتياطي | T156: =Study!C93 -> 1173984.1
... S160: الإشراف الهندسي | T160: =Study!C97 -> 1956640.2
C164: Fund Revenue | إيرادات الصندوق | K164: SR
C165: البيع المباشر (Direct Sale) | K165: =Study!C183 -> 0 | S165: حجم التمويل للفترة | T165: =Study!F242 -> 0 | U165: =Study!G242 -> 0 | V165: =Study!H242 -> 0 | W165: =Study!I242 -> 0 | X165: =Study!J242 -> 0 | Y165: =Study!K242 -> 0 | Z165: =Study!L242 -> 2552006 | AA165: =Study!M242 -> 3352006 | ... AQ165: =Study!AC242 -> 0
C166: البيع على الخارطة (Off-Plan Sale) | K166: =Study!C180 -> 46486957 | S166: أصل التمويل | T166: =Study!F244 -> 0 | U166: =Study!G244 -> 0 | V166: =Study!H244 -> 0 | W166: =Study!I244 -> 0 | X166: =Study!J244 -> 0 | Y166: =Study!K244 -> 0 | Z166: =Study!L244 -> 2552006 | AA166: =Study!M244 -> 800000 | ... AQ166: =Study!AC244 -> 0
...
